Workbook
Name OLE_LINK4: 'Operacoes 22.23'!$E$21
Name OLE_LINK4: 'Operacoes 23.24'!$E$22
Name OLE_LINK7: 'Operacoes 22.23'!$E$19
Name OLE_LINK7: 'Operacoes 23.24'!$E$20

Sheet Operacoes 22.23
B2: Tabela - Área plantada por cultura safra 2021/22 x 2022/23 | L2: Table - Planted Area by Crop 2021/22 vs. 2022/23 crop years
B3: Mix de culturas | C3: Área plantada | D3: Área Plantada | E3: Participação | F3: Δ% | L3: Crop Mix | M3: Planted Area | N3: Planted Area | O3: Share | P3: Δ%
C4: 2021/22 | D4: 2022/23 | E4: 2022/23 | M4: 2021/22 | N4: 2022/23 | O4: 2022/23
C5: ------------------ha ------------------ | E5: % | M5: ------------------ha ------------------ | O5: %
B6: Algodão em pluma | C6: 176985 | D6: 162243 | E6: =D6/$D$12 -> 0.24057955 | F6: =D6/C6-1 -> -0.083295195 | L6: Cotton lint | M6: =IF(C6<0,CONCATENATE("(",SUBSTITUTE(SUBSTITUTE(SUBSTITUTE(SUBSTITUTE(TEXT(C6,"#.##0"),",","*"),".",","),"*","."),"-",""),")"),IF(C6=0," -",SUBSTITUTE(SUBSTITUTE(SUBSTITUTE(TEXT(C6,"#.##0"),",","*"),".",","),"*","."))) -> 176,985 | N6: =IF(D6<0,CONCATENATE("(",SUBSTITUTE(SUBSTITUTE(SUBSTITUTE(SUBSTITUTE(TEXT(D6,"#.##0"),",","*"),".",","),"*","."),"-",""),")"),IF(D6=0," -",SUBSTITUTE(SUBSTITUTE(SUBSTITUTE(TEXT(D6,"#.##0"),",","*"),".",","),"*","."))) -> 162,243 | O6: =SUBSTITUTE(TEXT(E6,"0,0%"),",",".") -> 24.1% | P6: =SUBSTITUTE(TEXT(F6,"0,0%"),",",".") -> -8.3%
B7: Algodão em pluma 1ª safra | C7: 86357 | D7: 85823 | E7: =D7/$D$12 -> 0.12726132 | F7: =D7/C7-1 -> -0.0061836331 | L7: Cotton lint 1st crop | M7: =IF(C7<0,CONCATENATE("(",SUBSTITUTE(SUBSTITUTE(SUBSTITUTE(SUBSTITUTE(TEXT(C7,"#.##0"),",","*"),".",","),"*","."),"-",""),")"),IF(C7=0," -",SUBSTITUTE(SUBSTITUTE(SUBSTITUTE(TEXT(C7,"#.##0"),",","*"),".",","),"*","."))) -> 86,357 | N7: =IF(D7<0,CONCATENATE("(",SUBSTITUTE(SUBSTITUTE(SUBSTITUTE(SUBSTITUTE(TEXT(D7,"#.##0"),",","*"),".",","),"*","."),"-",""),")"),IF(D7=0," -",SUBSTITUTE(SUBSTITUTE(SUBSTITUTE(TEXT(D7,"#.##0"),",","*"),".",","),"*","."))) -> 85,823 | O7: =SUBSTITUTE(TEXT(E7,"0,0%"),",",".") -> 12.7% | P7: =SUBSTITUTE(TEXT(F7,"0,0%"),",",".") -> -0.6%
B8: Algodão em pluma 2ª safra | C8: 90628 | D8: 76420 | E8: =D8/$D$12 -> 0.11331823 | F8: =D8/C8-1 -> -0.15677274 | L8: Cotton lint 2nd crop | M8: =IF(C8<0,CONCATENATE("(",SUBSTITUTE(SUBSTITUTE(SUBSTITUTE(SUBSTITUTE(TEXT(C8,"#.##0"),",","*"),".",","),"*","."),"-",""),")"),IF(C8=0," -",SUBSTITUTE(SUBSTITUTE(SUBSTITUTE(TEXT(C8,"#.##0"),",","*"),".",","),"*","."))) -> 90,628 | N8: =IF(D8<0,CONCATENATE("(",SUBSTITUTE(SUBSTITUTE(SUBSTITUTE(SUBSTITUTE(TEXT(D8,"#.##0"),",","*"),".",","),"*","."),"-",""),")"),IF(D8=0," -",SUBSTITUTE(SUBSTITUTE(SUBSTITUTE(TEXT(D8,"#.##0"),",","*"),".",","),"*","."))) -> 76,420 | O8: =SUBSTITUTE(TEXT(E8,"0,0%"),",",".") -> 11.3% | P8: =SUBSTITUTE(TEXT(F8,"0,0%"),",",".") -> -15.7%
B9: Soja (Comercial + Semente) | C9: 334891 | D9: 346941 | E9: =D9/$D$12 -> 0.51445616 | F9: =D9/C9-1 -> 0.035981857 | L9: Soybean (Commercial + Seed) | M9: =IF(C9<0,CONCATENATE("(",SUBSTITUTE(SUBSTITUTE(SUBSTITUTE(SUBSTITUTE(TEXT(C9,"#.##0"),",","*"),".",","),"*","."),"-",""),")"),IF(C9=0," -",SUBSTITUTE(SUBSTITUTE(SUBSTITUTE(TEXT(C9,"#.##0"),",","*"),".",","),"*","."))) -> 334,891 | N9: =IF(D9<0,CONCATENATE("(",SUBSTITUTE(SUBSTITUTE(SUBSTITUTE(SUBSTITUTE(TEXT(D9,"#.##0"),",","*"),".",","),"*","."),"-",""),")"),IF(D9=0," -",SUBSTITUTE(SUBSTITUTE(SUBSTITUTE(TEXT(D9,"#.##0"),",","*"),".",","),"*","."))) -> 346,941 | O9: =SUBSTITUTE(TEXT(E9,"0,0%"),",",".") -> 51.4% | P9: =SUBSTITUTE(TEXT(F9,"0,0%"),",",".") -> 3.6%
B10: Milho 2ª safra | C10: 121633 | D10: 137585 | E10: =D10/$D$12 -> 0.20401581 | F10: =D10/C10-1 -> 0.13114862 | L10: Corn 2nd crop | M10: =IF(C10<0,CONCATENATE("(",SUBSTITUTE(SUBSTITUTE(SUBSTITUTE(SUBSTITUTE(TEXT(C10,"#.##0"),",","*"),".",","),"*","."),"-",""),")"),IF(C10=0," -",SUBSTITUTE(SUBSTITUTE(SUBSTITUTE(TEXT(C10,"#.##0"),",","*"),".",","),"*","."))) -> 121,633 | N10: =IF(D10<0,CONCATENATE("(",SUBSTITUTE(SUBSTITUTE(SUBSTITUTE(SUBSTITUTE(TEXT(D10,"#.##0"),",","*"),".",","),"*","."),"-",""),")"),IF(D10=0," -",SUBSTITUTE(SUBSTITUTE(SUBSTITUTE(TEXT(D10,"#.##0"),",","*"),".",","),"*","."))) -> 137,585 | O10: =SUBSTITUTE(TEXT(E10,"0,0%"),",",".") -> 20.4% | P10: =SUBSTITUTE(TEXT(F10,"0,0%"),",",".") -> 13.1%
B11: Outras culturas (1) | C11: 38437 | D11: 27615 | E11: =D11/$D$12 -> 0.04094848 | F11: =D11/C11-1 -> -0.28155163 | L11: Other Crops (1) | M11: =IF(C11<0,CONCATENATE("(",SUBSTITUTE(SUBSTITUTE(SUBSTITUTE(SUBSTITUTE(TEXT(C11,"#.##0"),",","*"),".",","),"*","."),"-",""),")"),IF(C11=0," -",SUBSTITUTE(SUBSTITUTE(SUBSTITUTE(TEXT(C11,"#.##0"),",","*"),".",","),"*","."))) -> 38,437 | N11: =IF(D11<0,CONCATENATE("(",SUBSTITUTE(SUBSTITUTE(SUBSTITUTE(SUBSTITUTE(TEXT(D11,"#.##0"),",","*"),".",","),"*","."),"-",""),")"),IF(D11=0," -",SUBSTITUTE(SUBSTITUTE(SUBSTITUTE(TEXT(D11,"#.##0"),",","*"),".",","),"*","."))) -> 27,615 | O11: =SUBSTITUTE(TEXT(E11,"0,0%"),",",".") -> 4.1% | P11: =SUBSTITUTE(TEXT(F11,"0,0%"),",",".") -> -28.2%
B12: Área Total | C12: 671946 | D12: 674384 | E12: =D12/$D$12 -> 1 | F12: =D12/C12-1 -> 0.0036282677 | L12: Total Area | M12: =IF(C12<0,CONCATENATE("(",SUBSTITUTE(SUBSTITUTE(SUBSTITUTE(SUBSTITUTE(TEXT(C12,"#.##0"),",","*"),".",","),"*","."),"-",""),")"),IF(C12=0," -",SUBSTITUTE(SUBSTITUTE(SUBSTITUTE(TEXT(C12,"#.##0"),",","*"),".",","),"*","."))) -> 671,946 | N12: =IF(D12<0,CONCATENATE("(",SUBSTITUTE(SUBSTITUTE(SUBSTITUTE(SUBSTITUTE(TEXT(D12,"#.##0"),",","*"),".",","),"*","."),"-",""),")"),IF(D12=0," -",SUBSTITUTE(SUBSTITUTE(SUBSTITUTE(TEXT(D12,"#.##0"),",","*"),".",","),"*","."))) -> 674,384 | O12: =SUBSTITUTE(TEXT(E12,"0,0%"),",",".") -> 100.0% | P12: =SUBSTITUTE(TEXT(F12,"0,0%"),",",".") -> 0.4%
B13: (2) Outras Culturas (Semente de Braquiária 6.314,86 ha, Semente de Estilosantes 716,02 ha, Feijão 1.430,58 ha, Gergelim 2.494,26 ha, Semente de Milheto 8.786,01 ha, Milho 1ª Safra 1.133,88 ha, Milho Semente 667,46 ha, Pecuária 3.962,42 ha, Sorgo 1.041,77 ha e Trigo 1.067,74 ha) total 27.615,00 ha. | L13: (1) Other Crops (Brachiaria Seed 6,314.86 ha, Stylosanthes Seed 716.02 ha, Beans ,1.430.58 ha, Sesame 2.494,26 ha, MIllet Seed 8,786.01 ha, Corn 1st crop 1,133.88 ha, Corn Seed 667.46 ha, Cattle Herd 3,962.42 ha, Sorghum 1,041.77 ha and Wheat 1,067.74 ha) total 27,615 ha.
B15: Tabela - Produtividade Realizada Safra 2022/23 | L15: Table - Achieved Yields 2022/23 crop year
B16: Produtividade (kg/ha) | C16: Safra 2021/22 | D16: Safra 2022/23 | E16: Safra 2022/23 | F16: ∆% | G16: ∆% | L16: Yield (kg/ha) | M16: 2021/22 Crop Year | N16: 2022/23 Crop Year | O16: 2022/23 Crop Year | P16: ∆% | Q16: ∆%
C17: Realizado (a) | D17: Orçado (b) | E17: Realizado (c) | F17: (c) x (a) | G17: (c) x (b) | M17: Achieved (a) | N17: Budget (b) | O17: Forecast(c) | P17: (c) x (a) | Q17: (c) x (b)
B18: Algodão em pluma 1ª safra | C18: 1682 | D18: 1927 | E18: 2000 | F18: 0.189 | G18: 0.038 | L18: Cotton lint 1st crop | M18: =IF(C18<0,CONCATENATE("(",SUBSTITUTE(SUBSTITUTE(SUBSTITUTE(SUBSTITUTE(TEXT(C18,"#.##0"),",","*"),".",","),"*","."),"-",""),")"),IF(C18=0," -",SUBSTITUTE(SUBSTITUTE(SUBSTITUTE(TEXT(C18,"#.##0"),",","*"),".",","),"*","."))) -> 1,682 | N18: =IF(D18<0,CONCATENATE("(",SUBSTITUTE(SUBSTITUTE(SUBSTITUTE(SUBSTITUTE(TEXT(D18,"#.##0"),",","*"),".",","),"*","."),"-",""),")"),IF(D18=0," -",SUBSTITUTE(SUBSTITUTE(SUBSTITUTE(TEXT(D18,"#.##0"),",","*"),".",","),"*","."))) -> 1,927 | O18: =IF(E18<0,CONCATENATE("(",SUBSTITUTE(SUBSTITUTE(SUBSTITUTE(SUBSTITUTE(TEXT(E18,"#.##0"),",","*"),".",","),"*","."),"-",""),")"),IF(E18=0," -",SUBSTITUTE(SUBSTITUTE(SUBSTITUTE(TEXT(E18,"#.##0"),",","*"),".",","),"*","."))) -> 2,000 | P18: =SUBSTITUTE(TEXT(F18,"0,0%"),",",".") -> 18.9% | Q18: =SUBSTITUTE(TEXT(G18,"0,0%"),",",".") -> 3.8%
B19: Algodão em pluma 2ª safra | C19: 1305 | D19: 1839 | E19: 2037 | F19: 0.561 | G19: 0.108 | L19: Cotton lint 2nd crop | M19: =IF(C19<0,CONCATENATE("(",SUBSTITUTE(SUBSTITUTE(SUBSTITUTE(SUBSTITUTE(TEXT(C19,"#.##0"),",","*"),".",","),"*","."),"-",""),")"),IF(C19=0," -",SUBSTITUTE(SUBSTITUTE(SUBSTITUTE(TEXT(C19,"#.##0"),",","*"),".",","),"*","."))) -> 1,305 | N19: =IF(D19<0,CONCATENATE("(",SUBSTITUTE(SUBSTITUTE(SUBSTITUTE(SUBSTITUTE(TEXT(D19,"#.##0"),",","*"),".",","),"*","."),"-",""),")"),IF(D19=0," -",SUBSTITUTE(SUBSTITUTE(SUBSTITUTE(TEXT(D19,"#.##0"),",","*"),".",","),"*","."))) -> 1,839 | O19: =IF(E19<0,CONCATENATE("(",SUBSTITUTE(SUBSTITUTE(SUBSTITUTE(SUBSTITUTE(TEXT(E19,"#.##0"),",","*"),".",","),"*","."),"-",""),")"),IF(E19=0," -",SUBSTITUTE(SUBSTITUTE(SUBSTITUTE(TEXT(E19,"#.##0"),",","*"),".",","),"*","."))) -> 2,037 | P19: =SUBSTITUTE(TEXT(F19,"0,0%"),",",".") -> 56.1% | Q19: =SUBSTITUTE(TEXT(G19,"0,0%"),",",".") -> 10.8%
B20: Caroço de algodão | C20: 1833 | D20: 2372 | E20: 2491 | F20: 0.359 | G20: 0.05 | L20: Cotton seed | M20: =IF(C20<0,CONCATENATE("(",SUBSTITUTE(SUBSTITUTE(SUBSTITUTE(SUBSTITUTE(TEXT(C20,"#.##0"),",","*"),".",","),"*","."),"-",""),")"),IF(C20=0," -",SUBSTITUTE(SUBSTITUTE(SUBSTITUTE(TEXT(C20,"#.##0"),",","*"),".",","),"*","."))) -> 1,833 | N20: =IF(D20<0,CONCATENATE("(",SUBSTITUTE(SUBSTITUTE(SUBSTITUTE(SUBSTITUTE(TEXT(D20,"#.##0"),",","*"),".",","),"*","."),"-",""),")"),IF(D20=0," -",SUBSTITUTE(SUBSTITUTE(SUBSTITUTE(TEXT(D20,"#.##0"),",","*"),".",","),"*","."))) -> 2,372 | O20: =IF(E20<0,CONCATENATE("(",SUBSTITUTE(SUBSTITUTE(SUBSTITUTE(SUBSTITUTE(TEXT(E20,"#.##0"),",","*"),".",","),"*","."),"-",""),")"),IF(E20=0," -",SUBSTITUTE(SUBSTITUTE(SUBSTITUTE(TEXT(E20,"#.##0"),",","*"),".",","),"*","."))) -> 2,491 | P20: =SUBSTITUTE(TEXT(F20,"0,0%"),",",".") -> 35.9% | Q20: =SUBSTITUTE(TEXT(G20,"0,0%"),",",".") -> 5.0%
B21: Soja (Comercial + Semente) | C21: 3974 | D21: 3918 | E21: 3904 | F21: -0.018 | G21: -0.004 | L21: Soybean (Commercial + Seed) | M21: =IF(C21<0,CONCATENATE("(",SUBSTITUTE(SUBSTITUTE(SUBSTITUTE(SUBSTITUTE(TEXT(C21,"#.##0"),",","*"),".",","),"*","."),"-",""),")"),IF(C21=0," -",SUBSTITUTE(SUBSTITUTE(SUBSTITUTE(TEXT(C21,"#.##0"),",","*"),".",","),"*","."))) -> 3,974 | N21: =IF(D21<0,CONCATENATE("(",SUBSTITUTE(SUBSTITUTE(SUBSTITUTE(SUBSTITUTE(TEXT(D21,"#.##0"),",","*"),".",","),"*","."),"-",""),")"),IF(D21=0," -",SUBSTITUTE(SUBSTITUTE(SUBSTITUTE(TEXT(D21,"#.##0"),",","*"),".",","),"*","."))) -> 3,918 | O21: =IF(E21<0,CONCATENATE("(",SUBSTITUTE(SUBSTITUTE(SUBSTITUTE(SUBSTITUTE(TEXT(E21,"#.##0"),",","*"),".",","),"*","."),"-",""),")"),IF(E21=0," -",SUBSTITUTE(SUBSTITUTE(SUBSTITUTE(TEXT(E21,"#.##0"),",","*"),".",","),"*","."))) -> 3,904 | P21: =SUBSTITUTE(TEXT(F21,"0,0%"),",",".") -> -1.8% | Q21: =SUBSTITUTE(TEXT(G21,"0,0%"),",",".") -> -0.4%
B22: Milho 2ª safra | C22: 6303 | D22: 7685 | E22: 7708 | F22: =E22/C22-1 -> 0.22290973 | G22: 0.003 | L22: Corn 2nd crop | M22: =IF(C22<0,CONCATENATE("(",SUBSTITUTE(SUBSTITUTE(SUBSTITUTE(SUBSTITUTE(TEXT(C22,"#.##0"),",","*"),".",","),"*","."),"-",""),")"),IF(C22=0," -",SUBSTITUTE(SUBSTITUTE(SUBSTITUTE(TEXT(C22,"#.##0"),",","*"),".",","),"*","."))) -> 6,303 | N22: =IF(D22<0,CONCATENATE("(",SUBSTITUTE(SUBSTITUTE(SUBSTITUTE(SUBSTITUTE(TEXT(D22,"#.##0"),",","*"),".",","),"*","."),"-",""),")"),IF(D22=0," -",SUBSTITUTE(SUBSTITUTE(SUBSTITUTE(TEXT(D22,"#.##0"),",","*"),".",","),"*","."))) -> 7,685 | O22: =IF(E22<0,CONCATENATE("(",SUBSTITUTE(SUBSTITUTE(SUBSTITUTE(SUBSTITUTE(TEXT(E22,"#.##0"),",","*"),".",","),"*","."),"-",""),")"),IF(E22=0," -",SUBSTITUTE(SUBSTITUTE(SUBSTITUTE(TEXT(E22,"#.##0"),",","*"),".",","),"*","."))) -> 7,708 | P22: =SUBSTITUTE(TEXT(F22,"0,0%"),",",".") -> 22.3% | Q22: =SUBSTITUTE(TEXT(G22,"0,0%"),",",".") -> 0.3%
B25: Tabela - Custos Realizados Safra 2022/23 | L25: Table - Achieved Costs – 2022/23 Crop Year
B26: % | C26: Algodão | D26: Soja | E26: Milho | F26: Média Real. 2022/23 | G26: Média Real. 2021/22 | L26: % | M26: Cotton | N26: Soybean | O26: Corn | P26: Average Ach. 2022/23 | Q26: Average Ach 2021/22
B27: Custos Variáveis | C27: 82.8 | D27: 74.8 | E27: 81.5 | F27: 80.4 | G27: 79.6 | L27: Variable Costs | M27: 82.8 | N27: 74.8 | O27: 81.5 | P27: 80.4 | Q27: 79.6
B28: Sementes | C28: 8.5 | D28: 14.2 | E28: 18.4 | F28: 11.4 | G28: 12.7 | L28: Seeds | M28: 8.5 | N28: 14.2 | O28: 18.4 | P28: 11.4 | Q28: 12.7
B29: Fertilizantes | C29: 24.2 | D29: 15.5 | E29: 34 | F29: 23 | G29: 25.4 | L29: Fertilizers | M29: 24.2 | N29: 15.5 | O29: 34 | P29: 23 | Q29: 25.4
B30: Defensivos | C30: 24.7 | D30: 19.4 | E30: 13.3 | F30: 21.7 | G30: 18.8 | L30: Chemicals | M30: 24.7 | N30: 19.4 | O30: 13.3 | P30: 21.7 | Q30: 18.8
B31: Pulverização Aérea | C31: 1.9 | D31: 1.7 | E31: 1.5 | F31: 1.7 | G31: 1.3 | L31: Air Spraying | M31: 1.9 | N31: 1.7 | O31: 1.5 | P31: 1.7 | Q31: 1.3
B32: Combustíveis e lubrificantes | C32: 3.1 | D32: 5.3 | E32: 3.8 | F32: 3.8 | G32: 4.6 | L32: Fuels and Lubricants | M32: 3.1 | N32: 5.3 | O32: 3.8 | P32: 3.8 | Q32: 4.6
B33: Mão-de-obra | C33: 0.7 | D33: 0.7 | E33: 0.5 | F33: 0.7 | G33: 0.8 | L33: Labor | M33: 0.7 | N33: 0.7 | O33: 0.5 | P33: 0.7 | Q33: 0.8
B34: Beneficiamento | C34: 9 | D34: 3.8 | E34: 2.4 | F34: 6.7 | G34: 4.8 | L34: Ginning | M34: 9.0 | N34: 3.8 | O34: 2.4 | P34: 6.7 | Q34: 4.8
B35: Manutenção de máquinas e implementos | C35: 4.9 | D35: 4.8 | E35: 3.2 | F35: 4.6 | G35: 4.1 | L35: Maintenance | M35: 4.9 | N35: 4.8 | O35: 3.2 | P35: 4.6 | Q35: 4.1
B36: Outros | C36: 5.8 | D36: 9.5 | E36: 4.4 | F36: 6.7 | G36: 7.1 | L36: Others | M36: 5.8 | N36: 9.5 | O36: 4.4 | P36: 6.7 | Q36: 7.1
B37: Custos Fixos | C37: 17.2 | D37: 25.2 | E37: 18.5 | F37: 19.6 | G37: 20.4 | L37: Fixed Costs | M37: 17.2 | N37: 25.2 | O37: 18.5 | P37: 19.6 | Q37: 20.4
B38: Mão-de-obra | C38: 6.2 | D38: 8.1 | E38: 6.1 | F38: 6.7 | G38: 7.2 | L38: Labor | M38: 6.2 | N38: 8.1 | O38: 6.1 | P38: 6.7 | Q38: 7.2
B39: Depreciações e amortizações | C39: 3.6 | D39: 5.8 | E39: 3.8 | F39: 4.3 | G39: 4.4 | L39: Depreciation and amortizations | M39: 3.6 | N39: 5.8 | O39: 3.8 | P39: 4.3 | Q39: 4.4
B40: Depreciação do Direito de Uso -Arrendamentos | C40: 4.7 | D40: 7.6 | E40: 6 | F40: 5.7 | G40: 6.2 | L40: Right-of-Use Depreciation - Leasing | M40: 4.7 | N40: 7.6 | O40: 6 | P40: 5.7 | Q40: 6.2
B41: Outros | C41: 2.7 | D41: 3.6 | E41: 2.6 | F41: 2.9 | G41: 2.6 | L41: Others | M41: 2.7 | N41: 3.6 | O41: 2.6 | P41: 2.9 | Q41: 2.6
B43: Tabela - Custo de produção – Breakdown em R$ por hectare – Safra 2022/23 | L43: Table – Production Cost – Breakdown in % and R$ per hectare – 2022/23 Crop Year
B44: R$/ha | C44: Algodão Real. | D44: Algodão Real. | E44: Soja Real. | F44: Milho Real. | G44: Média Real. | H44: Média Real. | L44: R$/ha | M44: Cotton Achieved | N44: Cotton Achieved | O44: Soybean Achieved | P44: Corn Achieved | Q44: Average Achieved | R44: Average Achieved
C45: 1 ª safra | D45: 2ª safra | F45: 2ª Safra | G45: 2022/23 | H45: 2021/22 | M45: 1st crop | N45: 2nd crop | P45: 2nd crop | Q45: 2022/23 | R45: 2021/22
B46: Custos Variáveis | C46: =SUM(C47:C55) -> 12554.964 | D46: =SUM(D47:D55) -> 11324.556 | E46: =SUM(E47:E55) -> 4027.373 | F46: =SUM(F47:F55) -> 3966.605 | G46: =SUM(G47:G55) -> 6060.241 | H46: =SUM(H47:H55) -> 5065.744 | L46: Variable Costs | M46: =IF(C46<0,CONCATENATE("(",SUBSTITUTE(SUBSTITUTE(SUBSTITUTE(SUBSTITUTE(TEXT(C46,"#.##0"),",","*"),".",","),"*","."),"-",""),")"),IF(C46=0," -",SUBSTITUTE(SUBSTITUTE(SUBSTITUTE(TEXT(C46,"#.##0"),",","*"),".",","),"*","."))) -> 12,555 | N46: =IF(D46<0,CONCATENATE("(",SUBSTITUTE(SUBSTITUTE(SUBSTITUTE(SUBSTITUTE(TEXT(D46,"#.##0"),",","*"),".",","),"*","."),"-",""),")"),IF(D46=0," -",SUBSTITUTE(SUBSTITUTE(SUBSTITUTE(TEXT(D46,"#.##0"),",","*"),".",","),"*","."))) -> 11,325 | O46: =IF(E46<0,CONCATENATE("(",SUBSTITUTE(SUBSTITUTE(SUBSTITUTE(SUBSTITUTE(TEXT(E46,"#.##0"),",","*"),".",","),"*","."),"-",""),")"),IF(E46=0," -",SUBSTITUTE(SUBSTITUTE(SUBSTITUTE(TEXT(E46,"#.##0"),",","*"),".",","),"*","."))) -> 4,027 | P46: =IF(F46<0,CONCATENATE("(",SUBSTITUTE(SUBSTITUTE(SUBSTITUTE(SUBSTITUTE(TEXT(F46,"#.##0"),",","*"),".",","),"*","."),"-",""),")"),IF(F46=0," -",SUBSTITUTE(SUBSTITUTE(SUBSTITUTE(TEXT(F46,"#.##0"),",","*"),".",","),"*","."))) -> 3,967 | Q46: =IF(G46<0,CONCATENATE("(",SUBSTITUTE(SUBSTITUTE(SUBSTITUTE(SUBSTITUTE(TEXT(G46,"#.##0"),",","*"),".",","),"*","."),"-",""),")"),IF(G46=0," -",SUBSTITUTE(SUBSTITUTE(SUBSTITUTE(TEXT(G46,"#.##0"),",","*"),".",","),"*","."))) -> 6,060 | R46: =IF(H46<0,CONCATENATE("(",SUBSTITUTE(SUBSTITUTE(SUBSTITUTE(SUBSTITUTE(TEXT(H46,"#.##0"),",","*"),".",","),"*","."),"-",""),")"),IF(H46=0," -",SUBSTITUTE(SUBSTITUTE(SUBSTITUTE(TEXT(H46,"#.##0"),",","*"),".",","),"*","."))) -> 5,066
B47: Sementes | C47: =C28*D$67/100 -> 1288.855 | D47: =C28*D$68/100 -> 1162.545 | E47: =D28*D$69/100 -> 763.534 | F47: =E28*D$70/100 -> 895.528 | G47: =F28*7547/100 -> 860.358 | H47: =G28*6364/100 -> 808.228 | L47: Seeds | M47: =IF(C47<0,CONCATENATE("(",SUBSTITUTE(SUBSTITUTE(SUBSTITUTE(SUBSTITUTE(TEXT(C47,"#.##0"),",","*"),".",","),"*","."),"-",""),")"),IF(C47=0," -",SUBSTITUTE(SUBSTITUTE(SUBSTITUTE(TEXT(C47,"#.##0"),",","*"),".",","),"*","."))) -> 1,289 | N47: =IF(D47<0,CONCATENATE("(",SUBSTITUTE(SUBSTITUTE(SUBSTITUTE(SUBSTITUTE(TEXT(D47,"#.##0"),",","*"),".",","),"*","."),"-",""),")"),IF(D47=0," -",SUBSTITUTE(SUBSTITUTE(SUBSTITUTE(TEXT(D47,"#.##0"),",","*"),".",","),"*","."))) -> 1,163 | O47: =IF(E47<0,CONCATENATE("(",SUBSTITUTE(SUBSTITUTE(SUBSTITUTE(SUBSTITUTE(TEXT(E47,"#.##0"),",","*"),".",","),"*","."),"-",""),")"),IF(E47=0," -",SUBSTITUTE(SUBSTITUTE(SUBSTITUTE(TEXT(E47,"#.##0"),",","*"),".",","),"*","."))) -> 764 | P47: =IF(F47<0,CONCATENATE("(",SUBSTITUTE(SUBSTITUTE(SUBSTITUTE(SUBSTITUTE(TEXT(F47,"#.##0"),",","*"),".",","),"*","."),"-",""),")"),IF(F47=0," -",SUBSTITUTE(SUBSTITUTE(SUBSTITUTE(TEXT(F47,"#.##0"),",","*"),".",","),"*","."))) -> 896 | Q47: =IF(G47<0,CONCATENATE("(",SUBSTITUTE(SUBSTITUTE(SUBSTITUTE(SUBSTITUTE(TEXT(G47,"#.##0"),",","*"),".",","),"*","."),"-",""),")"),IF(G47=0," -",SUBSTITUTE(SUBSTITUTE(SUBSTITUTE(TEXT(G47,"#.##0"),",","*"),".",","),"*","."))) -> 860 | R47: =IF(H47<0,CONCATENATE("(",SUBSTITUTE(SUBSTITUTE(SUBSTITUTE(SUBSTITUTE(TEXT(H47,"#.##0"),",","*"),".",","),"*","."),"-",""),")"),IF(H47=0," -",SUBSTITUTE(SUBSTITUTE(SUBSTITUTE(TEXT(H47,"#.##0"),",","*"),".",","),"*","."))) -> 808
B48: Fertilizantes | C48: =C29*D$67/100 -> 3669.446 | D48: =C29*D$68/100 -> 3309.834 | E48: =D29*D$69/100 -> 833.435 | F48: =E29*D$70/100 -> 1654.78 | G48: =F29*7547/100 -> 1735.81 | H48: =G29*6364/100 -> 1616.456 | L48: Fertilizers | M48: =IF(C48<0,CONCATENATE("(",SUBSTITUTE(SUBSTITUTE(SUBSTITUTE(SUBSTITUTE(TEXT(C48,"#.##0"),",","*"),".",","),"*","."),"-",""),")"),IF(C48=0," -",SUBSTITUTE(SUBSTITUTE(SUBSTITUTE(TEXT(C48,"#.##0"),",","*"),".",","),"*","."))) -> 3,669 | N48: =IF(D48<0,CONCATENATE("(",SUBSTITUTE(SUBSTITUTE(SUBSTITUTE(SUBSTITUTE(TEXT(D48,"#.##0"),",","*"),".",","),"*","."),"-",""),")"),IF(D48=0," -",SUBSTITUTE(SUBSTITUTE(SUBSTITUTE(TEXT(D48,"#.##0"),",","*"),".",","),"*","."))) -> 3,310 | O48: =IF(E48<0,CONCATENATE("(",SUBSTITUTE(SUBSTITUTE(SUBSTITUTE(SUBSTITUTE(TEXT(E48,"#.##0"),",","*"),".",","),"*","."),"-",""),")"),IF(E48=0," -",SUBSTITUTE(SUBSTITUTE(SUBSTITUTE(TEXT(E48,"#.##0"),",","*"),".",","),"*","."))) -> 833 | P48: =IF(F48<0,CONCATENATE("(",SUBSTITUTE(SUBSTITUTE(SUBSTITUTE(SUBSTITUTE(TEXT(F48,"#.##0"),",","*"),".",","),"*","."),"-",""),")"),IF(F48=0," -",SUBSTITUTE(SUBSTITUTE(SUBSTITUTE(TEXT(F48,"#.##0"),",","*"),".",","),"*","."))) -> 1,655 | Q48: =IF(G48<0,CONCATENATE("(",SUBSTITUTE(SUBSTITUTE(SUBSTITUTE(SUBSTITUTE(TEXT(G48,"#.##0"),",","*"),".",","),"*","."),"-",""),")"),IF(G48=0," -",SUBSTITUTE(SUBSTITUTE(SUBSTITUTE(TEXT(G48,"#.##0"),",","*"),".",","),"*","."))) -> 1,736 | R48: =IF(H48<0,CONCATENATE("(",SUBSTITUTE(SUBSTITUTE(SUBSTITUTE(SUBSTITUTE(TEXT(H48,"#.##0"),",","*"),".",","),"*","."),"-",""),")"),IF(H48=0," -",SUBSTITUTE(SUBSTITUTE(SUBSTITUTE(TEXT(H48,"#.##0"),",","*"),".",","),"*","."))) -> 1,616
B49: Defensivos | C49: =C30*D$67/100 -> 3745.261 | D49: =C30*D$68/100 -> 3378.219 | E49: =D30*D$69/100 -> 1043.138 | F49: =E30*D$70/100 -> 647.311 | G49: =F30*7547/100 -> 1637.699 | H49: =G30*6364/100 -> 1196.432 | L49: Crop protection | M49: =IF(C49<0,CONCATENATE("(",SUBSTITUTE(SUBSTITUTE(SUBSTITUTE(SUBSTITUTE(TEXT(C49,"#.##0"),",","*"),".",","),"*","."),"-",""),")"),IF(C49=0," -",SUBSTITUTE(SUBSTITUTE(SUBSTITUTE(TEXT(C49,"#.##0"),",","*"),".",","),"*","."))) -> 3,745 | N49: =IF(D49<0,CONCATENATE("(",SUBSTITUTE(SUBSTITUTE(SUBSTITUTE(SUBSTITUTE(TEXT(D49,"#.##0"),",","*"),".",","),"*","."),"-",""),")"),IF(D49=0," -",SUBSTITUTE(SUBSTITUTE(SUBSTITUTE(TEXT(D49,"#.##0"),",","*"),".",","),"*","."))) -> 3,378 | O49: =IF(E49<0,CONCATENATE("(",SUBSTITUTE(SUBSTITUTE(SUBSTITUTE(SUBSTITUTE(TEXT(E49,"#.##0"),",","*"),".",","),"*","."),"-",""),")"),IF(E49=0," -",SUBSTITUTE(SUBSTITUTE(SUBSTITUTE(TEXT(E49,"#.##0"),",","*"),".",","),"*","."))) -> 1,043 | P49: =IF(F49<0,CONCATENATE("(",SUBSTITUTE(SUBSTITUTE(SUBSTITUTE(SUBSTITUTE(TEXT(F49,"#.##0"),",","*"),".",","),"*","."),"-",""),")"),IF(F49=0," -",SUBSTITUTE(SUBSTITUTE(SUBSTITUTE(TEXT(F49,"#.##0"),",","*"),".",","),"*","."))) -> 647 | Q49: =IF(G49<0,CONCATENATE("(",SUBSTITUTE(SUBSTITUTE(SUBSTITUTE(SUBSTITUTE(TEXT(G49,"#.##0"),",","*"),".",","),"*","."),"-",""),")"),IF(G49=0," -",SUBSTITUTE(SUBSTITUTE(SUBSTITUTE(TEXT(G49,"#.##0"),",","*"),".",","),"*","."))) -> 1,638 | R49: =IF(H49<0,CONCATENATE("(",SUBSTITUTE(SUBSTITUTE(SUBSTITUTE(SUBSTITUTE(TEXT(H49,"#.##0"),",","*"),".",","),"*","."),"-",""),")"),IF(H49=0," -",SUBSTITUTE(SUBSTITUTE(SUBSTITUTE(TEXT(H49,"#.##0"),",","*"),".",","),"*","."))) -> 1,196
B50: Pulverização Aérea | C50: =C31*D$67/100 -> 288.097 | D50: =C31*D$68/100 -> 259.863 | E50: =D31*D$69/100 -> 91.409 | F50: =E31*D$70/100 -> 73.005 | G50: =F31*7547/100 -> 128.299 | H50: =G31*6364/100 -> 82.732 | L50: Aerial Spraying | M50: =IF(C50<0,CONCATENATE("(",SUBSTITUTE(SUBSTITUTE(SUBSTITUTE(SUBSTITUTE(TEXT(C50,"#.##0"),",","*"),".",","),"*","."),"-",""),")"),IF(C50=0," -",SUBSTITUTE(SUBSTITUTE(SUBSTITUTE(TEXT(C50,"#.##0"),",","*"),".",","),"*","."))) -> 288 | N50: =IF(D50<0,CONCATENATE("(",SUBSTITUTE(SUBSTITUTE(SUBSTITUTE(SUBSTITUTE(TEXT(D50,"#.##0"),",","*"),".",","),"*","."),"-",""),")"),IF(D50=0," -",SUBSTITUTE(SUBSTITUTE(SUBSTITUTE(TEXT(D50,"#.##0"),",","*"),".",","),"*","."))) -> 260 | O50: =IF(E50<0,CONCATENATE("(",SUBSTITUTE(SUBSTITUTE(SUBSTITUTE(SUBSTITUTE(TEXT(E50,"#.##0"),",","*"),".",","),"*","."),"-",""),")"),IF(E50=0," -",SUBSTITUTE(SUBSTITUTE(SUBSTITUTE(TEXT(E50,"#.##0"),",","*"),".",","),"*","."))) -> 91 | P50: =IF(F50<0,CONCATENATE("(",SUBSTITUTE(SUBSTITUTE(SUBSTITUTE(SUBSTITUTE(TEXT(F50,"#.##0"),",","*"),".",","),"*","."),"-",""),")"),IF(F50=0," -",SUBSTITUTE(SUBSTITUTE(SUBSTITUTE(TEXT(F50,"#.##0"),",","*"),".",","),"*","."))) -> 73 | Q50: =IF(G50<0,CONCATENATE("(",SUBSTITUTE(SUBSTITUTE(SUBSTITUTE(SUBSTITUTE(TEXT(G50,"#.##0"),",","*"),".",","),"*","."),"-",""),")"),IF(G50=0," -",SUBSTITUTE(SUBSTITUTE(SUBSTITUTE(TEXT(G50,"#.##0"),",","*"),".",","),"*","."))) -> 128 | R50: =IF(H50<0,CONCATENATE("(",SUBSTITUTE(SUBSTITUTE(SUBSTITUTE(SUBSTITUTE(TEXT(H50,"#.##0"),",","*"),".",","),"*","."),"-",""),")"),IF(H50=0," -",SUBSTITUTE(SUBSTITUTE(SUBSTITUTE(TEXT(H50,"#.##0"),",","*"),".",","),"*","."))) -> 83
B51: Combustíveis e lubrificantes | C51: =C32*D$67/100 -> 470.053 | D51: =C32*D$68/100 -> 423.987 | E51: =D32*D$69/100 -> 284.981 | F51: =E32*D$70/100 -> 184.946 | G51: =F32*7547/100 -> 286.786 | H51: =G32*6364/100 -> 292.744 | L51: Fuels and lubrificants | M51: =IF(C51<0,CONCATENATE("(",SUBSTITUTE(SUBSTITUTE(SUBSTITUTE(SUBSTITUTE(TEXT(C51,"#.##0"),",","*"),".",","),"*","."),"-",""),")"),IF(C51=0," -",SUBSTITUTE(SUBSTITUTE(SUBSTITUTE(TEXT(C51,"#.##0"),",","*"),".",","),"*","."))) -> 470 | N51: =IF(D51<0,CONCATENATE("(",SUBSTITUTE(SUBSTITUTE(SUBSTITUTE(SUBSTITUTE(TEXT(D51,"#.##0"),",","*"),".",","),"*","."),"-",""),")"),IF(D51=0," -",SUBSTITUTE(SUBSTITUTE(SUBSTITUTE(TEXT(D51,"#.##0"),",","*"),".",","),"*","."))) -> 424 | O51: =IF(E51<0,CONCATENATE("(",SUBSTITUTE(SUBSTITUTE(SUBSTITUTE(SUBSTITUTE(TEXT(E51,"#.##0"),",","*"),".",","),"*","."),"-",""),")"),IF(E51=0," -",SUBSTITUTE(SUBSTITUTE(SUBSTITUTE(TEXT(E51,"#.##0"),",","*"),".",","),"*","."))) -> 285 | P51: =IF(F51<0,CONCATENATE("(",SUBSTITUTE(SUBSTITUTE(SUBSTITUTE(SUBSTITUTE(TEXT(F51,"#.##0"),",","*"),".",","),"*","."),"-",""),")"),IF(F51=0," -",SUBSTITUTE(SUBSTITUTE(SUBSTITUTE(TEXT(F51,"#.##0"),",","*"),".",","),"*","."))) -> 185 | Q51: =IF(G51<0,CONCATENATE("(",SUBSTITUTE(SUBSTITUTE(SUBSTITUTE(SUBSTITUTE(TEXT(G51,"#.##0"),",","*"),".",","),"*","."),"-",""),")"),IF(G51=0," -",SUBSTITUTE(SUBSTITUTE(SUBSTITUTE(TEXT(G51,"#.##0"),",","*"),".",","),"*","."))) -> 287 | R51: =IF(H51<0,CONCATENATE("(",SUBSTITUTE(SUBSTITUTE(SUBSTITUTE(SUBSTITUTE(TEXT(H51,"#.##0"),",","*"),".",","),"*","."),"-",""),")"),IF(H51=0," -",SUBSTITUTE(SUBSTITUTE(SUBSTITUTE(TEXT(H51,"#.##0"),",","*"),".",","),"*","."))) -> 293
B52: Mão-de-obra | C52: =C33*D$67/100 -> 106.141 | D52: =C33*D$68/100 -> 95.739 | E52: =D33*D$69/100 -> 37.639 | F52: =E33*D$70/100 -> 24.335 | G52: =F33*7547/100 -> 52.829 | H52: =G33*6364/100 -> 50.912 | L52: Labor | M52: =IF(C52<0,CONCATENATE("(",SUBSTITUTE(SUBSTITUTE(SUBSTITUTE(SUBSTITUTE(TEXT(C52,"#.##0"),",","*"),".",","),"*","."),"-",""),")"),IF(C52=0," -",SUBSTITUTE(SUBSTITUTE(SUBSTITUTE(TEXT(C52,"#.##0"),",","*"),".",","),"*","."))) -> 106 | N52: =IF(D52<0,CONCATENATE("(",SUBSTITUTE(SUBSTITUTE(SUBSTITUTE(SUBSTITUTE(TEXT(D52,"#.##0"),",","*"),".",","),"*","."),"-",""),")"),IF(D52=0," -",SUBSTITUTE(SUBSTITUTE(SUBSTITUTE(TEXT(D52,"#.##0"),",","*"),".",","),"*","."))) -> 96 | O52: =IF(E52<0,CONCATENATE("(",SUBSTITUTE(SUBSTITUTE(SUBSTITUTE(SUBSTITUTE(TEXT(E52,"#.##0"),",","*"),".",","),"*","."),"-",""),")"),IF(E52=0," -",SUBSTITUTE(SUBSTITUTE(SUBSTITUTE(TEXT(E52,"#.##0"),",","*"),".",","),"*","."))) -> 38 | P52: =IF(F52<0,CONCATENATE("(",SUBSTITUTE(SUBSTITUTE(SUBSTITUTE(SUBSTITUTE(TEXT(F52,"#.##0"),",","*"),".",","),"*","."),"-",""),")"),IF(F52=0," -",SUBSTITUTE(SUBSTITUTE(SUBSTITUTE(TEXT(F52,"#.##0"),",","*"),".",","),"*","."))) -> 24 | Q52: =IF(G52<0,CONCATENATE("(",SUBSTITUTE(SUBSTITUTE(SUBSTITUTE(SUBSTITUTE(TEXT(G52,"#.##0"),",","*"),".",","),"*","."),"-",""),")"),IF(G52=0," -",SUBSTITUTE(SUBSTITUTE(SUBSTITUTE(TEXT(G52,"#.##0"),",","*"),".",","),"*","."))) -> 53 | R52: =IF(H52<0,CONCATENATE("(",SUBSTITUTE(SUBSTITUTE(SUBSTITUTE(SUBSTITUTE(TEXT(H52,"#.##0"),",","*"),".",","),"*","."),"-",""),")"),IF(H52=0," -",SUBSTITUTE(SUBSTITUTE(SUBSTITUTE(TEXT(H52,"#.##0"),",","*"),".",","),"*","."))) -> 51
B53: Beneficiamento | C53: =C34*D$67/100 -> 1364.67 | D53: =C34*D$68/100 -> 1230.93 | E53: =D34*D$69/100 -> 204.326 | F53: =E34*D$70/100 -> 116.808 | G53: =F34*7547/100 -> 505.649 | H53: =G34*6364/100 -> 305.472 | L53: Ginning | M53: =IF(C53<0,CONCATENATE("(",SUBSTITUTE(SUBSTITUTE(SUBSTITUTE(SUBSTITUTE(TEXT(C53,"#.##0"),",","*"),".",","),"*","."),"-",""),")"),IF(C53=0," -",SUBSTITUTE(SUBSTITUTE(SUBSTITUTE(TEXT(C53,"#.##0"),",","*"),".",","),"*","."))) -> 1,365 | N53: =IF(D53<0,CONCATENATE("(",SUBSTITUTE(SUBSTITUTE(SUBSTITUTE(SUBSTITUTE(TEXT(D53,"#.##0"),",","*"),".",","),"*","."),"-",""),")"),IF(D53=0," -",SUBSTITUTE(SUBSTITUTE(SUBSTITUTE(TEXT(D53,"#.##0"),",","*"),".",","),"*","."))) -> 1,231 | O53: =IF(E53<0,CONCATENATE("(",SUBSTITUTE(SUBSTITUTE(SUBSTITUTE(SUBSTITUTE(TEXT(E53,"#.##0"),",","*"),".",","),"*","."),"-",""),")"),IF(E53=0," -",SUBSTITUTE(SUBSTITUTE(SUBSTITUTE(TEXT(E53,"#.##0"),",","*"),".",","),"*","."))) -> 204 | P53: =IF(F53<0,CONCATENATE("(",SUBSTITUTE(SUBSTITUTE(SUBSTITUTE(SUBSTITUTE(TEXT(F53,"#.##0"),",","*"),".",","),"*","."),"-",""),")"),IF(F53=0," -",SUBSTITUTE(SUBSTITUTE(SUBSTITUTE(TEXT(F53,"#.##0"),",","*"),".",","),"*","."))) -> 117 | Q53: =IF(G53<0,CONCATENATE("(",SUBSTITUTE(SUBSTITUTE(SUBSTITUTE(SUBSTITUTE(TEXT(G53,"#.##0"),",","*"),".",","),"*","."),"-",""),")"),IF(G53=0," -",SUBSTITUTE(SUBSTITUTE(SUBSTITUTE(TEXT(G53,"#.##0"),",","*"),".",","),"*","."))) -> 506 | R53: =IF(H53<0,CONCATENATE("(",SUBSTITUTE(SUBSTITUTE(SUBSTITUTE(SUBSTITUTE(TEXT(H53,"#.##0"),",","*"),".",","),"*","."),"-",""),")"),IF(H53=0," -",SUBSTITUTE(SUBSTITUTE(SUBSTITUTE(TEXT(H53,"#.##0"),",","*"),".",","),"*","."))) -> 305
B54: Manutenção de máquinas e implementos | C54: =C35*D$67/100 -> 742.987 | D54: =C35*D$68/100 -> 670.173 | E54: =D35*D$69/100 -> 258.096 | F54: =E35*D$70/100 -> 155.744 | G54: =F35*7547/100 -> 347.162 | H54: =G35*6364/100 -> 260.924 | L54: Maintenance of machines and implements | M54: =IF(C54<0,CONCATENATE("(",SUBSTITUTE(SUBSTITUTE(SUBSTITUTE(SUBSTITUTE(TEXT(C54,"#.##0"),",","*"),".",","),"*","."),"-",""),")"),IF(C54=0," -",SUBSTITUTE(SUBSTITUTE(SUBSTITUTE(TEXT(C54,"#.##0"),",","*"),".",","),"*","."))) -> 743 | N54: =IF(D54<0,CONCATENATE("(",SUBSTITUTE(SUBSTITUTE(SUBSTITUTE(SUBSTITUTE(TEXT(D54,"#.##0"),",","*"),".",","),"*","."),"-",""),")"),IF(D54=0," -",SUBSTITUTE(SUBSTITUTE(SUBSTITUTE(TEXT(D54,"#.##0"),",","*"),".",","),"*","."))) -> 670 | O54: =IF(E54<0,CONCATENATE("(",SUBSTITUTE(SUBSTITUTE(SUBSTITUTE(SUBSTITUTE(TEXT(E54,"#.##0"),",","*"),".",","),"*","."),"-",""),")"),IF(E54=0," -",SUBSTITUTE(SUBSTITUTE(SUBSTITUTE(TEXT(E54,"#.##0"),",","*"),".",","),"*","."))) -> 258 | P54: =IF(F54<0,CONCATENATE("(",SUBSTITUTE(SUBSTITUTE(SUBSTITUTE(SUBSTITUTE(TEXT(F54,"#.##0"),",","*"),".",","),"*","."),"-",""),")"),IF(F54=0," -",SUBSTITUTE(SUBSTITUTE(SUBSTITUTE(TEXT(F54,"#.##0"),",","*"),".",","),"*","."))) -> 156 | Q54: =IF(G54<0,CONCATENATE("(",SUBSTITUTE(SUBSTITUTE(SUBSTITUTE(SUBSTITUTE(TEXT(G54,"#.##0"),",","*"),".",","),"*","."),"-",""),")"),IF(G54=0," -",SUBSTITUTE(SUBSTITUTE(SUBSTITUTE(TEXT(G54,"#.##0"),",","*"),".",","),"*","."))) -> 347 | R54: =IF(H54<0,CONCATENATE("(",SUBSTITUTE(SUBSTITUTE(SUBSTITUTE(SUBSTITUTE(TEXT(H54,"#.##0"),",","*"),".",","),"*","."),"-",""),")"),IF(H54=0," -",SUBSTITUTE(SUBSTITUTE(SUBSTITUTE(TEXT(H54,"#.##0"),",","*"),".",","),"*","."))) -> 261
B55: Outros | C55: =C36*D$67/100 -> 879.454 | D55: =C36*D$68/100 -> 793.266 | E55: =D36*D$69/100 -> 510.815 | F55: =E36*D$70/100 -> 214.148 | G55: =F36*7547/100 -> 505.649 | H55: =G36*6364/100 -> 451.844 | L55: Others | M55: =IF(C55<0,CONCATENATE("(",SUBSTITUTE(SUBSTITUTE(SUBSTITUTE(SUBSTITUTE(TEXT(C55,"#.##0"),",","*"),".",","),"*","."),"-",""),")"),IF(C55=0," -",SUBSTITUTE(SUBSTITUTE(SUBSTITUTE(TEXT(C55,"#.##0"),",","*"),".",","),"*","."))) -> 879 | N55: =IF(D55<0,CONCATENATE("(",SUBSTITUTE(SUBSTITUTE(SUBSTITUTE(SUBSTITUTE(TEXT(D55,"#.##0"),",","*"),".",","),"*","."),"-",""),")"),IF(D55=0," -",SUBSTITUTE(SUBSTITUTE(SUBSTITUTE(TEXT(D55,"#.##0"),",","*"),".",","),"*","."))) -> 793 | O55: =IF(E55<0,CONCATENATE("(",SUBSTITUTE(SUBSTITUTE(SUBSTITUTE(SUBSTITUTE(TEXT(E55,"#.##0"),",","*"),".",","),"*","."),"-",""),")"),IF(E55=0," -",SUBSTITUTE(SUBSTITUTE(SUBSTITUTE(TEXT(E55,"#.##0"),",","*"),".",","),"*","."))) -> 511 | P55: =IF(F55<0,CONCATENATE("(",SUBSTITUTE(SUBSTITUTE(SUBSTITUTE(SUBSTITUTE(TEXT(F55,"#.##0"),",","*"),".",","),"*","."),"-",""),")"),IF(F55=0," -",SUBSTITUTE(SUBSTITUTE(SUBSTITUTE(TEXT(F55,"#.##0"),",","*"),".",","),"*","."))) -> 214 | Q55: =IF(G55<0,CONCATENATE("(",SUBSTITUTE(SUBSTITUTE(SUBSTITUTE(SUBSTITUTE(TEXT(G55,"#.##0"),",","*"),".",","),"*","."),"-",""),")"),IF(G55=0," -",SUBSTITUTE(SUBSTITUTE(SUBSTITUTE(TEXT(G55,"#.##0"),",","*"),".",","),"*","."))) -> 506 | R55: =IF(H55<0,CONCATENATE("(",SUBSTITUTE(SUBSTITUTE(SUBSTITUTE(SUBSTITUTE(TEXT(H55,"#.##0"),",","*"),".",","),"*","."),"-",""),")"),IF(H55=0," -",SUBSTITUTE(SUBSTITUTE(SUBSTITUTE(TEXT(H55,"#.##0"),",","*"),".",","),"*","."))) -> 452
B56: Custos Fixos | C56: =SUM(C57:C60) -> 2608.036 | D56: =SUM(D57:D60) -> 2352.444 | E56: =SUM(E57:E60) -> 1349.627 | F56: =SUM(F57:F60) -> 881.895 | G56: =SUM(G57:G60) -> 1479.212 | H56: =SUM(H57:H60) -> 1298.256 | L56: Fixed Costs | M56: =IF(C56<0,CONCATENATE("(",SUBSTITUTE(SUBSTITUTE(SUBSTITUTE(SUBSTITUTE(TEXT(C56,"#.##0"),",","*"),".",","),"*","."),"-",""),")"),IF(C56=0," -",SUBSTITUTE(SUBSTITUTE(SUBSTITUTE(TEXT(C56,"#.##0"),",","*"),".",","),"*","."))) -> 2,608 | N56: =IF(D56<0,CONCATENATE("(",SUBSTITUTE(SUBSTITUTE(SUBSTITUTE(SUBSTITUTE(TEXT(D56,"#.##0"),",","*"),".",","),"*","."),"-",""),")"),IF(D56=0," -",SUBSTITUTE(SUBSTITUTE(SUBSTITUTE(TEXT(D56,"#.##0"),",","*"),".",","),"*","."))) -> 2,352 | O56: =IF(E56<0,CONCATENATE("(",SUBSTITUTE(SUBSTITUTE(SUBSTITUTE(SUBSTITUTE(TEXT(E56,"#.##0"),",","*"),".",","),"*","."),"-",""),")"),IF(E56=0," -",SUBSTITUTE(SUBSTITUTE(SUBSTITUTE(TEXT(E56,"#.##0"),",","*"),".",","),"*","."))) -> 1,350 | P56: =IF(F56<0,CONCATENATE("(",SUBSTITUTE(SUBSTITUTE(SUBSTITUTE(SUBSTITUTE(TEXT(F56,"#.##0"),",","*"),".",","),"*","."),"-",""),")"),IF(F56=0," -",SUBSTITUTE(SUBSTITUTE(SUBSTITUTE(TEXT(F56,"#.##0"),",","*"),".",","),"*","."))) -> 882 | Q56: =IF(G56<0,CONCATENATE("(",SUBSTITUTE(SUBSTITUTE(SUBSTITUTE(SUBSTITUTE(TEXT(G56,"#.##0"),",","*"),".",","),"*","."),"-",""),")"),IF(G56=0," -",SUBSTITUTE(SUBSTITUTE(SUBSTITUTE(TEXT(G56,"#.##0"),",","*"),".",","),"*","."))) -> 1,479 | R56: =IF(H56<0,CONCATENATE("(",SUBSTITUTE(SUBSTITUTE(SUBSTITUTE(SUBSTITUTE(TEXT(H56,"#.##0"),",","*"),".",","),"*","."),"-",""),")"),IF(H56=0," -",SUBSTITUTE(SUBSTITUTE(SUBSTITUTE(TEXT(H56,"#.##0"),",","*"),".",","),"*","."))) -> 1,298
B57: Mão-de-obra | C57: =C38*D$67/100 -> 940.106 | D57: =C38*D$68/100 -> 847.974 | E57: =D38*D$69/100 -> 435.537 | F57: =E38*E$70/100 -> 290.787 | G57: =F38*7547/100 -> 505.649 | H57: =G38*6364/100 -> 458.208 | L57: Labor | M57: =IF(C57<0,CONCATENATE("(",SUBSTITUTE(SUBSTITUTE(SUBSTITUTE(SUBSTITUTE(TEXT(C57,"#.##0"),",","*"),".",","),"*","."),"-",""),")"),IF(C57=0," -",SUBSTITUTE(SUBSTITUTE(SUBSTITUTE(TEXT(C57,"#.##0"),",","*"),".",","),"*","."))) -> 940 | N57: =IF(D57<0,CONCATENATE("(",SUBSTITUTE(SUBSTITUTE(SUBSTITUTE(SUBSTITUTE(TEXT(D57,"#.##0"),",","*"),".",","),"*","."),"-",""),")"),IF(D57=0," -",SUBSTITUTE(SUBSTITUTE(SUBSTITUTE(TEXT(D57,"#.##0"),",","*"),".",","),"*","."))) -> 848 | O57: =IF(E57<0,CONCATENATE("(",SUBSTITUTE(SUBSTITUTE(SUBSTITUTE(SUBSTITUTE(TEXT(E57,"#.##0"),",","*"),".",","),"*","."),"-",""),")"),IF(E57=0," -",SUBSTITUTE(SUBSTITUTE(SUBSTITUTE(TEXT(E57,"#.##0"),",","*"),".",","),"*","."))) -> 436 | P57: =IF(F57<0,CONCATENATE("(",SUBSTITUTE(SUBSTITUTE(SUBSTITUTE(SUBSTITUTE(TEXT(F57,"#.##0"),",","*"),".",","),"*","."),"-",""),")"),IF(F57=0," -",SUBSTITUTE(SUBSTITUTE(SUBSTITUTE(TEXT(F57,"#.##0"),",","*"),".",","),"*","."))) -> 291 | Q57: =IF(G57<0,CONCATENATE("(",SUBSTITUTE(SUBSTITUTE(SUBSTITUTE(SUBSTITUTE(TEXT(G57,"#.##0"),",","*"),".",","),"*","."),"-",""),")"),IF(G57=0," -",SUBSTITUTE(SUBSTITUTE(SUBSTITUTE(TEXT(G57,"#.##0"),",","*"),".",","),"*","."))) -> 506 | R57: =IF(H57<0,CONCATENATE("(",SUBSTITUTE(SUBSTITUTE(SUBSTITUTE(SUBSTITUTE(TEXT(H57,"#.##0"),",","*"),".",","),"*","."),"-",""),")"),IF(H57=0," -",SUBSTITUTE(SUBSTITUTE(SUBSTITUTE(TEXT(H57,"#.##0"),",","*"),".",","),"*","."))) -> 458
B58: Depreciações e amortizações | C58: =C39*D$67/100 -> 545.868 | D58: =C39*D$68/100 -> 492.372 | E58: =D39*D$69/100 -> 311.866 | F58: =E39*E$70/100 -> 181.146 | G58: =F39*7547/100 -> 324.521 | H58: =G39*6364/100 -> 280.016 | L58: Depreciation e amortization | M58: =IF(C58<0,CONCATENATE("(",SUBSTITUTE(SUBSTITUTE(SUBSTITUTE(SUBSTITUTE(TEXT(C58,"#.##0"),",","*"),".",","),"*","."),"-",""),")"),IF(C58=0," -",SUBSTITUTE(SUBSTITUTE(SUBSTITUTE(TEXT(C58,"#.##0"),",","*"),".",","),"*","."))) -> 546 | N58: =IF(D58<0,CONCATENATE("(",SUBSTITUTE(SUBSTITUTE(SUBSTITUTE(SUBSTITUTE(TEXT(D58,"#.##0"),",","*"),".",","),"*","."),"-",""),")"),IF(D58=0," -",SUBSTITUTE(SUBSTITUTE(SUBSTITUTE(TEXT(D58,"#.##0"),",","*"),".",","),"*","."))) -> 492 | O58: =IF(E58<0,CONCATENATE("(",SUBSTITUTE(SUBSTITUTE(SUBSTITUTE(SUBSTITUTE(TEXT(E58,"#.##0"),",","*"),".",","),"*","."),"-",""),")"),IF(E58=0," -",SUBSTITUTE(SUBSTITUTE(SUBSTITUTE(TEXT(E58,"#.##0"),",","*"),".",","),"*","."))) -> 312 | P58: =IF(F58<0,CONCATENATE("(",SUBSTITUTE(SUBSTITUTE(SUBSTITUTE(SUBSTITUTE(TEXT(F58,"#.##0"),",","*"),".",","),"*","."),"-",""),")"),IF(F58=0," -",SUBSTITUTE(SUBSTITUTE(SUBSTITUTE(TEXT(F58,"#.##0"),",","*"),".",","),"*","."))) -> 181 | Q58: =IF(G58<0,CONCATENATE("(",SUBSTITUTE(SUBSTITUTE(SUBSTITUTE(SUBSTITUTE(TEXT(G58,"#.##0"),",","*"),".",","),"*","."),"-",""),")"),IF(G58=0," -",SUBSTITUTE(SUBSTITUTE(SUBSTITUTE(TEXT(G58,"#.##0"),",","*"),".",","),"*","."))) -> 325 | R58: =IF(H58<0,CONCATENATE("(",SUBSTITUTE(SUBSTITUTE(SUBSTITUTE(SUBSTITUTE(TEXT(H58,"#.##0"),",","*"),".",","),"*","."),"-",""),")"),IF(H58=0," -",SUBSTITUTE(SUBSTITUTE(SUBSTITUTE(TEXT(H58,"#.##0"),",","*"),".",","),"*","."))) -> 280
B59: Amortização do Direito de Uso -Arrendamentos | C59: =C40*D$67/100 -> 712.661 | D59: =C40*D$68/100 -> 642.819 | E59: =D40*D$69/100 -> 408.652 | F59: =E40*E$70/100 -> 286.02 | G59: =F40*7547/100 -> 430.179 | H59: =G40*6364/100 -> 394.568 | L59: Right-of-Use Amortization - Leasing | M59: =IF(C59<0,CONCATENATE("(",SUBSTITUTE(SUBSTITUTE(SUBSTITUTE(SUBSTITUTE(TEXT(C59,"#.##0"),",","*"),".",","),"*","."),"-",""),")"),IF(C59=0," -",SUBSTITUTE(SUBSTITUTE(SUBSTITUTE(TEXT(C59,"#.##0"),",","*"),".",","),"*","."))) -> 713 | N59: =IF(D59<0,CONCATENATE("(",SUBSTITUTE(SUBSTITUTE(SUBSTITUTE(SUBSTITUTE(TEXT(D59,"#.##0"),",","*"),".",","),"*","."),"-",""),")"),IF(D59=0," -",SUBSTITUTE(SUBSTITUTE(SUBSTITUTE(TEXT(D59,"#.##0"),",","*"),".",","),"*","."))) -> 643 | O59: =IF(E59<0,CONCATENATE("(",SUBSTITUTE(SUBSTITUTE(SUBSTITUTE(SUBSTITUTE(TEXT(E59,"#.##0"),",","*"),".",","),"*","."),"-",""),")"),IF(E59=0," -",SUBSTITUTE(SUBSTITUTE(SUBSTITUTE(TEXT(E59,"#.##0"),",","*"),".",","),"*","."))) -> 409 | P59: =IF(F59<0,CONCATENATE("(",SUBSTITUTE(SUBSTITUTE(SUBSTITUTE(SUBSTITUTE(TEXT(F59,"#.##0"),",","*"),".",","),"*","."),"-",""),")"),IF(F59=0," -",SUBSTITUTE(SUBSTITUTE(SUBSTITUTE(TEXT(F59,"#.##0"),",","*"),".",","),"*","."))) -> 286 | Q59: =IF(G59<0,CONCATENATE("(",SUBSTITUTE(SUBSTITUTE(SUBSTITUTE(SUBSTITUTE(TEXT(G59,"#.##0"),",","*"),".",","),"*","."),"-",""),")"),IF(G59=0," -",SUBSTITUTE(SUBSTITUTE(SUBSTITUTE(TEXT(G59,"#.##0"),",","*"),".",","),"*","."))) -> 430 | R59: =IF(H59<0,CONCATENATE("(",SUBSTITUTE(SUBSTITUTE(SUBSTITUTE(SUBSTITUTE(TEXT(H59,"#.##0"),",","*"),".",","),"*","."),"-",""),")"),IF(H59=0," -",SUBSTITUTE(SUBSTITUTE(SUBSTITUTE(TEXT(H59,"#.##0"),",","*"),".",","),"*","."))) -> 395
B60: Outros | C60: =C41*D$67/100 -> 409.401 | D60: =C41*D$68/100 -> 369.279 | E60: =D41*D$69/100 -> 193.572 | F60: =E41*E$70/100 -> 123.942 | G60: =F41*7547/100 -> 218.863 | H60: =G41*6364/100 -> 165.464 | L60: Others | M60: =IF(C60<0,CONCATENATE("(",SUBSTITUTE(SUBSTITUTE(SUBSTITUTE(SUBSTITUTE(TEXT(C60,"#.##0"),",","*"),".",","),"*","."),"-",""),")"),IF(C60=0," -",SUBSTITUTE(SUBSTITUTE(SUBSTITUTE(TEXT(C60,"#.##0"),",","*"),".",","),"*","."))) -> 409 | N60: =IF(D60<0,CONCATENATE("(",SUBSTITUTE(SUBSTITUTE(SUBSTITUTE(SUBSTITUTE(TEXT(D60,"#.##0"),",","*"),".",","),"*","."),"-",""),")"),IF(D60=0," -",SUBSTITUTE(SUBSTITUTE(SUBSTITUTE(TEXT(D60,"#.##0"),",","*"),".",","),"*","."))) -> 369 | O60: =IF(E60<0,CONCATENATE("(",SUBSTITUTE(SUBSTITUTE(SUBSTITUTE(SUBSTITUTE(TEXT(E60,"#.##0"),",","*"),".",","),"*","."),"-",""),")"),IF(E60=0," -",SUBSTITUTE(SUBSTITUTE(SUBSTITUTE(TEXT(E60,"#.##0"),",","*"),".",","),"*","."))) -> 194 | P60: =IF(F60<0,CONCATENATE("(",SUBSTITUTE(SUBSTITUTE(SUBSTITUTE(SUBSTITUTE(TEXT(F60,"#.##0"),",","*"),".",","),"*","."),"-",""),")"),IF(F60=0," -",SUBSTITUTE(SUBSTITUTE(SUBSTITUTE(TEXT(F60,"#.##0"),",","*"),".",","),"*","."))) -> 124 | Q60: =IF(G60<0,CONCATENATE("(",SUBSTITUTE(SUBSTITUTE(SUBSTITUTE(SUBSTITUTE(TEXT(G60,"#.##0"),",","*"),".",","),"*","."),"-",""),")"),IF(G60=0," -",SUBSTITUTE(SUBSTITUTE(SUBSTITUTE(TEXT(G60,"#.##0"),",","*"),".",","),"*","."))) -> 219 | R60: =IF(H60<0,CONCATENATE("(",SUBSTITUTE(SUBSTITUTE(SUBSTITUTE(SUBSTITUTE(TEXT(H60,"#.##0"),",","*"),".",","),"*","."),"-",""),")"),IF(H60=0," -",SUBSTITUTE(SUBSTITUTE(SUBSTITUTE(TEXT(H60,"#.##0"),",","*"),".",","),"*","."))) -> 165
B61: Total | C61: =C56+C46 -> 15163 | D61: =D56+D46 -> 13677 | E61: =E56+E46 -> 5377 | F61: =F56+F46 -> 4848.5 | G61: =G56+G46 -> 7539.453 | H61: =H56+H46 -> 6364 | L61: Total | M61: =IF(C61<0,CONCATENATE("(",SUBSTITUTE(SUBSTITUTE(SUBSTITUTE(SUBSTITUTE(TEXT(C61,"#.##0"),",","*"),".",","),"*","."),"-",""),")"),IF(C61=0," -",SUBSTITUTE(SUBSTITUTE(SUBSTITUTE(TEXT(C61,"#.##0"),",","*"),".",","),"*","."))) -> 15,163 | N61: =IF(D61<0,CONCATENATE("(",SUBSTITUTE(SUBSTITUTE(SUBSTITUTE(SUBSTITUTE(TEXT(D61,"#.##0"),",","*"),".",","),"*","."),"-",""),")"),IF(D61=0," -",SUBSTITUTE(SUBSTITUTE(SUBSTITUTE(TEXT(D61,"#.##0"),",","*"),".",","),"*","."))) -> 13,677 | O61: =IF(E61<0,CONCATENATE("(",SUBSTITUTE(SUBSTITUTE(SUBSTITUTE(SUBSTITUTE(TEXT(E61,"#.##0"),",","*"),".",","),"*","."),"-",""),")"),IF(E61=0," -",SUBSTITUTE(SUBSTITUTE(SUBSTITUTE(TEXT(E61,"#.##0"),",","*"),".",","),"*","."))) -> 5,377 | P61: =IF(F61<0,CONCATENATE("(",SUBSTITUTE(SUBSTITUTE(SUBSTITUTE(SUBSTITUTE(TEXT(F61,"#.##0"),",","*"),".",","),"*","."),"-",""),")"),IF(F61=0," -",SUBSTITUTE(SUBSTITUTE(SUBSTITUTE(TEXT(F61,"#.##0"),",","*"),".",","),"*","."))) -> 4,849 | Q61: =IF(G61<0,CONCATENATE("(",SUBSTITUTE(SUBSTITUTE(SUBSTITUTE(SUBSTITUTE(TEXT(G61,"#.##0"),",","*"),".",","),"*","."),"-",""),")"),IF(G61=0," -",SUBSTITUTE(SUBSTITUTE(SUBSTITUTE(TEXT(G61,"#.##0"),",","*"),".",","),"*","."))) -> 7,539 | R61: =IF(H61<0,CONCATENATE("(",SUBSTITUTE(SUBSTITUTE(SUBSTITUTE(SUBSTITUTE(TEXT(H61,"#.##0"),",","*"),".",","),"*","."),"-",""),")"),IF(H61=0," -",SUBSTITUTE(SUBSTITUTE(SUBSTITUTE(TEXT(H61,"#.##0"),",","*"),".",","),"*","."))) -> 6,364
B65: Tabela - Custo de Produção em R$/ha Safra 2022/23 | L65: Table - Production Cost in R$/hectare, 2022/23Crop Year
B66: Total (R$/ha) | C66: Realizado 2021/22 (a) | D66: Orçado 2022/23 (b) | E66: Realizado 2022/23 (c) | F66: ∆% (c x b) | G66: ∆% (c x a) | L66: Total (R$/ha) | M66: Achieved 2021/22 (a) | N66: Budget 2022/23 (b) | O66: Achieved 2022/23 (c) | P66: ∆% (c x b) | Q66: ∆% (c x a)
B67: Algodão em pluma 1ª safra | C67: 12580 | D67: 15163 | E67: 15357 | F67: =E67/D67-1 -> 0.012794302 | G67: =E67/C67-1 -> 0.22074722 | L67: Cotton lint 1st crop | M67: =IF(C67<0,CONCATENATE("(",SUBSTITUTE(SUBSTITUTE(SUBSTITUTE(SUBSTITUTE(TEXT(C67,"#.##0"),",","*"),".",","),"*","."),"-",""),")"),IF(C67=0," -",SUBSTITUTE(SUBSTITUTE(SUBSTITUTE(TEXT(C67,"#.##0"),",","*"),".",","),"*","."))) -> 12,580 | N67: =IF(D67<0,CONCATENATE("(",SUBSTITUTE(SUBSTITUTE(SUBSTITUTE(SUBSTITUTE(TEXT(D67,"#.##0"),",","*"),".",","),"*","."),"-",""),")"),IF(D67=0," -",SUBSTITUTE(SUBSTITUTE(SUBSTITUTE(TEXT(D67,"#.##0"),",","*"),".",","),"*","."))) -> 15,163 | O67: =IF(E67<0,CONCATENATE("(",SUBSTITUTE(SUBSTITUTE(SUBSTITUTE(SUBSTITUTE(TEXT(E67,"#.##0"),",","*"),".",","),"*","."),"-",""),")"),IF(E67=0," -",SUBSTITUTE(SUBSTITUTE(SUBSTITUTE(TEXT(E67,"#.##0"),",","*"),".",","),"*","."))) -> 15,357 | P67: =SUBSTITUTE(TEXT(F67,"0,0%"),",",".") -> 1.3% | Q67: =SUBSTITUTE(TEXT(G67,"0,0%"),",",".") -> 22.1%
B68: Algodão em pluma 2ª safra | C68: 10191 | D68: 13677 | E68: 14161 | F68: =E68/D68-1 -> 0.035387877 | G68: =E68/C68-1 -> 0.38955942 | L68: Cotton lint 2nd crop | M68: =IF(C68<0,CONCATENATE("(",SUBSTITUTE(SUBSTITUTE(SUBSTITUTE(SUBSTITUTE(TEXT(C68,"#.##0"),",","*"),".",","),"*","."),"-",""),")"),IF(C68=0," -",SUBSTITUTE(SUBSTITUTE(SUBSTITUTE(TEXT(C68,"#.##0"),",","*"),".",","),"*","."))) -> 10,191 | N68: =IF(D68<0,CONCATENATE("(",SUBSTITUTE(SUBSTITUTE(SUBSTITUTE(SUBSTITUTE(TEXT(D68,"#.##0"),",","*"),".",","),"*","."),"-",""),")"),IF(D68=0," -",SUBSTITUTE(SUBSTITUTE(SUBSTITUTE(TEXT(D68,"#.##0"),",","*"),".",","),"*","."))) -> 13,677 | O68: =IF(E68<0,CONCATENATE("(",SUBSTITUTE(SUBSTITUTE(SUBSTITUTE(SUBSTITUTE(TEXT(E68,"#.##0"),",","*"),".",","),"*","."),"-",""),")"),IF(E68=0," -",SUBSTITUTE(SUBSTITUTE(SUBSTITUTE(TEXT(E68,"#.##0"),",","*"),".",","),"*","."))) -> 14,161 | P68: =SUBSTITUTE(TEXT(F68,"0,0%"),",",".") -> 3.5% | Q68: =SUBSTITUTE(TEXT(G68,"0,0%"),",",".") -> 39.0%
B69: Soja(1) | C69: 4283 | D69: 5377 | E69: 5128 | F69: =E69/D69-1 -> -0.04630835 | G69: =E69/C69-1 -> 0.19729162 | L69: Soybean(1) | M69: =IF(C69<0,CONCATENATE("(",SUBSTITUTE(SUBSTITUTE(SUBSTITUTE(SUBSTITUTE(TEXT(C69,"#.##0"),",","*"),".",","),"*","."),"-",""),")"),IF(C69=0," -",SUBSTITUTE(SUBSTITUTE(SUBSTITUTE(TEXT(C69,"#.##0"),",","*"),".",","),"*","."))) -> 4,283 | N69: =IF(D69<0,CONCATENATE("(",SUBSTITUTE(SUBSTITUTE(SUBSTITUTE(SUBSTITUTE(TEXT(D69,"#.##0"),",","*"),".",","),"*","."),"-",""),")"),IF(D69=0," -",SUBSTITUTE(SUBSTITUTE(SUBSTITUTE(TEXT(D69,"#.##0"),",","*"),".",","),"*","."))) -> 5,377 | O69: =IF(E69<0,CONCATENATE("(",SUBSTITUTE(SUBSTITUTE(SUBSTITUTE(SUBSTITUTE(TEXT(E69,"#.##0"),",","*"),".",","),"*","."),"-",""),")"),IF(E69=0," -",SUBSTITUTE(SUBSTITUTE(SUBSTITUTE(TEXT(E69,"#.##0"),",","*"),".",","),"*","."))) -> 5,128 | P69: =SUBSTITUTE(TEXT(F69,"0,0%"),",",".") -> -4.6% | Q69: =SUBSTITUTE(TEXT(G69,"0,0%"),",",".") -> 19.7%
B70: Milho 2ª safra | C70: 3711 | D70: 4867 | E70: 4767 | F70: =E70/D70-1 -> -0.020546538 | G70: =E70/C70-1 -> 0.28455942 | L70: Corn 2nd crop | M70: =IF(C70<0,CONCATENATE("(",SUBSTITUTE(SUBSTITUTE(SUBSTITUTE(SUBSTITUTE(TEXT(C70,"#.##0"),",","*"),".",","),"*","."),"-",""),")"),IF(C70=0," -",SUBSTITUTE(SUBSTITUTE(SUBSTITUTE(TEXT(C70,"#.##0"),",","*"),".",","),"*","."))) -> 3,711 | N70: =IF(D70<0,CONCATENATE("(",SUBSTITUTE(SUBSTITUTE(SUBSTITUTE(SUBSTITUTE(TEXT(D70,"#.##0"),",","*"),".",","),"*","."),"-",""),")"),IF(D70=0," -",SUBSTITUTE(SUBSTITUTE(SUBSTITUTE(TEXT(D70,"#.##0"),",","*"),".",","),"*","."))) -> 4,867 | O70: =IF(E70<0,CONCATENATE("(",SUBSTITUTE(SUBSTITUTE(SUBSTITUTE(SUBSTITUTE(TEXT(E70,"#.##0"),",","*"),".",","),"*","."),"-",""),")"),IF(E70=0," -",SUBSTITUTE(SUBSTITUTE(SUBSTITUTE(TEXT(E70,"#.##0"),",","*"),".",","),"*","."))) -> 4,767 | P70: =SUBSTITUTE(TEXT(F70,"0,0%"),",",".") -> -2.1% | Q70: =SUBSTITUTE(TEXT(G70,"0,0%"),",",".") -> 28.5%
B71: Custo médio total | C71: 6425 | D71: 7547 | E71: 7476 | F71: =7476/7547-1 -> -0.0094077117 | G71: =7476/6425-1 -> 0.16357977 | L71: Total average cost | M71: =IF(C71<0,CONCATENATE("(",SUBSTITUTE(SUBSTITUTE(SUBSTITUTE(SUBSTITUTE(TEXT(C71,"#.##0"),",","*"),".",","),"*","."),"-",""),")"),IF(C71=0," -",SUBSTITUTE(SUBSTITUTE(SUBSTITUTE(TEXT(C71,"#.##0"),",","*"),".",","),"*","."))) -> 6,425 | N71: =IF(D71<0,CONCATENATE("(",SUBSTITUTE(SUBSTITUTE(SUBSTITUTE(SUBSTITUTE(TEXT(D71,"#.##0"),",","*"),".",","),"*","."),"-",""),")"),IF(D71=0," -",SUBSTITUTE(SUBSTITUTE(SUBSTITUTE(TEXT(D71,"#.##0"),",","*"),".",","),"*","."))) -> 7,547 | O71: =IF(E71<0,CONCATENATE("(",SUBSTITUTE(SUBSTITUTE(SUBSTITUTE(SUBSTITUTE(TEXT(E71,"#.##0"),",","*"),".",","),"*","."),"-",""),")"),IF(E71=0," -",SUBSTITUTE(SUBSTITUTE(SUBSTITUTE(TEXT(E71,"#.##0"),",","*"),".",","),"*","."))) -> 7,476 | P71: =SUBSTITUTE(TEXT(F71,"0,0%"),",",".") -> -0.9% | Q71: =SUBSTITUTE(TEXT(G71,"0,0%"),",",".") -> 16.4%
B72: (1) Inclusos os custos com produção de sementes. | L72: (1) Including seed production costs.
B74: Tabela – Custo unitário Safra 2022/23 | L74: Table – Unitary Cost 2022/23 Crop Year
C75: Produtividade | D75: Custo | E75: R$/Kg | F75: Produtividade | G75: Custo | H75: R$/Kg | I75: ∆% | M75: Budget Yield (Kg/ha) | N75: Budget Cost (R$/ha) | O75: Budget | P75: Yield | Q75: Cost | R75: Achieved | S75: ∆%
C76: Orçada (Kg/ha) | D76: Orçado (R$/ha) | E76: Orçado (a) | F76: Realizado (Kg/ha) | G76: Realizado | H76: Realizado (b) | I76: b x a | M76: 2022/23 | N76: 2022/23 | O76: R$/Kg (a) | P76: Achieved (Kg/ha) | Q76: Achieved | R76: R$/Kg (b) | S76: b x a
C77: 2022/23 | D77: 2022/23 | E77: 2022/23 | F77: 2022/23 | G77: (R$/ha) | H77: 2022/23 | O77: 2022/23 | P77: 2022/23 | Q77: (R$/ha) | R77: 2022/23
G78: 2022/23 | Q78: 2022/23
B79: Algodão em pluma 1ª safra | C79: 1927 | D79: =D67 -> 15163 | E79: =D79/C79 -> 7.8687078 | F79: =E18 -> 2000 | G79: =E67 -> 15357 | H79: =G79/F79 -> 7.6785 | I79: =H79/E79-1 -> -0.02417269 | L79: Cotton lint 1st crop | M79: =IF(C79<0,CONCATENATE("(",SUBSTITUTE(SUBSTITUTE(SUBSTITUTE(SUBSTITUTE(TEXT(C79,"#.##0"),",","*"),".",","),"*","."),"-",""),")"),IF(C79=0," -",SUBSTITUTE(SUBSTITUTE(SUBSTITUTE(TEXT(C79,"#.##0"),",","*"),".",","),"*","."))) -> 1,927 | N79: =IF(D79<0,CONCATENATE("(",SUBSTITUTE(SUBSTITUTE(SUBSTITUTE(SUBSTITUTE(TEXT(D79,"#.##0"),",","*"),".",","),"*","."),"-",""),")"),IF(D79=0," -",SUBSTITUTE(SUBSTITUTE(SUBSTITUTE(TEXT(D79,"#.##0"),",","*"),".",","),"*","."))) -> 15,163 | O79: =E79 -> 7.8687078 | P79: =IF(F79<0,CONCATENATE("(",SUBSTITUTE(SUBSTITUTE(SUBSTITUTE(SUBSTITUTE(TEXT(F79,"#.##0"),",","*"),".",","),"*","."),"-",""),")"),IF(F79=0," -",SUBSTITUTE(SUBSTITUTE(SUBSTITUTE(TEXT(F79,"#.##0"),",","*"),".",","),"*","."))) -> 2,000 | Q79: =IF(G79<0,CONCATENATE("(",SUBSTITUTE(SUBSTITUTE(SUBSTITUTE(SUBSTITUTE(TEXT(G79,"#.##0"),",","*"),".",","),"*","."),"-",""),")"),IF(G79=0," -",SUBSTITUTE(SUBSTITUTE(SUBSTITUTE(TEXT(G79,"#.##0"),",","*"),".",","),"*","."))) -> 15,357 | R79: =H79 -> 7.6785 | S79: =SUBSTITUTE(TEXT(I79,"0,0%"),",",".") -> -2.4%
B80: Algodão em pluma 2ª safra | C80: 1839 | D80: =D68 -> 13677 | E80: =D80/C80 -> 7.4371941 | F80: =OLE_LINK7 -> 2037 | G80: =E68 -> 14161 | H80: =G80/F80 -> 6.95189 | I80: =H80/E80-1 -> -0.065253654 | L80: Cotton lint 2nd crop | M80: =IF(C80<0,CONCATENATE("(",SUBSTITUTE(SUBSTITUTE(SUBSTITUTE(SUBSTITUTE(TEXT(C80,"#.##0"),",","*"),".",","),"*","."),"-",""),")"),IF(C80=0," -",SUBSTITUTE(SUBSTITUTE(SUBSTITUTE(TEXT(C80,"#.##0"),",","*"),".",","),"*","."))) -> 1,839 | N80: =IF(D80<0,CONCATENATE("(",SUBSTITUTE(SUBSTITUTE(SUBSTITUTE(SUBSTITUTE(TEXT(D80,"#.##0"),",","*"),".",","),"*","."),"-",""),")"),IF(D80=0," -",SUBSTITUTE(SUBSTITUTE(SUBSTITUTE(TEXT(D80,"#.##0"),",","*"),".",","),"*","."))) -> 13,677 | O80: =E80 -> 7.4371941 | P80: =IF(F80<0,CONCATENATE("(",SUBSTITUTE(SUBSTITUTE(SUBSTITUTE(SUBSTITUTE(TEXT(F80,"#.##0"),",","*"),".",","),"*","."),"-",""),")"),IF(F80=0," -",SUBSTITUTE(SUBSTITUTE(SUBSTITUTE(TEXT(F80,"#.##0"),",","*"),".",","),"*","."))) -> 2,037 | Q80: =IF(G80<0,CONCATENATE("(",SUBSTITUTE(SUBSTITUTE(SUBSTITUTE(SUBSTITUTE(TEXT(G80,"#.##0"),",","*"),".",","),"*","."),"-",""),")"),IF(G80=0," -",SUBSTITUTE(SUBSTITUTE(SUBSTITUTE(TEXT(G80,"#.##0"),",","*"),".",","),"*","."))) -> 14,161 | R80: =H80 -> 6.95189 | S80: =SUBSTITUTE(TEXT(I80,"0,0%"),",",".") -> -6.5%
B81: Soja(1) | C81: 3918 | D81: =D69 -> 5377 | E81: =D81/C81 -> 1.3723839 | F81: =OLE_LINK4 -> 3904 | G81: =E69 -> 5128 | H81: =G81/F81 -> 1.3135246 | I81: =H81/E81-1 -> -0.04288835 | L81: Soybean(1) | M81: =IF(C81<0,CONCATENATE("(",SUBSTITUTE(SUBSTITUTE(SUBSTITUTE(SUBSTITUTE(TEXT(C81,"#.##0"),",","*"),".",","),"*","."),"-",""),")"),IF(C81=0," -",SUBSTITUTE(SUBSTITUTE(SUBSTITUTE(TEXT(C81,"#.##0"),",","*"),".",","),"*","."))) -> 3,918 | N81: =IF(D81<0,CONCATENATE("(",SUBSTITUTE(SUBSTITUTE(SUBSTITUTE(SUBSTITUTE(TEXT(D81,"#.##0"),",","*"),".",","),"*","."),"-",""),")"),IF(D81=0," -",SUBSTITUTE(SUBSTITUTE(SUBSTITUTE(TEXT(D81,"#.##0"),",","*"),".",","),"*","."))) -> 5,377 | O81: =E81 -> 1.3723839 | P81: =IF(F81<0,CONCATENATE("(",SUBSTITUTE(SUBSTITUTE(SUBSTITUTE(SUBSTITUTE(TEXT(F81,"#.##0"),",","*"),".",","),"*","."),"-",""),")"),IF(F81=0," -",SUBSTITUTE(SUBSTITUTE(SUBSTITUTE(TEXT(F81,"#.##0"),",","*"),".",","),"*","."))) -> 3,904 | Q81: =IF(G81<0,CONCATENATE("(",SUBSTITUTE(SUBSTITUTE(SUBSTITUTE(SUBSTITUTE(TEXT(G81,"#.##0"),",","*"),".",","),"*","."),"-",""),")"),IF(G81=0," -",SUBSTITUTE(SUBSTITUTE(SUBSTITUTE(TEXT(G81,"#.##0"),",","*"),".",","),"*","."))) -> 5,128 | R81: =H81 -> 1.3135246 | S81: =SUBSTITUTE(TEXT(I81,"0,0%"),",",".") -> -4.3%
B82: Milho 2ª safra | C82: 7685 | D82: =D70 -> 4867 | E82: =D82/C82 -> 0.63331165 | F82: =E22 -> 7708 | G82: =E70 -> 4767 | H82: =G82/F82 -> 0.61844837 | I82: =H82/E82-1 -> -0.023469142 | L82: Corn 2nd crop | M82: =IF(C82<0,CONCATENATE("(",SUBSTITUTE(SUBSTITUTE(SUBSTITUTE(SUBSTITUTE(TEXT(C82,"#.##0"),",","*"),".",","),"*","."),"-",""),")"),IF(C82=0," -",SUBSTITUTE(SUBSTITUTE(SUBSTITUTE(TEXT(C82,"#.##0"),",","*"),".",","),"*","."))) -> 7,685 | N82: =IF(D82<0,CONCATENATE("(",SUBSTITUTE(SUBSTITUTE(SUBSTITUTE(SUBSTITUTE(TEXT(D82,"#.##0"),",","*"),".",","),"*","."),"-",""),")"),IF(D82=0," -",SUBSTITUTE(SUBSTITUTE(SUBSTITUTE(TEXT(D82,"#.##0"),",","*"),".",","),"*","."))) -> 4,867 | O82: =E82 -> 0.63331165 | P82: =IF(F82<0,CONCATENATE("(",SUBSTITUTE(SUBSTITUTE(SUBSTITUTE(SUBSTITUTE(TEXT(F82,"#.##0"),",","*"),".",","),"*","."),"-",""),")"),IF(F82=0," -",SUBSTITUTE(SUBSTITUTE(SUBSTITUTE(TEXT(F82,"#.##0"),",","*"),".",","),"*","."))) -> 7,708 | Q82: =IF(G82<0,CONCATENATE("(",SUBSTITUTE(SUBSTITUTE(SUBSTITUTE(SUBSTITUTE(TEXT(G82,"#.##0"),",","*"),".",","),"*","."),"-",""),")"),IF(G82=0," -",SUBSTITUTE(SUBSTITUTE(SUBSTITUTE(TEXT(G82,"#.##0"),",","*"),".",","),"*","."))) -> 4,767 | R82: =H82 -> 0.61844837 | S82: =SUBSTITUTE(TEXT(I82,"0,0%"),",",".") -> -2.3%
B83: (1) Inclusos os custos com produção de sementes. | L83: (1) Including seed production costs

Sheet Operacoes 23.24
B2: Tabela - Área plantada por cultura safra 2022/23 x 2023/24 | L2: Table - Planted Area by Crop 2022/23 vs. 2023/24 crop years
B3: Mix de culturas | C3: Área plantada | D3: Área Plantada | E3: Área Plantada | F3: Participação | G3: Δ% | L3: Crop Mix | M3: Planted Area | N3: Planted Area | O3: Planted Area | P3: Share | Q3: Δ%
C4: 2022/23 | D4: 2023/24 Orçado (a) | E4: 2023/24(1) Forecast (b) | F4: 2023/24 | G4: (b x a) | M4: 2022/23 | N4: 2023/24 Budget (a) | O4: 2023/24(1) Forecast (b) | P4: 2023/24 | Q4: (b x a)
C5: ----------------------------ha ---------------------------- | F5: % | M5: ----------------------------ha ---------------------------- | P5: %
B6: Algodão em pluma | C6: 162243 | D6: 187464 | E6: 188730 | F6: =E6/$E$12 -> 0.28958933 | G6: =E6/D6-1 -> 0.0067532966 | L6: Cotton lint | M6: =IF(C6<0,CONCATENATE("(",SUBSTITUTE(SUBSTITUTE(SUBSTITUTE(SUBSTITUTE(TEXT(C6,"#.##0"),",","*"),".",","),"*","."),"-",""),")"),IF(C6=0," -",SUBSTITUTE(SUBSTITUTE(SUBSTITUTE(TEXT(C6,"#.##0"),",","*"),".",","),"*","."))) -> 162,243 | N6: =IF(D6<0,CONCATENATE("(",SUBSTITUTE(SUBSTITUTE(SUBSTITUTE(SUBSTITUTE(TEXT(D6,"#.##0"),",","*"),".",","),"*","."),"-",""),")"),IF(D6=0," -",SUBSTITUTE(SUBSTITUTE(SUBSTITUTE(TEXT(D6,"#.##0"),",","*"),".",","),"*","."))) -> 187,464 | O6: =IF(E6<0,CONCATENATE("(",SUBSTITUTE(SUBSTITUTE(SUBSTITUTE(SUBSTITUTE(TEXT(E6,"#.##0"),",","*"),".",","),"*","."),"-",""),")"),IF(E6=0," -",SUBSTITUTE(SUBSTITUTE(SUBSTITUTE(TEXT(E6,"#.##0"),",","*"),".",","),"*","."))) -> 188,730 | P6: =SUBSTITUTE(TEXT(F6,"0,0%"),",",".") -> 29.0% | Q6: =SUBSTITUTE(TEXT(G6,"0,0%"),",",".") -> 0.7%
B7: Algodão em pluma 1ª safra | C7: 85823 | D7: 90088 | E7: 106715 | F7: =E7/$E$12 -> 0.16374464 | G7: =E7/D7-1 -> 0.18456398 | L7: Cotton lint 1st crop | M7: =IF(C7<0,CONCATENATE("(",SUBSTITUTE(SUBSTITUTE(SUBSTITUTE(SUBSTITUTE(TEXT(C7,"#.##0"),",","*"),".",","),"*","."),"-",""),")"),IF(C7=0," -",SUBSTITUTE(SUBSTITUTE(SUBSTITUTE(TEXT(C7,"#.##0"),",","*"),".",","),"*","."))) -> 85,823 | N7: =IF(D7<0,CONCATENATE("(",SUBSTITUTE(SUBSTITUTE(SUBSTITUTE(SUBSTITUTE(TEXT(D7,"#.##0"),",","*"),".",","),"*","."),"-",""),")"),IF(D7=0," -",SUBSTITUTE(SUBSTITUTE(SUBSTITUTE(TEXT(D7,"#.##0"),",","*"),".",","),"*","."))) -> 90,088 | O7: =IF(E7<0,CONCATENATE("(",SUBSTITUTE(SUBSTITUTE(SUBSTITUTE(SUBSTITUTE(TEXT(E7,"#.##0"),",","*"),".",","),"*","."),"-",""),")"),IF(E7=0," -",SUBSTITUTE(SUBSTITUTE(SUBSTITUTE(TEXT(E7,"#.##0"),",","*"),".",","),"*","."))) -> 106,715 | P7: =SUBSTITUTE(TEXT(F7,"0,0%"),",",".") -> 16.4% | Q7: =SUBSTITUTE(TEXT(G7,"0,0%"),",",".") -> 18.5%
B8: Algodão em pluma 2ª safra | C8: 76420 | D8: 97376 | E8: 82015 | F8: =E8/$E$12 -> 0.12584469 | G8: =E8/D8-1 -> -0.15774934 | L8: Cotton lint 2nd crop | M8: =IF(C8<0,CONCATENATE("(",SUBSTITUTE(SUBSTITUTE(SUBSTITUTE(SUBSTITUTE(TEXT(C8,"#.##0"),",","*"),".",","),"*","."),"-",""),")"),IF(C8=0," -",SUBSTITUTE(SUBSTITUTE(SUBSTITUTE(TEXT(C8,"#.##0"),",","*"),".",","),"*","."))) -> 76,420 | N8: =IF(D8<0,CONCATENATE("(",SUBSTITUTE(SUBSTITUTE(SUBSTITUTE(SUBSTITUTE(TEXT(D8,"#.##0"),",","*"),".",","),"*","."),"-",""),")"),IF(D8=0," -",SUBSTITUTE(SUBSTITUTE(SUBSTITUTE(TEXT(D8,"#.##0"),",","*"),".",","),"*","."))) -> 97,376 | O8: =IF(E8<0,CONCATENATE("(",SUBSTITUTE(SUBSTITUTE(SUBSTITUTE(SUBSTITUTE(TEXT(E8,"#.##0"),",","*"),".",","),"*","."),"-",""),")"),IF(E8=0," -",SUBSTITUTE(SUBSTITUTE(SUBSTITUTE(TEXT(E8,"#.##0"),",","*"),".",","),"*","."))) -> 82,015 | P8: =SUBSTITUTE(TEXT(F8,"0,0%"),",",".") -> 12.6% | Q8: =SUBSTITUTE(TEXT(G8,"0,0%"),",",".") -> -15.8%
B9: Soja (Comercial + Semente) | C9: 346941 | D9: 336770 | E9: 320009 | F9: =E9/$E$12 -> 0.49102523 | G9: =E9/D9-1 -> -0.049769873 | L9: Soybean (Commercial + Seed) | M9: =IF(C9<0,CONCATENATE("(",SUBSTITUTE(SUBSTITUTE(SUBSTITUTE(SUBSTITUTE(TEXT(C9,"#.##0"),",","*"),".",","),"*","."),"-",""),")"),IF(C9=0," -",SUBSTITUTE(SUBSTITUTE(SUBSTITUTE(TEXT(C9,"#.##0"),",","*"),".",","),"*","."))) -> 346,941 | N9: =IF(D9<0,CONCATENATE("(",SUBSTITUTE(SUBSTITUTE(SUBSTITUTE(SUBSTITUTE(TEXT(D9,"#.##0"),",","*"),".",","),"*","."),"-",""),")"),IF(D9=0," -",SUBSTITUTE(SUBSTITUTE(SUBSTITUTE(TEXT(D9,"#.##0"),",","*"),".",","),"*","."))) -> 336,770 | O9: =IF(E9<0,CONCATENATE("(",SUBSTITUTE(SUBSTITUTE(SUBSTITUTE(SUBSTITUTE(TEXT(E9,"#.##0"),",","*"),".",","),"*","."),"-",""),")"),IF(E9=0," -",SUBSTITUTE(SUBSTITUTE(SUBSTITUTE(TEXT(E9,"#.##0"),",","*"),".",","),"*","."))) -> 320,009 | P9: =SUBSTITUTE(TEXT(F9,"0,0%"),",",".") -> 49.1% | Q9: =SUBSTITUTE(TEXT(G9,"0,0%"),",",".") -> -5.0%
B10: Milho 2ª safra | C10: 137585 | D10: 103436 | E10: 96661 | F10: =E10/$E$12 -> 0.14831767 | G10: =E10/D10-1 -> -0.065499439 | L10: Corn 2nd crop | M10: =IF(C10<0,CONCATENATE("(",SUBSTITUTE(SUBSTITUTE(SUBSTITUTE(SUBSTITUTE(TEXT(C10,"#.##0"),",","*"),".",","),"*","."),"-",""),")"),IF(C10=0," -",SUBSTITUTE(SUBSTITUTE(SUBSTITUTE(TEXT(C10,"#.##0"),",","*"),".",","),"*","."))) -> 137,585 | N10: =IF(D10<0,CONCATENATE("(",SUBSTITUTE(SUBSTITUTE(SUBSTITUTE(SUBSTITUTE(TEXT(D10,"#.##0"),",","*"),".",","),"*","."),"-",""),")"),IF(D10=0," -",SUBSTITUTE(SUBSTITUTE(SUBSTITUTE(TEXT(D10,"#.##0"),",","*"),".",","),"*","."))) -> 103,436 | O10: =IF(E10<0,CONCATENATE("(",SUBSTITUTE(SUBSTITUTE(SUBSTITUTE(SUBSTITUTE(TEXT(E10,"#.##0"),",","*"),".",","),"*","."),"-",""),")"),IF(E10=0," -",SUBSTITUTE(SUBSTITUTE(SUBSTITUTE(TEXT(E10,"#.##0"),",","*"),".",","),"*","."))) -> 96,661 | P10: =SUBSTITUTE(TEXT(F10,"0,0%"),",",".") -> 14.8% | Q10: =SUBSTITUTE(TEXT(G10,"0,0%"),",",".") -> -6.5%
B11: Outras culturas (2) | C11: 27615 | D11: 46733 | E11: 46316 | F11: =E11/$E$12 -> 0.071067766 | G11: =E11/D11-1 -> -0.0089230308 | L11: Other Crops (2) | M11: =IF(C11<0,CONCATENATE("(",SUBSTITUTE(SUBSTITUTE(SUBSTITUTE(SUBSTITUTE(TEXT(C11,"#.##0"),",","*"),".",","),"*","."),"-",""),")"),IF(C11=0," -",SUBSTITUTE(SUBSTITUTE(SUBSTITUTE(TEXT(C11,"#.##0"),",","*"),".",","),"*","."))) -> 27,615 | N11: =IF(D11<0,CONCATENATE("(",SUBSTITUTE(SUBSTITUTE(SUBSTITUTE(SUBSTITUTE(TEXT(D11,"#.##0"),",","*"),".",","),"*","."),"-",""),")"),IF(D11=0," -",SUBSTITUTE(SUBSTITUTE(SUBSTITUTE(TEXT(D11,"#.##0"),",","*"),".",","),"*","."))) -> 46,733 | O11: =IF(E11<0,CONCATENATE("(",SUBSTITUTE(SUBSTITUTE(SUBSTITUTE(SUBSTITUTE(TEXT(E11,"#.##0"),",","*"),".",","),"*","."),"-",""),")"),IF(E11=0," -",SUBSTITUTE(SUBSTITUTE(SUBSTITUTE(TEXT(E11,"#.##0"),",","*"),".",","),"*","."))) -> 46,316 | P11: =SUBSTITUTE(TEXT(F11,"0,0%"),",",".") -> 7.1% | Q11: =SUBSTITUTE(TEXT(G11,"0,0%"),",",".") -> -0.9%
B12: Área Total | C12: 674384 | D12: 674403 | E12: 651716 | F12: =E12/$E$12 -> 1 | G12: =E12/D12-1 -> -0.033640123 | L12: Total Area | M12: =IF(C12<0,CONCATENATE("(",SUBSTITUTE(SUBSTITUTE(SUBSTITUTE(SUBSTITUTE(TEXT(C12,"#.##0"),",","*"),".",","),"*","."),"-",""),")"),IF(C12=0," -",SUBSTITUTE(SUBSTITUTE(SUBSTITUTE(TEXT(C12,"#.##0"),",","*"),".",","),"*","."))) -> 674,384 | N12: =IF(D12<0,CONCATENATE("(",SUBSTITUTE(SUBSTITUTE(SUBSTITUTE(SUBSTITUTE(TEXT(D12,"#.##0"),",","*"),".",","),"*","."),"-",""),")"),IF(D12=0," -",SUBSTITUTE(SUBSTITUTE(SUBSTITUTE(TEXT(D12,"#.##0"),",","*"),".",","),"*","."))) -> 674,403 | O12: =IF(E12<0,CONCATENATE("(",SUBSTITUTE(SUBSTITUTE(SUBSTITUTE(SUBSTITUTE(TEXT(E12,"#.##0"),",","*"),".",","),"*","."),"-",""),")"),IF(E12=0," -",SUBSTITUTE(SUBSTITUTE(SUBSTITUTE(TEXT(E12,"#.##0"),",","*"),".",","),"*","."))) -> 651,716 | P12: =SUBSTITUTE(TEXT(F12,"0,0%"),",",".") -> 100.0% | Q12: =SUBSTITUTE(TEXT(G12,"0,0%"),",",".") -> -3.4%
B13: (1) Fatores climáticos poderão afetar a projeção de área plantada. | L13: (1) Weather factors may affect the planted area forecast.
B14: (2) Outras Culturas (Semente de Braquiária 12.042 ha, Semente de Crotalária 1.859 ha, Feijão 3.482 ha, Gergelim 2.624 ha, Semente de Milheto 6.522 ha, Milho 1ª Safra 266 ha, Milho Semente 767 ha, Semente de Nabo Forrageiro 5.062 ha, Pecuária 3.606 ha, Sorgo 262 ha, Trigo 9.306 ha e Semente de Trigo Mourisco 519 ha) total 46.316 ha. | L14: (2) Other Crops (First-crop corn 266 ha, Corn seed 767 ha, Wheat 9,306 ha, Mung bean 3,482 ha, Livestock 3,606 ha, Sorghum 262 ha, Sesame 2,624 ha, Brachiaria seed 12,042 ha, Buckwheat 519 ha, Pearl millet seed 6,522 ha, Crotalaria 1,859 ha, Forage Radish Seed 5,062 ha) Total 46,316 hectares.
B16: Tabela - Produtividade Orçada Safra 2023/24 | L16: Table - Projected Yields 2023/24 crop year
B17: Produtividade (kg/ha) | C17: Safra 2022/23 | D17: Safra 2023/24 | E17: Safra 2023/24 | F17: ∆% | G17: ∆% | L17: Yield (kg/ha) | M17: 2022/23 Crop Year | N17: 2023/24 Crop Year | O17: 2023/24 Crop Year | P17: ∆% | Q17: ∆%
C18: Realizado (a) | D18: Orçado (b) | E18: Forecast (c) | F18: (c) x (a) | G18: (c) x (b) | M18: Achieved (a) | N18: Budget (b) | O18: Forecast(c) | P18: (c) x (a) | Q18: (c) x (b)
B19: Algodão em pluma 1ª safra | C19: 2000 | D19: 2020 | E19: 2020 | F19: =E19/C19-1 -> 0.01 | G19: =E19/D19-1 -> 0 | L19: Cotton lint 1st crop | M19: =IF(C19<0,CONCATENATE("(",SUBSTITUTE(SUBSTITUTE(SUBSTITUTE(SUBSTITUTE(TEXT(C19,"#.##0"),",","*"),".",","),"*","."),"-",""),")"),IF(C19=0," -",SUBSTITUTE(SUBSTITUTE(SUBSTITUTE(TEXT(C19,"#.##0"),",","*"),".",","),"*","."))) -> 2,000 | N19: =IF(D19<0,CONCATENATE("(",SUBSTITUTE(SUBSTITUTE(SUBSTITUTE(SUBSTITUTE(TEXT(D19,"#.##0"),",","*"),".",","),"*","."),"-",""),")"),IF(D19=0," -",SUBSTITUTE(SUBSTITUTE(SUBSTITUTE(TEXT(D19,"#.##0"),",","*"),".",","),"*","."))) -> 2,020 | O19: =IF(E19<0,CONCATENATE("(",SUBSTITUTE(SUBSTITUTE(SUBSTITUTE(SUBSTITUTE(TEXT(E19,"#.##0"),",","*"),".",","),"*","."),"-",""),")"),IF(E19=0," -",SUBSTITUTE(SUBSTITUTE(SUBSTITUTE(TEXT(E19,"#.##0"),",","*"),".",","),"*","."))) -> 2,020 | P19: =SUBSTITUTE(TEXT(F19,"0,0%"),",",".") -> 1.0% | Q19: =SUBSTITUTE(TEXT(G19,"0,0%"),",",".") -> 0.0%
B20: Algodão em pluma 2ª safra | C20: 2037 | D20: 1869 | E20: 1869 | F20: =E20/C20-1 -> -0.082474227 | G20: =E20/D20-1 -> 0 | L20: Cotton lint 2nd crop | M20: =IF(C20<0,CONCATENATE("(",SUBSTITUTE(SUBSTITUTE(SUBSTITUTE(SUBSTITUTE(TEXT(C20,"#.##0"),",","*"),".",","),"*","."),"-",""),")"),IF(C20=0," -",SUBSTITUTE(SUBSTITUTE(SUBSTITUTE(TEXT(C20,"#.##0"),",","*"),".",","),"*","."))) -> 2,037 | N20: =IF(D20<0,CONCATENATE("(",SUBSTITUTE(SUBSTITUTE(SUBSTITUTE(SUBSTITUTE(TEXT(D20,"#.##0"),",","*"),".",","),"*","."),"-",""),")"),IF(D20=0," -",SUBSTITUTE(SUBSTITUTE(SUBSTITUTE(TEXT(D20,"#.##0"),",","*"),".",","),"*","."))) -> 1,869 | O20: =IF(E20<0,CONCATENATE("(",SUBSTITUTE(SUBSTITUTE(SUBSTITUTE(SUBSTITUTE(TEXT(E20,"#.##0"),",","*"),".",","),"*","."),"-",""),")"),IF(E20=0," -",SUBSTITUTE(SUBSTITUTE(SUBSTITUTE(TEXT(E20,"#.##0"),",","*"),".",","),"*","."))) -> 1,869 | P20: =SUBSTITUTE(TEXT(F20,"0,0%"),",",".") -> -8.2% | Q20: =SUBSTITUTE(TEXT(G20,"0,0%"),",",".") -> 0.0%
B21: Caroço de algodão | C21: 2491 | D21: 2410 | E21: 2410 | F21: =E21/C21-1 -> -0.032517061 | G21: =E21/D21-1 -> 0 | L21: Cotton seed | M21: =IF(C21<0,CONCATENATE("(",SUBSTITUTE(SUBSTITUTE(SUBSTITUTE(SUBSTITUTE(TEXT(C21,"#.##0"),",","*"),".",","),"*","."),"-",""),")"),IF(C21=0," -",SUBSTITUTE(SUBSTITUTE(SUBSTITUTE(TEXT(C21,"#.##0"),",","*"),".",","),"*","."))) -> 2,491 | N21: =IF(D21<0,CONCATENATE("(",SUBSTITUTE(SUBSTITUTE(SUBSTITUTE(SUBSTITUTE(TEXT(D21,"#.##0"),",","*"),".",","),"*","."),"-",""),")"),IF(D21=0," -",SUBSTITUTE(SUBSTITUTE(SUBSTITUTE(TEXT(D21,"#.##0"),",","*"),".",","),"*","."))) -> 2,410 | O21: =IF(E21<0,CONCATENATE("(",SUBSTITUTE(SUBSTITUTE(SUBSTITUTE(SUBSTITUTE(TEXT(E21,"#.##0"),",","*"),".",","),"*","."),"-",""),")"),IF(E21=0," -",SUBSTITUTE(SUBSTITUTE(SUBSTITUTE(TEXT(E21,"#.##0"),",","*"),".",","),"*","."))) -> 2,410 | P21: =SUBSTITUTE(TEXT(F21,"0,0%"),",",".") -> -3.3% | Q21: =SUBSTITUTE(TEXT(G21,"0,0%"),",",".") -> 0.0%
B22: Soja (Comercial + Semente) | C22: 3904 | D22: 3948 | E22: 3432 | F22: =E22/C22-1 -> -0.12090164 | G22: =E22/D22-1 -> -0.13069909 | L22: Soybean (Commercial + Seed) | M22: =IF(C22<0,CONCATENATE("(",SUBSTITUTE(SUBSTITUTE(SUBSTITUTE(SUBSTITUTE(TEXT(C22,"#.##0"),",","*"),".",","),"*","."),"-",""),")"),IF(C22=0," -",SUBSTITUTE(SUBSTITUTE(SUBSTITUTE(TEXT(C22,"#.##0"),",","*"),".",","),"*","."))) -> 3,904 | N22: =IF(D22<0,CONCATENATE("(",SUBSTITUTE(SUBSTITUTE(SUBSTITUTE(SUBSTITUTE(TEXT(D22,"#.##0"),",","*"),".",","),"*","."),"-",""),")"),IF(D22=0," -",SUBSTITUTE(SUBSTITUTE(SUBSTITUTE(TEXT(D22,"#.##0"),",","*"),".",","),"*","."))) -> 3,948 | O22: =IF(E22<0,CONCATENATE("(",SUBSTITUTE(SUBSTITUTE(SUBSTITUTE(SUBSTITUTE(TEXT(E22,"#.##0"),",","*"),".",","),"*","."),"-",""),")"),IF(E22=0," -",SUBSTITUTE(SUBSTITUTE(SUBSTITUTE(TEXT(E22,"#.##0"),",","*"),".",","),"*","."))) -> 3,432 | P22: =SUBSTITUTE(TEXT(F22,"0,0%"),",",".") -> -12.1% | Q22: =SUBSTITUTE(TEXT(G22,"0,0%"),",",".") -> -13.1%
B23: Milho 2ª safra | C23: 7708 | D23: 7580 | E23: 7580 | F23: =E23/C23-1 -> -0.016606124 | G23: =E23/D23-1 -> 0 | L23: Corn 2nd crop | M23: =IF(C23<0,CONCATENATE("(",SUBSTITUTE(SUBSTITUTE(SUBSTITUTE(SUBSTITUTE(TEXT(C23,"#.##0"),",","*"),".",","),"*","."),"-",""),")"),IF(C23=0," -",SUBSTITUTE(SUBSTITUTE(SUBSTITUTE(TEXT(C23,"#.##0"),",","*"),".",","),"*","."))) -> 7,708 | N23: =IF(D23<0,CONCATENATE("(",SUBSTITUTE(SUBSTITUTE(SUBSTITUTE(SUBSTITUTE(TEXT(D23,"#.##0"),",","*"),".",","),"*","."),"-",""),")"),IF(D23=0," -",SUBSTITUTE(SUBSTITUTE(SUBSTITUTE(TEXT(D23,"#.##0"),",","*"),".",","),"*","."))) -> 7,580 | O23: =IF(E23<0,CONCATENATE("(",SUBSTITUTE(SUBSTITUTE(SUBSTITUTE(SUBSTITUTE(TEXT(E23,"#.##0"),",","*"),".",","),"*","."),"-",""),")"),IF(E23=0," -",SUBSTITUTE(SUBSTITUTE(SUBSTITUTE(TEXT(E23,"#.##0"),",","*"),".",","),"*","."))) -> 7,580 | P23: =SUBSTITUTE(TEXT(F23,"0,0%"),",",".") -> -1.7% | Q23: =SUBSTITUTE(TEXT(G23,"0,0%"),",",".") -> 0.0%
B26: Tabela - Custos Orçadas Safra 2023/24 | L26: Table - Budgeted Costs – 2023/24 Crop Year
B27: % | C27: Algodão | D27: Soja | E27: Milho | F27: Média Orç. 2023/24 | G27: Média Orç. 2022/23 | L27: % | M27: Cotton | N27: Soybean | O27: Corn | P27: Average Budg. 2023/24 | Q27: Average Budg. 2022/23
B28: Custos Variáveis | C28: 79.6 | D28: 74.8 | E28: 80 | F28: 77.8 | G28: 79.8 | L28: Variable Costs | M28: =IF(C28<0,CONCATENATE("(",SUBSTITUTE(SUBSTITUTE(SUBSTITUTE(SUBSTITUTE(TEXT(C28,"#.##0,00"),",","*"),".",","),"*","."),"-",""),")"),IF(C28=0," -",SUBSTITUTE(SUBSTITUTE(SUBSTITUTE(TEXT(C28,"#.##0,0"),",","*"),".",","),"*","."))) -> 79.6 | N28: =IF(D28<0,CONCATENATE("(",SUBSTITUTE(SUBSTITUTE(SUBSTITUTE(SUBSTITUTE(TEXT(D28,"#.##0,00"),",","*"),".",","),"*","."),"-",""),")"),IF(D28=0," -",SUBSTITUTE(SUBSTITUTE(SUBSTITUTE(TEXT(D28,"#.##0,0"),",","*"),".",","),"*","."))) -> 74.8 | O28: =IF(E28<0,CONCATENATE("(",SUBSTITUTE(SUBSTITUTE(SUBSTITUTE(SUBSTITUTE(TEXT(E28,"#.##0,00"),",","*"),".",","),"*","."),"-",""),")"),IF(E28=0," -",SUBSTITUTE(SUBSTITUTE(SUBSTITUTE(TEXT(E28,"#.##0,0"),",","*"),".",","),"*","."))) -> 80.0 | P28: =IF(F28<0,CONCATENATE("(",SUBSTITUTE(SUBSTITUTE(SUBSTITUTE(SUBSTITUTE(TEXT(F28,"#.##0,00"),",","*"),".",","),"*","."),"-",""),")"),IF(F28=0," -",SUBSTITUTE(SUBSTITUTE(SUBSTITUTE(TEXT(F28,"#.##0,0"),",","*"),".",","),"*","."))) -> 77.8 | Q28: =IF(G28<0,CONCATENATE("(",SUBSTITUTE(SUBSTITUTE(SUBSTITUTE(SUBSTITUTE(TEXT(G28,"#.##0,00"),",","*"),".",","),"*","."),"-",""),")"),IF(G28=0," -",SUBSTITUTE(SUBSTITUTE(SUBSTITUTE(TEXT(G28,"#.##0,0"),",","*"),".",","),"*","."))) -> 79.8
B29: Sementes | C29: 10.1 | D29: 15.2 | E29: 21.5 | F29: 13.2 | G29: 11.1 | L29: Seeds | M29: =IF(C29<0,CONCATENATE("(",SUBSTITUTE(SUBSTITUTE(SUBSTITUTE(SUBSTITUTE(TEXT(C29,"#.##0,00"),",","*"),".",","),"*","."),"-",""),")"),IF(C29=0," -",SUBSTITUTE(SUBSTITUTE(SUBSTITUTE(TEXT(C29,"#.##0,0"),",","*"),".",","),"*","."))) -> 10.1 | N29: =IF(D29<0,CONCATENATE("(",SUBSTITUTE(SUBSTITUTE(SUBSTITUTE(SUBSTITUTE(TEXT(D29,"#.##0,00"),",","*"),".",","),"*","."),"-",""),")"),IF(D29=0," -",SUBSTITUTE(SUBSTITUTE(SUBSTITUTE(TEXT(D29,"#.##0,0"),",","*"),".",","),"*","."))) -> 15.2 | O29: =IF(E29<0,CONCATENATE("(",SUBSTITUTE(SUBSTITUTE(SUBSTITUTE(SUBSTITUTE(TEXT(E29,"#.##0,00"),",","*"),".",","),"*","."),"-",""),")"),IF(E29=0," -",SUBSTITUTE(SUBSTITUTE(SUBSTITUTE(TEXT(E29,"#.##0,0"),",","*"),".",","),"*","."))) -> 21.5 | P29: =IF(F29<0,CONCATENATE("(",SUBSTITUTE(SUBSTITUTE(SUBSTITUTE(SUBSTITUTE(TEXT(F29,"#.##0,00"),",","*"),".",","),"*","."),"-",""),")"),IF(F29=0," -",SUBSTITUTE(SUBSTITUTE(SUBSTITUTE(TEXT(F29,"#.##0,0"),",","*"),".",","),"*","."))) -> 13.2 | Q29: =IF(G29<0,CONCATENATE("(",SUBSTITUTE(SUBSTITUTE(SUBSTITUTE(SUBSTITUTE(TEXT(G29,"#.##0,00"),",","*"),".",","),"*","."),"-",""),")"),IF(G29=0," -",SUBSTITUTE(SUBSTITUTE(SUBSTITUTE(TEXT(G29,"#.##0,0"),",","*"),".",","),"*","."))) -> 11.1
B30: Fertilizantes | C30: 21.1 | D30: 18.7 | E30: 32 | F30: 21.3 | G30: 23.2 | L30: Fertilizers | M30: =IF(C30<0,CONCATENATE("(",SUBSTITUTE(SUBSTITUTE(SUBSTITUTE(SUBSTITUTE(TEXT(C30,"#.##0,00"),",","*"),".",","),"*","."),"-",""),")"),IF(C30=0," -",SUBSTITUTE(SUBSTITUTE(SUBSTITUTE(TEXT(C30,"#.##0,0"),",","*"),".",","),"*","."))) -> 21.1 | N30: =IF(D30<0,CONCATENATE("(",SUBSTITUTE(SUBSTITUTE(SUBSTITUTE(SUBSTITUTE(TEXT(D30,"#.##0,00"),",","*"),".",","),"*","."),"-",""),")"),IF(D30=0," -",SUBSTITUTE(SUBSTITUTE(SUBSTITUTE(TEXT(D30,"#.##0,0"),",","*"),".",","),"*","."))) -> 18.7 | O30: =IF(E30<0,CONCATENATE("(",SUBSTITUTE(SUBSTITUTE(SUBSTITUTE(SUBSTITUTE(TEXT(E30,"#.##0,00"),",","*"),".",","),"*","."),"-",""),")"),IF(E30=0," -",SUBSTITUTE(SUBSTITUTE(SUBSTITUTE(TEXT(E30,"#.##0,0"),",","*"),".",","),"*","."))) -> 32.0 | P30: =IF(F30<0,CONCATENATE("(",SUBSTITUTE(SUBSTITUTE(SUBSTITUTE(SUBSTITUTE(TEXT(F30,"#.##0,00"),",","*"),".",","),"*","."),"-",""),")"),IF(F30=0," -",SUBSTITUTE(SUBSTITUTE(SUBSTITUTE(TEXT(F30,"#.##0,0"),",","*"),".",","),"*","."))) -> 21.3 | Q30: =IF(G30<0,CONCATENATE("(",SUBSTITUTE(SUBSTITUTE(SUBSTITUTE(SUBSTITUTE(TEXT(G30,"#.##0,00"),",","*"),".",","),"*","."),"-",""),")"),IF(G30=0," -",SUBSTITUTE(SUBSTITUTE(SUBSTITUTE(TEXT(G30,"#.##0,0"),",","*"),".",","),"*","."))) -> 23.2
B31: Defensivos | C31: 20.4 | D31: 16.8 | E31: 10.9 | F31: 18.1 | G31: 20.6 | L31: Chemicals | M31: =IF(C31<0,CONCATENATE("(",SUBSTITUTE(SUBSTITUTE(SUBSTITUTE(SUBSTITUTE(TEXT(C31,"#.##0,00"),",","*"),".",","),"*","."),"-",""),")"),IF(C31=0," -",SUBSTITUTE(SUBSTITUTE(SUBSTITUTE(TEXT(C31,"#.##0,0"),",","*"),".",","),"*","."))) -> 20.4 | N31: =IF(D31<0,CONCATENATE("(",SUBSTITUTE(SUBSTITUTE(SUBSTITUTE(SUBSTITUTE(TEXT(D31,"#.##0,00"),",","*"),".",","),"*","."),"-",""),")"),IF(D31=0," -",SUBSTITUTE(SUBSTITUTE(SUBSTITUTE(TEXT(D31,"#.##0,0"),",","*"),".",","),"*","."))) -> 16.8 | O31: =IF(E31<0,CONCATENATE("(",SUBSTITUTE(SUBSTITUTE(SUBSTITUTE(SUBSTITUTE(TEXT(E31,"#.##0,00"),",","*"),".",","),"*","."),"-",""),")"),IF(E31=0," -",SUBSTITUTE(SUBSTITUTE(SUBSTITUTE(TEXT(E31,"#.##0,0"),",","*"),".",","),"*","."))) -> 10.9 | P31: =IF(F31<0,CONCATENATE("(",SUBSTITUTE(SUBSTITUTE(SUBSTITUTE(SUBSTITUTE(TEXT(F31,"#.##0,00"),",","*"),".",","),"*","."),"-",""),")"),IF(F31=0," -",SUBSTITUTE(SUBSTITUTE(SUBSTITUTE(TEXT(F31,"#.##0,0"),",","*"),".",","),"*","."))) -> 18.1 | Q31: =IF(G31<0,CONCATENATE("(",SUBSTITUTE(SUBSTITUTE(SUBSTITUTE(SUBSTITUTE(TEXT(G31,"#.##0,00"),",","*"),".",","),"*","."),"-",""),")"),IF(G31=0," -",SUBSTITUTE(SUBSTITUTE(SUBSTITUTE(TEXT(G31,"#.##0,0"),",","*"),".",","),"*","."))) -> 20.6
B32: Pulverização Aérea | C32: 2.3 | D32: 1.4 | E32: 1.6 | F32: 1.9 | G32: 1.6 | L32: Air Spraying | M32: =IF(C32<0,CONCATENATE("(",SUBSTITUTE(SUBSTITUTE(SUBSTITUTE(SUBSTITUTE(TEXT(C32,"#.##0,00"),",","*"),".",","),"*","."),"-",""),")"),IF(C32=0," -",SUBSTITUTE(SUBSTITUTE(SUBSTITUTE(TEXT(C32,"#.##0,0"),",","*"),".",","),"*","."))) -> 2.3 | N32: =IF(D32<0,CONCATENATE("(",SUBSTITUTE(SUBSTITUTE(SUBSTITUTE(SUBSTITUTE(TEXT(D32,"#.##0,00"),",","*"),".",","),"*","."),"-",""),")"),IF(D32=0," -",SUBSTITUTE(SUBSTITUTE(SUBSTITUTE(TEXT(D32,"#.##0,0"),",","*"),".",","),"*","."))) -> 1.4 | O32: =IF(E32<0,CONCATENATE("(",SUBSTITUTE(SUBSTITUTE(SUBSTITUTE(SUBSTITUTE(TEXT(E32,"#.##0,00"),",","*"),".",","),"*","."),"-",""),")"),IF(E32=0," -",SUBSTITUTE(SUBSTITUTE(SUBSTITUTE(TEXT(E32,"#.##0,0"),",","*"),".",","),"*","."))) -> 1.6 | P32: =IF(F32<0,CONCATENATE("(",SUBSTITUTE(SUBSTITUTE(SUBSTITUTE(SUBSTITUTE(TEXT(F32,"#.##0,00"),",","*"),".",","),"*","."),"-",""),")"),IF(F32=0," -",SUBSTITUTE(SUBSTITUTE(SUBSTITUTE(TEXT(F32,"#.##0,0"),",","*"),".",","),"*","."))) -> 1.9 | Q32: =IF(G32<0,CONCATENATE("(",SUBSTITUTE(SUBSTITUTE(SUBSTITUTE(SUBSTITUTE(TEXT(G32,"#.##0,00"),",","*"),".",","),"*","."),"-",""),")"),IF(G32=0," -",SUBSTITUTE(SUBSTITUTE(SUBSTITUTE(TEXT(G32,"#.##0,0"),",","*"),".",","),"*","."))) -> 1.6
B33: Combustíveis e lubrificantes | C33: 3.4 | D33: 3.5 | E33: 3.6 | F33: 3.5 | G33: 4.3 | L33: Fuels and Lubricants | M33: =IF(C33<0,CONCATENATE("(",SUBSTITUTE(SUBSTITUTE(SUBSTITUTE(SUBSTITUTE(TEXT(C33,"#.##0,00"),",","*"),".",","),"*","."),"-",""),")"),IF(C33=0," -",SUBSTITUTE(SUBSTITUTE(SUBSTITUTE(TEXT(C33,"#.##0,0"),",","*"),".",","),"*","."))) -> 3.4 | N33: =IF(D33<0,CONCATENATE("(",SUBSTITUTE(SUBSTITUTE(SUBSTITUTE(SUBSTITUTE(TEXT(D33,"#.##0,00"),",","*"),".",","),"*","."),"-",""),")"),IF(D33=0," -",SUBSTITUTE(SUBSTITUTE(SUBSTITUTE(TEXT(D33,"#.##0,0"),",","*"),".",","),"*","."))) -> 3.5 | O33: =IF(E33<0,CONCATENATE("(",SUBSTITUTE(SUBSTITUTE(SUBSTITUTE(SUBSTITUTE(TEXT(E33,"#.##0,00"),",","*"),".",","),"*","."),"-",""),")"),IF(E33=0," -",SUBSTITUTE(SUBSTITUTE(SUBSTITUTE(TEXT(E33,"#.##0,0"),",","*"),".",","),"*","."))) -> 3.6 | P33: =IF(F33<0,CONCATENATE("(",SUBSTITUTE(SUBSTITUTE(SUBSTITUTE(SUBSTITUTE(TEXT(F33,"#.##0,00"),",","*"),".",","),"*","."),"-",""),")"),IF(F33=0," -",SUBSTITUTE(SUBSTITUTE(SUBSTITUTE(TEXT(F33,"#.##0,0"),",","*"),".",","),"*","."))) -> 3.5 | Q33: =IF(G33<0,CONCATENATE("(",SUBSTITUTE(SUBSTITUTE(SUBSTITUTE(SUBSTITUTE(TEXT(G33,"#.##0,00"),",","*"),".",","),"*","."),"-",""),")"),IF(G33=0," -",SUBSTITUTE(SUBSTITUTE(SUBSTITUTE(TEXT(G33,"#.##0,0"),",","*"),".",","),"*","."))) -> 4.3
B34: Mão-de-obra | C34: 0.9 | D34: 0.7 | E34: 0.6 | F34: 0.8 | G34: 0.6 | L34: Labor | M34: =IF(C34<0,CONCATENATE("(",SUBSTITUTE(SUBSTITUTE(SUBSTITUTE(SUBSTITUTE(TEXT(C34,"#.##0,00"),",","*"),".",","),"*","."),"-",""),")"),IF(C34=0," -",SUBSTITUTE(SUBSTITUTE(SUBSTITUTE(TEXT(C34,"#.##0,0"),",","*"),".",","),"*","."))) -> 0.9 | N34: =IF(D34<0,CONCATENATE("(",SUBSTITUTE(SUBSTITUTE(SUBSTITUTE(SUBSTITUTE(TEXT(D34,"#.##0,00"),",","*"),".",","),"*","."),"-",""),")"),IF(D34=0," -",SUBSTITUTE(SUBSTITUTE(SUBSTITUTE(TEXT(D34,"#.##0,0"),",","*"),".",","),"*","."))) -> 0.7 | O34: =IF(E34<0,CONCATENATE("(",SUBSTITUTE(SUBSTITUTE(SUBSTITUTE(SUBSTITUTE(TEXT(E34,"#.##0,00"),",","*"),".",","),"*","."),"-",""),")"),IF(E34=0," -",SUBSTITUTE(SUBSTITUTE(SUBSTITUTE(TEXT(E34,"#.##0,0"),",","*"),".",","),"*","."))) -> 0.6 | P34: =IF(F34<0,CONCATENATE("(",SUBSTITUTE(SUBSTITUTE(SUBSTITUTE(SUBSTITUTE(TEXT(F34,"#.##0,00"),",","*"),".",","),"*","."),"-",""),")"),IF(F34=0," -",SUBSTITUTE(SUBSTITUTE(SUBSTITUTE(TEXT(F34,"#.##0,0"),",","*"),".",","),"*","."))) -> 0.8 | Q34: =IF(G34<0,CONCATENATE("(",SUBSTITUTE(SUBSTITUTE(SUBSTITUTE(SUBSTITUTE(TEXT(G34,"#.##0,00"),",","*"),".",","),"*","."),"-",""),")"),IF(G34=0," -",SUBSTITUTE(SUBSTITUTE(SUBSTITUTE(TEXT(G34,"#.##0,0"),",","*"),".",","),"*","."))) -> 0.6
B35: Beneficiamento | C35: 9.7 | D35: 3 | E35: 2.4 | F35: 6.4 | G35: 6.3 | L35: Ginning | M35: =IF(C35<0,CONCATENATE("(",SUBSTITUTE(SUBSTITUTE(SUBSTITUTE(SUBSTITUTE(TEXT(C35,"#.##0,00"),",","*"),".",","),"*","."),"-",""),")"),IF(C35=0," -",SUBSTITUTE(SUBSTITUTE(SUBSTITUTE(TEXT(C35,"#.##0,0"),",","*"),".",","),"*","."))) -> 9.7 | N35: =IF(D35<0,CONCATENATE("(",SUBSTITUTE(SUBSTITUTE(SUBSTITUTE(SUBSTITUTE(TEXT(D35,"#.##0,00"),",","*"),".",","),"*","."),"-",""),")"),IF(D35=0," -",SUBSTITUTE(SUBSTITUTE(SUBSTITUTE(TEXT(D35,"#.##0,0"),",","*"),".",","),"*","."))) -> 3.0 | O35: =IF(E35<0,CONCATENATE("(",SUBSTITUTE(SUBSTITUTE(SUBSTITUTE(SUBSTITUTE(TEXT(E35,"#.##0,00"),",","*"),".",","),"*","."),"-",""),")"),IF(E35=0," -",SUBSTITUTE(SUBSTITUTE(SUBSTITUTE(TEXT(E35,"#.##0,0"),",","*"),".",","),"*","."))) -> 2.4 | P35: =IF(F35<0,CONCATENATE("(",SUBSTITUTE(SUBSTITUTE(SUBSTITUTE(SUBSTITUTE(TEXT(F35,"#.##0,00"),",","*"),".",","),"*","."),"-",""),")"),IF(F35=0," -",SUBSTITUTE(SUBSTITUTE(SUBSTITUTE(TEXT(F35,"#.##0,0"),",","*"),".",","),"*","."))) -> 6.4 | Q35: =IF(G35<0,CONCATENATE("(",SUBSTITUTE(SUBSTITUTE(SUBSTITUTE(SUBSTITUTE(TEXT(G35,"#.##0,00"),",","*"),".",","),"*","."),"-",""),")"),IF(G35=0," -",SUBSTITUTE(SUBSTITUTE(SUBSTITUTE(TEXT(G35,"#.##0,0"),",","*"),".",","),"*","."))) -> 6.3
B36: Manutenção de máquinas e implementos | C36: 4.3 | D36: 4.1 | E36: 3.3 | F36: 4.1 | G36: 4 | L36: Maintenance | M36: =IF(C36<0,CONCATENATE("(",SUBSTITUTE(SUBSTITUTE(SUBSTITUTE(SUBSTITUTE(TEXT(C36,"#.##0,00"),",","*"),".",","),"*","."),"-",""),")"),IF(C36=0," -",SUBSTITUTE(SUBSTITUTE(SUBSTITUTE(TEXT(C36,"#.##0,0"),",","*"),".",","),"*","."))) -> 4.3 | N36: =IF(D36<0,CONCATENATE("(",SUBSTITUTE(SUBSTITUTE(SUBSTITUTE(SUBSTITUTE(TEXT(D36,"#.##0,00"),",","*"),".",","),"*","."),"-",""),")"),IF(D36=0," -",SUBSTITUTE(SUBSTITUTE(SUBSTITUTE(TEXT(D36,"#.##0,0"),",","*"),".",","),"*","."))) -> 4.1 | O36: =IF(E36<0,CONCATENATE("(",SUBSTITUTE(SUBSTITUTE(SUBSTITUTE(SUBSTITUTE(TEXT(E36,"#.##0,00"),",","*"),".",","),"*","."),"-",""),")"),IF(E36=0," -",SUBSTITUTE(SUBSTITUTE(SUBSTITUTE(TEXT(E36,"#.##0,0"),",","*"),".",","),"*","."))) -> 3.3 | P36: =IF(F36<0,CONCATENATE("(",SUBSTITUTE(SUBSTITUTE(SUBSTITUTE(SUBSTITUTE(TEXT(F36,"#.##0,00"),",","*"),".",","),"*","."),"-",""),")"),IF(F36=0," -",SUBSTITUTE(SUBSTITUTE(SUBSTITUTE(TEXT(F36,"#.##0,0"),",","*"),".",","),"*","."))) -> 4.1 | Q36: =IF(G36<0,CONCATENATE("(",SUBSTITUTE(SUBSTITUTE(SUBSTITUTE(SUBSTITUTE(TEXT(G36,"#.##0,00"),",","*"),".",","),"*","."),"-",""),")"),IF(G36=0," -",SUBSTITUTE(SUBSTITUTE(SUBSTITUTE(TEXT(G36,"#.##0,0"),",","*"),".",","),"*","."))) -> 4.0
B37: Outros | C37: 7.4 | D37: 11.4 | E37: 4 | F37: 8.5 | G37: 8.1 | L37: Others | M37: =IF(C37<0,CONCATENATE("(",SUBSTITUTE(SUBSTITUTE(SUBSTITUTE(SUBSTITUTE(TEXT(C37,"#.##0,00"),",","*"),".",","),"*","."),"-",""),")"),IF(C37=0," -",SUBSTITUTE(SUBSTITUTE(SUBSTITUTE(TEXT(C37,"#.##0,0"),",","*"),".",","),"*","."))) -> 7.4 | N37: =IF(D37<0,CONCATENATE("(",SUBSTITUTE(SUBSTITUTE(SUBSTITUTE(SUBSTITUTE(TEXT(D37,"#.##0,00"),",","*"),".",","),"*","."),"-",""),")"),IF(D37=0," -",SUBSTITUTE(SUBSTITUTE(SUBSTITUTE(TEXT(D37,"#.##0,0"),",","*"),".",","),"*","."))) -> 11.4 | O37: =IF(E37<0,CONCATENATE("(",SUBSTITUTE(SUBSTITUTE(SUBSTITUTE(SUBSTITUTE(TEXT(E37,"#.##0,00"),",","*"),".",","),"*","."),"-",""),")"),IF(E37=0," -",SUBSTITUTE(SUBSTITUTE(SUBSTITUTE(TEXT(E37,"#.##0,0"),",","*"),".",","),"*","."))) -> 4.0 | P37: =IF(F37<0,CONCATENATE("(",SUBSTITUTE(SUBSTITUTE(SUBSTITUTE(SUBSTITUTE(TEXT(F37,"#.##0,00"),",","*"),".",","),"*","."),"-",""),")"),IF(F37=0," -",SUBSTITUTE(SUBSTITUTE(SUBSTITUTE(TEXT(F37,"#.##0,0"),",","*"),".",","),"*","."))) -> 8.5 | Q37: =IF(G37<0,CONCATENATE("(",SUBSTITUTE(SUBSTITUTE(SUBSTITUTE(SUBSTITUTE(TEXT(G37,"#.##0,00"),",","*"),".",","),"*","."),"-",""),")"),IF(G37=0," -",SUBSTITUTE(SUBSTITUTE(SUBSTITUTE(TEXT(G37,"#.##0,0"),",","*"),".",","),"*","."))) -> 8.1
B38: Custos Fixos | C38: 20.4 | D38: 25.2 | E38: 20 | F38: 22.2 | G38: 20.2 | L38: Fixed Costs | M38: =IF(C38<0,CONCATENATE("(",SUBSTITUTE(SUBSTITUTE(SUBSTITUTE(SUBSTITUTE(TEXT(C38,"#.##0,00"),",","*"),".",","),"*","."),"-",""),")"),IF(C38=0," -",SUBSTITUTE(SUBSTITUTE(SUBSTITUTE(TEXT(C38,"#.##0,0"),",","*"),".",","),"*","."))) -> 20.4 | N38: =IF(D38<0,CONCATENATE("(",SUBSTITUTE(SUBSTITUTE(SUBSTITUTE(SUBSTITUTE(TEXT(D38,"#.##0,00"),",","*"),".",","),"*","."),"-",""),")"),IF(D38=0," -",SUBSTITUTE(SUBSTITUTE(SUBSTITUTE(TEXT(D38,"#.##0,0"),",","*"),".",","),"*","."))) -> 25.2 | O38: =IF(E38<0,CONCATENATE("(",SUBSTITUTE(SUBSTITUTE(SUBSTITUTE(SUBSTITUTE(TEXT(E38,"#.##0,00"),",","*"),".",","),"*","."),"-",""),")"),IF(E38=0," -",SUBSTITUTE(SUBSTITUTE(SUBSTITUTE(TEXT(E38,"#.##0,0"),",","*"),".",","),"*","."))) -> 20.0 | P38: =IF(F38<0,CONCATENATE("(",SUBSTITUTE(SUBSTITUTE(SUBSTITUTE(SUBSTITUTE(TEXT(F38,"#.##0,00"),",","*"),".",","),"*","."),"-",""),")"),IF(F38=0," -",SUBSTITUTE(SUBSTITUTE(SUBSTITUTE(TEXT(F38,"#.##0,0"),",","*"),".",","),"*","."))) -> 22.2 | Q38: =IF(G38<0,CONCATENATE("(",SUBSTITUTE(SUBSTITUTE(SUBSTITUTE(SUBSTITUTE(TEXT(G38,"#.##0,00"),",","*"),".",","),"*","."),"-",""),")"),IF(G38=0," -",SUBSTITUTE(SUBSTITUTE(SUBSTITUTE(TEXT(G38,"#.##0,0"),",","*"),".",","),"*","."))) -> 20.2
B39: Mão-de-obra | C39: 7.2 | D39: 8.1 | E39: 6.4 | F39: 7.4 | G39: 6.6 | L39: Labor | M39: =IF(C39<0,CONCATENATE("(",SUBSTITUTE(SUBSTITUTE(SUBSTITUTE(SUBSTITUTE(TEXT(C39,"#.##0,00"),",","*"),".",","),"*","."),"-",""),")"),IF(C39=0," -",SUBSTITUTE(SUBSTITUTE(SUBSTITUTE(TEXT(C39,"#.##0,0"),",","*"),".",","),"*","."))) -> 7.2 | N39: =IF(D39<0,CONCATENATE("(",SUBSTITUTE(SUBSTITUTE(SUBSTITUTE(SUBSTITUTE(TEXT(D39,"#.##0,00"),",","*"),".",","),"*","."),"-",""),")"),IF(D39=0," -",SUBSTITUTE(SUBSTITUTE(SUBSTITUTE(TEXT(D39,"#.##0,0"),",","*"),".",","),"*","."))) -> 8.1 | O39: =IF(E39<0,CONCATENATE("(",SUBSTITUTE(SUBSTITUTE(SUBSTITUTE(SUBSTITUTE(TEXT(E39,"#.##0,00"),",","*"),".",","),"*","."),"-",""),")"),IF(E39=0," -",SUBSTITUTE(SUBSTITUTE(SUBSTITUTE(TEXT(E39,"#.##0,0"),",","*"),".",","),"*","."))) -> 6.4 | P39: =IF(F39<0,CONCATENATE("(",SUBSTITUTE(SUBSTITUTE(SUBSTITUTE(SUBSTITUTE(TEXT(F39,"#.##0,00"),",","*"),".",","),"*","."),"-",""),")"),IF(F39=0," -",SUBSTITUTE(SUBSTITUTE(SUBSTITUTE(TEXT(F39,"#.##0,0"),",","*"),".",","),"*","."))) -> 7.4 | Q39: =IF(G39<0,CONCATENATE("(",SUBSTITUTE(SUBSTITUTE(SUBSTITUTE(SUBSTITUTE(TEXT(G39,"#.##0,00"),",","*"),".",","),"*","."),"-",""),")"),IF(G39=0," -",SUBSTITUTE(SUBSTITUTE(SUBSTITUTE(TEXT(G39,"#.##0,0"),",","*"),".",","),"*","."))) -> 6.6
... B42: Outros | C42: 2.8 | D42: 3.4 | E42: 2.7 | F42: 3.1 | G42: 2.8 | L42: Others | M42: =IF(C42<0,CONCATENATE("(",SUBSTITUTE(SUBSTITUTE(SUBSTITUTE(SUBSTITUTE(TEXT(C42,"#.##0,00"),",","*"),".",","),"*","."),"-",""),")"),IF(C42=0," -",SUBSTITUTE(SUBSTITUTE(SUBSTITUTE(TEXT(C42,"#.##0,0"),",","*"),".",","),"*","."))) -> 2.8 | N42: =IF(D42<0,CONCATENATE("(",SUBSTITUTE(SUBSTITUTE(SUBSTITUTE(SUBSTITUTE(TEXT(D42,"#.##0,00"),",","*"),".",","),"*","."),"-",""),")"),IF(D42=0," -",SUBSTITUTE(SUBSTITUTE(SUBSTITUTE(TEXT(D42,"#.##0,0"),",","*"),".",","),"*","."))) -> 3.4 | O42: =IF(E42<0,CONCATENATE("(",SUBSTITUTE(SUBSTITUTE(SUBSTITUTE(SUBSTITUTE(TEXT(E42,"#.##0,00"),",","*"),".",","),"*","."),"-",""),")"),IF(E42=0," -",SUBSTITUTE(SUBSTITUTE(SUBSTITUTE(TEXT(E42,"#.##0,0"),",","*"),".",","),"*","."))) -> 2.7 | P42: =IF(F42<0,CONCATENATE("(",SUBSTITUTE(SUBSTITUTE(SUBSTITUTE(SUBSTITUTE(TEXT(F42,"#.##0,00"),",","*"),".",","),"*","."),"-",""),")"),IF(F42=0," -",SUBSTITUTE(SUBSTITUTE(SUBSTITUTE(TEXT(F42,"#.##0,0"),",","*"),".",","),"*","."))) -> 3.1 | Q42: =IF(G42<0,CONCATENATE("(",SUBSTITUTE(SUBSTITUTE(SUBSTITUTE(SUBSTITUTE(TEXT(G42,"#.##0,00"),",","*"),".",","),"*","."),"-",""),")"),IF(G42=0," -",SUBSTITUTE(SUBSTITUTE(SUBSTITUTE(TEXT(G42,"#.##0,0"),",","*"),".",","),"*","."))) -> 2.8
B44: Tabela - Custo de produção – Breakdown em R$ por hectare – Safra 2023/24 | L44: Table – Production Cost – Breakdown in % and R$ per hectare – 2023/24 Crop Year
B45: R$/ha | C45: Algodão Orçado | D45: Algodão Orçado | E45: Soja Orçado | F45: Milho Orçado | G45: Média Orçado | H45: Média Orçado | L45: R$/ha | M45: Cotton Butdget | N45: Cotton Butdget | O45: Soybean Budget | P45: Corn Budget | Q45: Average Budget | R45: Average Budget
C46: 1 ª safra | D46: 2ª safra | F46: 2ª Safra | G46: 2023/24 | H46: 2022/23 | M46: 1st crop | N46: 2nd crop | P46: 2nd crop | Q46: 2023/24 | R46: 2022/23
B47: Custos Variáveis | C47: =SUM(C48:C56) -> 12069.748 | D47: =SUM(D48:D56) -> 10886.892 | E47: =SUM(E48:E56) -> 3906.804 | F47: =SUM(F48:F56) -> 3888.733 | G47: =SUM(G48:G56) -> 5583.706 | H47: =SUM(H48:H56) -> 6372.03 | L47: Variable Costs | M47: =IF(C47<0,CONCATENATE("(",SUBSTITUTE(SUBSTITUTE(SUBSTITUTE(SUBSTITUTE(TEXT(C47,"#.##0"),",","*"),".",","),"*","."),"-",""),")"),IF(C47=0," -",SUBSTITUTE(SUBSTITUTE(SUBSTITUTE(TEXT(C47,"#.##0"),",","*"),".",","),"*","."))) -> 12,070 | N47: =IF(D47<0,CONCATENATE("(",SUBSTITUTE(SUBSTITUTE(SUBSTITUTE(SUBSTITUTE(TEXT(D47,"#.##0"),",","*"),".",","),"*","."),"-",""),")"),IF(D47=0," -",SUBSTITUTE(SUBSTITUTE(SUBSTITUTE(TEXT(D47,"#.##0"),",","*"),".",","),"*","."))) -> 10,887 | O47: =IF(E47<0,CONCATENATE("(",SUBSTITUTE(SUBSTITUTE(SUBSTITUTE(SUBSTITUTE(TEXT(E47,"#.##0"),",","*"),".",","),"*","."),"-",""),")"),IF(E47=0," -",SUBSTITUTE(SUBSTITUTE(SUBSTITUTE(TEXT(E47,"#.##0"),",","*"),".",","),"*","."))) -> 3,907 | P47: =IF(F47<0,CONCATENATE("(",SUBSTITUTE(SUBSTITUTE(SUBSTITUTE(SUBSTITUTE(TEXT(F47,"#.##0"),",","*"),".",","),"*","."),"-",""),")"),IF(F47=0," -",SUBSTITUTE(SUBSTITUTE(SUBSTITUTE(TEXT(F47,"#.##0"),",","*"),".",","),"*","."))) -> 3,889 | Q47: =IF(G47<0,CONCATENATE("(",SUBSTITUTE(SUBSTITUTE(SUBSTITUTE(SUBSTITUTE(TEXT(G47,"#.##0"),",","*"),".",","),"*","."),"-",""),")"),IF(G47=0," -",SUBSTITUTE(SUBSTITUTE(SUBSTITUTE(TEXT(G47,"#.##0"),",","*"),".",","),"*","."))) -> 5,584 | R47: =IF(H47<0,CONCATENATE("(",SUBSTITUTE(SUBSTITUTE(SUBSTITUTE(SUBSTITUTE(TEXT(H47,"#.##0"),",","*"),".",","),"*","."),"-",""),")"),IF(H47=0," -",SUBSTITUTE(SUBSTITUTE(SUBSTITUTE(TEXT(H47,"#.##0"),",","*"),".",","),"*","."))) -> 6,372
B48: Sementes | C48: =C29*D$68/100 -> 1531.463 | D48: =C29*D$69/100 -> 1381.377 | E48: =D29*D$70/100 -> 793.896 | F48: =E29*D$71/100 -> 1046.405 | G48: =F29*7177/100 -> 947.364 | H48: =G29*7985/100 -> 886.335 | L48: Seeds | M48: =IF(C48<0,CONCATENATE("(",SUBSTITUTE(SUBSTITUTE(SUBSTITUTE(SUBSTITUTE(TEXT(C48,"#.##0"),",","*"),".",","),"*","."),"-",""),")"),IF(C48=0," -",SUBSTITUTE(SUBSTITUTE(SUBSTITUTE(TEXT(C48,"#.##0"),",","*"),".",","),"*","."))) -> 1,531 | N48: =IF(D48<0,CONCATENATE("(",SUBSTITUTE(SUBSTITUTE(SUBSTITUTE(SUBSTITUTE(TEXT(D48,"#.##0"),",","*"),".",","),"*","."),"-",""),")"),IF(D48=0," -",SUBSTITUTE(SUBSTITUTE(SUBSTITUTE(TEXT(D48,"#.##0"),",","*"),".",","),"*","."))) -> 1,381 | O48: =IF(E48<0,CONCATENATE("(",SUBSTITUTE(SUBSTITUTE(SUBSTITUTE(SUBSTITUTE(TEXT(E48,"#.##0"),",","*"),".",","),"*","."),"-",""),")"),IF(E48=0," -",SUBSTITUTE(SUBSTITUTE(SUBSTITUTE(TEXT(E48,"#.##0"),",","*"),".",","),"*","."))) -> 794 | P48: =IF(F48<0,CONCATENATE("(",SUBSTITUTE(SUBSTITUTE(SUBSTITUTE(SUBSTITUTE(TEXT(F48,"#.##0"),",","*"),".",","),"*","."),"-",""),")"),IF(F48=0," -",SUBSTITUTE(SUBSTITUTE(SUBSTITUTE(TEXT(F48,"#.##0"),",","*"),".",","),"*","."))) -> 1,046 | Q48: =IF(G48<0,CONCATENATE("(",SUBSTITUTE(SUBSTITUTE(SUBSTITUTE(SUBSTITUTE(TEXT(G48,"#.##0"),",","*"),".",","),"*","."),"-",""),")"),IF(G48=0," -",SUBSTITUTE(SUBSTITUTE(SUBSTITUTE(TEXT(G48,"#.##0"),",","*"),".",","),"*","."))) -> 947 | R48: =IF(H48<0,CONCATENATE("(",SUBSTITUTE(SUBSTITUTE(SUBSTITUTE(SUBSTITUTE(TEXT(H48,"#.##0"),",","*"),".",","),"*","."),"-",""),")"),IF(H48=0," -",SUBSTITUTE(SUBSTITUTE(SUBSTITUTE(TEXT(H48,"#.##0"),",","*"),".",","),"*","."))) -> 886
B49: Fertilizantes | C49: =C30*D$68/100 -> 3199.393 | D49: =C30*D$69/100 -> 2885.847 | E49: =D30*D$70/100 -> 976.701 | F49: =E30*D$71/100 -> 1557.44 | G49: =F30*7177/100 -> 1528.701 | H49: =G30*7985/100 -> 1852.52 | L49: Fertilizers | M49: =IF(C49<0,CONCATENATE("(",SUBSTITUTE(SUBSTITUTE(SUBSTITUTE(SUBSTITUTE(TEXT(C49,"#.##0"),",","*"),".",","),"*","."),"-",""),")"),IF(C49=0," -",SUBSTITUTE(SUBSTITUTE(SUBSTITUTE(TEXT(C49,"#.##0"),",","*"),".",","),"*","."))) -> 3,199 | N49: =IF(D49<0,CONCATENATE("(",SUBSTITUTE(SUBSTITUTE(SUBSTITUTE(SUBSTITUTE(TEXT(D49,"#.##0"),",","*"),".",","),"*","."),"-",""),")"),IF(D49=0," -",SUBSTITUTE(SUBSTITUTE(SUBSTITUTE(TEXT(D49,"#.##0"),",","*"),".",","),"*","."))) -> 2,886 | O49: =IF(E49<0,CONCATENATE("(",SUBSTITUTE(SUBSTITUTE(SUBSTITUTE(SUBSTITUTE(TEXT(E49,"#.##0"),",","*"),".",","),"*","."),"-",""),")"),IF(E49=0," -",SUBSTITUTE(SUBSTITUTE(SUBSTITUTE(TEXT(E49,"#.##0"),",","*"),".",","),"*","."))) -> 977 | P49: =IF(F49<0,CONCATENATE("(",SUBSTITUTE(SUBSTITUTE(SUBSTITUTE(SUBSTITUTE(TEXT(F49,"#.##0"),",","*"),".",","),"*","."),"-",""),")"),IF(F49=0," -",SUBSTITUTE(SUBSTITUTE(SUBSTITUTE(TEXT(F49,"#.##0"),",","*"),".",","),"*","."))) -> 1,557 | Q49: =IF(G49<0,CONCATENATE("(",SUBSTITUTE(SUBSTITUTE(SUBSTITUTE(SUBSTITUTE(TEXT(G49,"#.##0"),",","*"),".",","),"*","."),"-",""),")"),IF(G49=0," -",SUBSTITUTE(SUBSTITUTE(SUBSTITUTE(TEXT(G49,"#.##0"),",","*"),".",","),"*","."))) -> 1,529 | R49: =IF(H49<0,CONCATENATE("(",SUBSTITUTE(SUBSTITUTE(SUBSTITUTE(SUBSTITUTE(TEXT(H49,"#.##0"),",","*"),".",","),"*","."),"-",""),")"),IF(H49=0," -",SUBSTITUTE(SUBSTITUTE(SUBSTITUTE(TEXT(H49,"#.##0"),",","*"),".",","),"*","."))) -> 1,853
B50: Defensivos | C50: =C31*D$68/100 -> 3093.252 | D50: =C31*D$69/100 -> 2790.108 | E50: =D31*D$70/100 -> 877.464 | F50: =E31*D$71/100 -> 530.503 | G50: =F31*7177/100 -> 1299.037 | H50: =G31*7985/100 -> 1644.91 | L50: Crop protection | M50: =IF(C50<0,CONCATENATE("(",SUBSTITUTE(SUBSTITUTE(SUBSTITUTE(SUBSTITUTE(TEXT(C50,"#.##0"),",","*"),".",","),"*","."),"-",""),")"),IF(C50=0," -",SUBSTITUTE(SUBSTITUTE(SUBSTITUTE(TEXT(C50,"#.##0"),",","*"),".",","),"*","."))) -> 3,093 | N50: =IF(D50<0,CONCATENATE("(",SUBSTITUTE(SUBSTITUTE(SUBSTITUTE(SUBSTITUTE(TEXT(D50,"#.##0"),",","*"),".",","),"*","."),"-",""),")"),IF(D50=0," -",SUBSTITUTE(SUBSTITUTE(SUBSTITUTE(TEXT(D50,"#.##0"),",","*"),".",","),"*","."))) -> 2,790 | O50: =IF(E50<0,CONCATENATE("(",SUBSTITUTE(SUBSTITUTE(SUBSTITUTE(SUBSTITUTE(TEXT(E50,"#.##0"),",","*"),".",","),"*","."),"-",""),")"),IF(E50=0," -",SUBSTITUTE(SUBSTITUTE(SUBSTITUTE(TEXT(E50,"#.##0"),",","*"),".",","),"*","."))) -> 877 | P50: =IF(F50<0,CONCATENATE("(",SUBSTITUTE(SUBSTITUTE(SUBSTITUTE(SUBSTITUTE(TEXT(F50,"#.##0"),",","*"),".",","),"*","."),"-",""),")"),IF(F50=0," -",SUBSTITUTE(SUBSTITUTE(SUBSTITUTE(TEXT(F50,"#.##0"),",","*"),".",","),"*","."))) -> 531 | Q50: =IF(G50<0,CONCATENATE("(",SUBSTITUTE(SUBSTITUTE(SUBSTITUTE(SUBSTITUTE(TEXT(G50,"#.##0"),",","*"),".",","),"*","."),"-",""),")"),IF(G50=0," -",SUBSTITUTE(SUBSTITUTE(SUBSTITUTE(TEXT(G50,"#.##0"),",","*"),".",","),"*","."))) -> 1,299 | R50: =IF(H50<0,CONCATENATE("(",SUBSTITUTE(SUBSTITUTE(SUBSTITUTE(SUBSTITUTE(TEXT(H50,"#.##0"),",","*"),".",","),"*","."),"-",""),")"),IF(H50=0," -",SUBSTITUTE(SUBSTITUTE(SUBSTITUTE(TEXT(H50,"#.##0"),",","*"),".",","),"*","."))) -> 1,645
B51: Pulverização Aérea | C51: =C32*D$68/100 -> 348.749 | D51: =C32*D$69/100 -> 314.571 | E51: =D32*D$70/100 -> 73.122 | F51: =E32*D$71/100 -> 77.872 | G51: =F32*7177/100 -> 136.363 | H51: =G32*7985/100 -> 127.76 | L51: Aerial Spraying | M51: =IF(C51<0,CONCATENATE("(",SUBSTITUTE(SUBSTITUTE(SUBSTITUTE(SUBSTITUTE(TEXT(C51,"#.##0"),",","*"),".",","),"*","."),"-",""),")"),IF(C51=0," -",SUBSTITUTE(SUBSTITUTE(SUBSTITUTE(TEXT(C51,"#.##0"),",","*"),".",","),"*","."))) -> 349 | N51: =IF(D51<0,CONCATENATE("(",SUBSTITUTE(SUBSTITUTE(SUBSTITUTE(SUBSTITUTE(TEXT(D51,"#.##0"),",","*"),".",","),"*","."),"-",""),")"),IF(D51=0," -",SUBSTITUTE(SUBSTITUTE(SUBSTITUTE(TEXT(D51,"#.##0"),",","*"),".",","),"*","."))) -> 315 | O51: =IF(E51<0,CONCATENATE("(",SUBSTITUTE(SUBSTITUTE(SUBSTITUTE(SUBSTITUTE(TEXT(E51,"#.##0"),",","*"),".",","),"*","."),"-",""),")"),IF(E51=0," -",SUBSTITUTE(SUBSTITUTE(SUBSTITUTE(TEXT(E51,"#.##0"),",","*"),".",","),"*","."))) -> 73 | P51: =IF(F51<0,CONCATENATE("(",SUBSTITUTE(SUBSTITUTE(SUBSTITUTE(SUBSTITUTE(TEXT(F51,"#.##0"),",","*"),".",","),"*","."),"-",""),")"),IF(F51=0," -",SUBSTITUTE(SUBSTITUTE(SUBSTITUTE(TEXT(F51,"#.##0"),",","*"),".",","),"*","."))) -> 78 | Q51: =IF(G51<0,CONCATENATE("(",SUBSTITUTE(SUBSTITUTE(SUBSTITUTE(SUBSTITUTE(TEXT(G51,"#.##0"),",","*"),".",","),"*","."),"-",""),")"),IF(G51=0," -",SUBSTITUTE(SUBSTITUTE(SUBSTITUTE(TEXT(G51,"#.##0"),",","*"),".",","),"*","."))) -> 136 | R51: =IF(H51<0,CONCATENATE("(",SUBSTITUTE(SUBSTITUTE(SUBSTITUTE(SUBSTITUTE(TEXT(H51,"#.##0"),",","*"),".",","),"*","."),"-",""),")"),IF(H51=0," -",SUBSTITUTE(SUBSTITUTE(SUBSTITUTE(TEXT(H51,"#.##0"),",","*"),".",","),"*","."))) -> 128
B52: Combustíveis e lubrificantes | C52: =C33*D$68/100 -> 515.542 | D52: =C33*D$69/100 -> 465.018 | E52: =D33*D$70/100 -> 182.805 | F52: =E33*D$71/100 -> 175.212 | G52: =F33*7177/100 -> 251.195 | H52: =G33*7985/100 -> 343.355 | L52: Fuels and lubrificants | M52: =IF(C52<0,CONCATENATE("(",SUBSTITUTE(SUBSTITUTE(SUBSTITUTE(SUBSTITUTE(TEXT(C52,"#.##0"),",","*"),".",","),"*","."),"-",""),")"),IF(C52=0," -",SUBSTITUTE(SUBSTITUTE(SUBSTITUTE(TEXT(C52,"#.##0"),",","*"),".",","),"*","."))) -> 516 | N52: =IF(D52<0,CONCATENATE("(",SUBSTITUTE(SUBSTITUTE(SUBSTITUTE(SUBSTITUTE(TEXT(D52,"#.##0"),",","*"),".",","),"*","."),"-",""),")"),IF(D52=0," -",SUBSTITUTE(SUBSTITUTE(SUBSTITUTE(TEXT(D52,"#.##0"),",","*"),".",","),"*","."))) -> 465 | O52: =IF(E52<0,CONCATENATE("(",SUBSTITUTE(SUBSTITUTE(SUBSTITUTE(SUBSTITUTE(TEXT(E52,"#.##0"),",","*"),".",","),"*","."),"-",""),")"),IF(E52=0," -",SUBSTITUTE(SUBSTITUTE(SUBSTITUTE(TEXT(E52,"#.##0"),",","*"),".",","),"*","."))) -> 183 | P52: =IF(F52<0,CONCATENATE("(",SUBSTITUTE(SUBSTITUTE(SUBSTITUTE(SUBSTITUTE(TEXT(F52,"#.##0"),",","*"),".",","),"*","."),"-",""),")"),IF(F52=0," -",SUBSTITUTE(SUBSTITUTE(SUBSTITUTE(TEXT(F52,"#.##0"),",","*"),".",","),"*","."))) -> 175 | Q52: =IF(G52<0,CONCATENATE("(",SUBSTITUTE(SUBSTITUTE(SUBSTITUTE(SUBSTITUTE(TEXT(G52,"#.##0"),",","*"),".",","),"*","."),"-",""),")"),IF(G52=0," -",SUBSTITUTE(SUBSTITUTE(SUBSTITUTE(TEXT(G52,"#.##0"),",","*"),".",","),"*","."))) -> 251 | R52: =IF(H52<0,CONCATENATE("(",SUBSTITUTE(SUBSTITUTE(SUBSTITUTE(SUBSTITUTE(TEXT(H52,"#.##0"),",","*"),".",","),"*","."),"-",""),")"),IF(H52=0," -",SUBSTITUTE(SUBSTITUTE(SUBSTITUTE(TEXT(H52,"#.##0"),",","*"),".",","),"*","."))) -> 343
B53: Mão-de-obra | C53: =C34*D$68/100 -> 136.467 | D53: =C34*D$69/100 -> 123.093 | E53: =D34*D$70/100 -> 36.561 | F53: =E34*D$71/100 -> 29.202 | G53: =F34*7177/100 -> 57.416 | H53: =G34*7985/100 -> 47.91 | L53: Labor | M53: =IF(C53<0,CONCATENATE("(",SUBSTITUTE(SUBSTITUTE(SUBSTITUTE(SUBSTITUTE(TEXT(C53,"#.##0"),",","*"),".",","),"*","."),"-",""),")"),IF(C53=0," -",SUBSTITUTE(SUBSTITUTE(SUBSTITUTE(TEXT(C53,"#.##0"),",","*"),".",","),"*","."))) -> 136 | N53: =IF(D53<0,CONCATENATE("(",SUBSTITUTE(SUBSTITUTE(SUBSTITUTE(SUBSTITUTE(TEXT(D53,"#.##0"),",","*"),".",","),"*","."),"-",""),")"),IF(D53=0," -",SUBSTITUTE(SUBSTITUTE(SUBSTITUTE(TEXT(D53,"#.##0"),",","*"),".",","),"*","."))) -> 123 | O53: =IF(E53<0,CONCATENATE("(",SUBSTITUTE(SUBSTITUTE(SUBSTITUTE(SUBSTITUTE(TEXT(E53,"#.##0"),",","*"),".",","),"*","."),"-",""),")"),IF(E53=0," -",SUBSTITUTE(SUBSTITUTE(SUBSTITUTE(TEXT(E53,"#.##0"),",","*"),".",","),"*","."))) -> 37 | P53: =IF(F53<0,CONCATENATE("(",SUBSTITUTE(SUBSTITUTE(SUBSTITUTE(SUBSTITUTE(TEXT(F53,"#.##0"),",","*"),".",","),"*","."),"-",""),")"),IF(F53=0," -",SUBSTITUTE(SUBSTITUTE(SUBSTITUTE(TEXT(F53,"#.##0"),",","*"),".",","),"*","."))) -> 29 | Q53: =IF(G53<0,CONCATENATE("(",SUBSTITUTE(SUBSTITUTE(SUBSTITUTE(SUBSTITUTE(TEXT(G53,"#.##0"),",","*"),".",","),"*","."),"-",""),")"),IF(G53=0," -",SUBSTITUTE(SUBSTITUTE(SUBSTITUTE(TEXT(G53,"#.##0"),",","*"),".",","),"*","."))) -> 57 | R53: =IF(H53<0,CONCATENATE("(",SUBSTITUTE(SUBSTITUTE(SUBSTITUTE(SUBSTITUTE(TEXT(H53,"#.##0"),",","*"),".",","),"*","."),"-",""),")"),IF(H53=0," -",SUBSTITUTE(SUBSTITUTE(SUBSTITUTE(TEXT(H53,"#.##0"),",","*"),".",","),"*","."))) -> 48
B54: Beneficiamento | C54: =C35*D$68/100 -> 1470.811 | D54: =C35*D$69/100 -> 1326.669 | E54: =D35*D$70/100 -> 156.69 | F54: =E35*D$71/100 -> 116.808 | G54: =F35*7177/100 -> 459.328 | H54: =G35*7985/100 -> 503.055 | L54: Ginning | M54: =IF(C54<0,CONCATENATE("(",SUBSTITUTE(SUBSTITUTE(SUBSTITUTE(SUBSTITUTE(TEXT(C54,"#.##0"),",","*"),".",","),"*","."),"-",""),")"),IF(C54=0," -",SUBSTITUTE(SUBSTITUTE(SUBSTITUTE(TEXT(C54,"#.##0"),",","*"),".",","),"*","."))) -> 1,471 | N54: =IF(D54<0,CONCATENATE("(",SUBSTITUTE(SUBSTITUTE(SUBSTITUTE(SUBSTITUTE(TEXT(D54,"#.##0"),",","*"),".",","),"*","."),"-",""),")"),IF(D54=0," -",SUBSTITUTE(SUBSTITUTE(SUBSTITUTE(TEXT(D54,"#.##0"),",","*"),".",","),"*","."))) -> 1,327 | O54: =IF(E54<0,CONCATENATE("(",SUBSTITUTE(SUBSTITUTE(SUBSTITUTE(SUBSTITUTE(TEXT(E54,"#.##0"),",","*"),".",","),"*","."),"-",""),")"),IF(E54=0," -",SUBSTITUTE(SUBSTITUTE(SUBSTITUTE(TEXT(E54,"#.##0"),",","*"),".",","),"*","."))) -> 157 | P54: =IF(F54<0,CONCATENATE("(",SUBSTITUTE(SUBSTITUTE(SUBSTITUTE(SUBSTITUTE(TEXT(F54,"#.##0"),",","*"),".",","),"*","."),"-",""),")"),IF(F54=0," -",SUBSTITUTE(SUBSTITUTE(SUBSTITUTE(TEXT(F54,"#.##0"),",","*"),".",","),"*","."))) -> 117 | Q54: =IF(G54<0,CONCATENATE("(",SUBSTITUTE(SUBSTITUTE(SUBSTITUTE(SUBSTITUTE(TEXT(G54,"#.##0"),",","*"),".",","),"*","."),"-",""),")"),IF(G54=0," -",SUBSTITUTE(SUBSTITUTE(SUBSTITUTE(TEXT(G54,"#.##0"),",","*"),".",","),"*","."))) -> 459 | R54: =IF(H54<0,CONCATENATE("(",SUBSTITUTE(SUBSTITUTE(SUBSTITUTE(SUBSTITUTE(TEXT(H54,"#.##0"),",","*"),".",","),"*","."),"-",""),")"),IF(H54=0," -",SUBSTITUTE(SUBSTITUTE(SUBSTITUTE(TEXT(H54,"#.##0"),",","*"),".",","),"*","."))) -> 503
B55: Manutenção de máquinas e implementos | C55: =C36*D$68/100 -> 652.009 | D55: =C36*D$69/100 -> 588.111 | E55: =D36*D$70/100 -> 214.143 | F55: =E36*D$71/100 -> 160.611 | G55: =F36*7177/100 -> 294.257 | H55: =G36*7985/100 -> 319.4 | L55: Maintenance of machines and implements | M55: =IF(C55<0,CONCATENATE("(",SUBSTITUTE(SUBSTITUTE(SUBSTITUTE(SUBSTITUTE(TEXT(C55,"#.##0"),",","*"),".",","),"*","."),"-",""),")"),IF(C55=0," -",SUBSTITUTE(SUBSTITUTE(SUBSTITUTE(TEXT(C55,"#.##0"),",","*"),".",","),"*","."))) -> 652 | N55: =IF(D55<0,CONCATENATE("(",SUBSTITUTE(SUBSTITUTE(SUBSTITUTE(SUBSTITUTE(TEXT(D55,"#.##0"),",","*"),".",","),"*","."),"-",""),")"),IF(D55=0," -",SUBSTITUTE(SUBSTITUTE(SUBSTITUTE(TEXT(D55,"#.##0"),",","*"),".",","),"*","."))) -> 588 | O55: =IF(E55<0,CONCATENATE("(",SUBSTITUTE(SUBSTITUTE(SUBSTITUTE(SUBSTITUTE(TEXT(E55,"#.##0"),",","*"),".",","),"*","."),"-",""),")"),IF(E55=0," -",SUBSTITUTE(SUBSTITUTE(SUBSTITUTE(TEXT(E55,"#.##0"),",","*"),".",","),"*","."))) -> 214 | P55: =IF(F55<0,CONCATENATE("(",SUBSTITUTE(SUBSTITUTE(SUBSTITUTE(SUBSTITUTE(TEXT(F55,"#.##0"),",","*"),".",","),"*","."),"-",""),")"),IF(F55=0," -",SUBSTITUTE(SUBSTITUTE(SUBSTITUTE(TEXT(F55,"#.##0"),",","*"),".",","),"*","."))) -> 161 | Q55: =IF(G55<0,CONCATENATE("(",SUBSTITUTE(SUBSTITUTE(SUBSTITUTE(SUBSTITUTE(TEXT(G55,"#.##0"),",","*"),".",","),"*","."),"-",""),")"),IF(G55=0," -",SUBSTITUTE(SUBSTITUTE(SUBSTITUTE(TEXT(G55,"#.##0"),",","*"),".",","),"*","."))) -> 294 | R55: =IF(H55<0,CONCATENATE("(",SUBSTITUTE(SUBSTITUTE(SUBSTITUTE(SUBSTITUTE(TEXT(H55,"#.##0"),",","*"),".",","),"*","."),"-",""),")"),IF(H55=0," -",SUBSTITUTE(SUBSTITUTE(SUBSTITUTE(TEXT(H55,"#.##0"),",","*"),".",","),"*","."))) -> 319
B56: Outros | C56: =C37*D$68/100 -> 1122.062 | D56: =C37*D$69/100 -> 1012.098 | E56: =D37*D$70/100 -> 595.422 | F56: =E37*D$71/100 -> 194.68 | G56: =F37*7177/100 -> 610.045 | H56: =G37*7985/100 -> 646.785 | L56: Others | M56: =IF(C56<0,CONCATENATE("(",SUBSTITUTE(SUBSTITUTE(SUBSTITUTE(SUBSTITUTE(TEXT(C56,"#.##0"),",","*"),".",","),"*","."),"-",""),")"),IF(C56=0," -",SUBSTITUTE(SUBSTITUTE(SUBSTITUTE(TEXT(C56,"#.##0"),",","*"),".",","),"*","."))) -> 1,122 | N56: =IF(D56<0,CONCATENATE("(",SUBSTITUTE(SUBSTITUTE(SUBSTITUTE(SUBSTITUTE(TEXT(D56,"#.##0"),",","*"),".",","),"*","."),"-",""),")"),IF(D56=0," -",SUBSTITUTE(SUBSTITUTE(SUBSTITUTE(TEXT(D56,"#.##0"),",","*"),".",","),"*","."))) -> 1,012 | O56: =IF(E56<0,CONCATENATE("(",SUBSTITUTE(SUBSTITUTE(SUBSTITUTE(SUBSTITUTE(TEXT(E56,"#.##0"),",","*"),".",","),"*","."),"-",""),")"),IF(E56=0," -",SUBSTITUTE(SUBSTITUTE(SUBSTITUTE(TEXT(E56,"#.##0"),",","*"),".",","),"*","."))) -> 595 | P56: =IF(F56<0,CONCATENATE("(",SUBSTITUTE(SUBSTITUTE(SUBSTITUTE(SUBSTITUTE(TEXT(F56,"#.##0"),",","*"),".",","),"*","."),"-",""),")"),IF(F56=0," -",SUBSTITUTE(SUBSTITUTE(SUBSTITUTE(TEXT(F56,"#.##0"),",","*"),".",","),"*","."))) -> 195 | Q56: =IF(G56<0,CONCATENATE("(",SUBSTITUTE(SUBSTITUTE(SUBSTITUTE(SUBSTITUTE(TEXT(G56,"#.##0"),",","*"),".",","),"*","."),"-",""),")"),IF(G56=0," -",SUBSTITUTE(SUBSTITUTE(SUBSTITUTE(TEXT(G56,"#.##0"),",","*"),".",","),"*","."))) -> 610 | R56: =IF(H56<0,CONCATENATE("(",SUBSTITUTE(SUBSTITUTE(SUBSTITUTE(SUBSTITUTE(TEXT(H56,"#.##0"),",","*"),".",","),"*","."),"-",""),")"),IF(H56=0," -",SUBSTITUTE(SUBSTITUTE(SUBSTITUTE(TEXT(H56,"#.##0"),",","*"),".",","),"*","."))) -> 647
B57: Custos Fixos | C57: =SUM(C58:C61) -> 3093.252 | D57: =SUM(D58:D61) -> 2790.108 | E57: =SUM(E58:E61) -> 1316.196 | F57: =SUM(F58:F61) -> 860.6 | G57: =F38*7177/100 -> 1593.294 | H57: =G38*7985/100 -> 1612.97 | L57: Fixed Costs | M57: =IF(C57<0,CONCATENATE("(",SUBSTITUTE(SUBSTITUTE(SUBSTITUTE(SUBSTITUTE(TEXT(C57,"#.##0"),",","*"),".",","),"*","."),"-",""),")"),IF(C57=0," -",SUBSTITUTE(SUBSTITUTE(SUBSTITUTE(TEXT(C57,"#.##0"),",","*"),".",","),"*","."))) -> 3,093 | N57: =IF(D57<0,CONCATENATE("(",SUBSTITUTE(SUBSTITUTE(SUBSTITUTE(SUBSTITUTE(TEXT(D57,"#.##0"),",","*"),".",","),"*","."),"-",""),")"),IF(D57=0," -",SUBSTITUTE(SUBSTITUTE(SUBSTITUTE(TEXT(D57,"#.##0"),",","*"),".",","),"*","."))) -> 2,790 | O57: =IF(E57<0,CONCATENATE("(",SUBSTITUTE(SUBSTITUTE(SUBSTITUTE(SUBSTITUTE(TEXT(E57,"#.##0"),",","*"),".",","),"*","."),"-",""),")"),IF(E57=0," -",SUBSTITUTE(SUBSTITUTE(SUBSTITUTE(TEXT(E57,"#.##0"),",","*"),".",","),"*","."))) -> 1,316 | P57: =IF(F57<0,CONCATENATE("(",SUBSTITUTE(SUBSTITUTE(SUBSTITUTE(SUBSTITUTE(TEXT(F57,"#.##0"),",","*"),".",","),"*","."),"-",""),")"),IF(F57=0," -",SUBSTITUTE(SUBSTITUTE(SUBSTITUTE(TEXT(F57,"#.##0"),",","*"),".",","),"*","."))) -> 861 | Q57: =IF(G57<0,CONCATENATE("(",SUBSTITUTE(SUBSTITUTE(SUBSTITUTE(SUBSTITUTE(TEXT(G57,"#.##0"),",","*"),".",","),"*","."),"-",""),")"),IF(G57=0," -",SUBSTITUTE(SUBSTITUTE(SUBSTITUTE(TEXT(G57,"#.##0"),",","*"),".",","),"*","."))) -> 1,593 | R57: =IF(H57<0,CONCATENATE("(",SUBSTITUTE(SUBSTITUTE(SUBSTITUTE(SUBSTITUTE(TEXT(H57,"#.##0"),",","*"),".",","),"*","."),"-",""),")"),IF(H57=0," -",SUBSTITUTE(SUBSTITUTE(SUBSTITUTE(TEXT(H57,"#.##0"),",","*"),".",","),"*","."))) -> 1,613
B58: Mão-de-obra | C58: =C39*D$68/100 -> 1091.736 | D58: =C39*D$69/100 -> 984.744 | E58: =D39*D$70/100 -> 423.063 | F58: =E39*E$71/100 -> 275.392 | G58: =F39*7177/100 -> 531.098 | H58: =G39*7985/100 -> 527.01 | L58: Labor | M58: =IF(C58<0,CONCATENATE("(",SUBSTITUTE(SUBSTITUTE(SUBSTITUTE(SUBSTITUTE(TEXT(C58,"#.##0"),",","*"),".",","),"*","."),"-",""),")"),IF(C58=0," -",SUBSTITUTE(SUBSTITUTE(SUBSTITUTE(TEXT(C58,"#.##0"),",","*"),".",","),"*","."))) -> 1,092 | N58: =IF(D58<0,CONCATENATE("(",SUBSTITUTE(SUBSTITUTE(SUBSTITUTE(SUBSTITUTE(TEXT(D58,"#.##0"),",","*"),".",","),"*","."),"-",""),")"),IF(D58=0," -",SUBSTITUTE(SUBSTITUTE(SUBSTITUTE(TEXT(D58,"#.##0"),",","*"),".",","),"*","."))) -> 985 | O58: =IF(E58<0,CONCATENATE("(",SUBSTITUTE(SUBSTITUTE(SUBSTITUTE(SUBSTITUTE(TEXT(E58,"#.##0"),",","*"),".",","),"*","."),"-",""),")"),IF(E58=0," -",SUBSTITUTE(SUBSTITUTE(SUBSTITUTE(TEXT(E58,"#.##0"),",","*"),".",","),"*","."))) -> 423 | P58: =IF(F58<0,CONCATENATE("(",SUBSTITUTE(SUBSTITUTE(SUBSTITUTE(SUBSTITUTE(TEXT(F58,"#.##0"),",","*"),".",","),"*","."),"-",""),")"),IF(F58=0," -",SUBSTITUTE(SUBSTITUTE(SUBSTITUTE(TEXT(F58,"#.##0"),",","*"),".",","),"*","."))) -> 275 | Q58: =IF(G58<0,CONCATENATE("(",SUBSTITUTE(SUBSTITUTE(SUBSTITUTE(SUBSTITUTE(TEXT(G58,"#.##0"),",","*"),".",","),"*","."),"-",""),")"),IF(G58=0," -",SUBSTITUTE(SUBSTITUTE(SUBSTITUTE(TEXT(G58,"#.##0"),",","*"),".",","),"*","."))) -> 531 | R58: =IF(H58<0,CONCATENATE("(",SUBSTITUTE(SUBSTITUTE(SUBSTITUTE(SUBSTITUTE(TEXT(H58,"#.##0"),",","*"),".",","),"*","."),"-",""),")"),IF(H58=0," -",SUBSTITUTE(SUBSTITUTE(SUBSTITUTE(TEXT(H58,"#.##0"),",","*"),".",","),"*","."))) -> 527
B59: Depreciações e amortizações | C59: =C40*D$68/100 -> 697.498 | D59: =C40*D$69/100 -> 629.142 | E59: =D40*D$70/100 -> 339.495 | F59: =E40*E$71/100 -> 197.938 | G59: =F40*7177/100 -> 380.381 | H59: =G40*7985/100 -> 351.34 | L59: Depreciation e amortization | M59: =IF(C59<0,CONCATENATE("(",SUBSTITUTE(SUBSTITUTE(SUBSTITUTE(SUBSTITUTE(TEXT(C59,"#.##0"),",","*"),".",","),"*","."),"-",""),")"),IF(C59=0," -",SUBSTITUTE(SUBSTITUTE(SUBSTITUTE(TEXT(C59,"#.##0"),",","*"),".",","),"*","."))) -> 697 | N59: =IF(D59<0,CONCATENATE("(",SUBSTITUTE(SUBSTITUTE(SUBSTITUTE(SUBSTITUTE(TEXT(D59,"#.##0"),",","*"),".",","),"*","."),"-",""),")"),IF(D59=0," -",SUBSTITUTE(SUBSTITUTE(SUBSTITUTE(TEXT(D59,"#.##0"),",","*"),".",","),"*","."))) -> 629 | O59: =IF(E59<0,CONCATENATE("(",SUBSTITUTE(SUBSTITUTE(SUBSTITUTE(SUBSTITUTE(TEXT(E59,"#.##0"),",","*"),".",","),"*","."),"-",""),")"),IF(E59=0," -",SUBSTITUTE(SUBSTITUTE(SUBSTITUTE(TEXT(E59,"#.##0"),",","*"),".",","),"*","."))) -> 339 | P59: =IF(F59<0,CONCATENATE("(",SUBSTITUTE(SUBSTITUTE(SUBSTITUTE(SUBSTITUTE(TEXT(F59,"#.##0"),",","*"),".",","),"*","."),"-",""),")"),IF(F59=0," -",SUBSTITUTE(SUBSTITUTE(SUBSTITUTE(TEXT(F59,"#.##0"),",","*"),".",","),"*","."))) -> 198 | Q59: =IF(G59<0,CONCATENATE("(",SUBSTITUTE(SUBSTITUTE(SUBSTITUTE(SUBSTITUTE(TEXT(G59,"#.##0"),",","*"),".",","),"*","."),"-",""),")"),IF(G59=0," -",SUBSTITUTE(SUBSTITUTE(SUBSTITUTE(TEXT(G59,"#.##0"),",","*"),".",","),"*","."))) -> 380 | R59: =IF(H59<0,CONCATENATE("(",SUBSTITUTE(SUBSTITUTE(SUBSTITUTE(SUBSTITUTE(TEXT(H59,"#.##0"),",","*"),".",","),"*","."),"-",""),")"),IF(H59=0," -",SUBSTITUTE(SUBSTITUTE(SUBSTITUTE(TEXT(H59,"#.##0"),",","*"),".",","),"*","."))) -> 351
B60: Amortização do Direito de Uso -Arrendamentos | C60: =C41*D$68/100 -> 879.454 | D60: =C41*D$69/100 -> 793.266 | E60: =D41*D$70/100 -> 376.056 | F60: =E41*E$71/100 -> 271.089 | G60: =F41*7177/100 -> 459.328 | H60: =G41*7985/100 -> 511.04 | L60: Right-of-Use Amortization - Leasing | M60: =IF(C60<0,CONCATENATE("(",SUBSTITUTE(SUBSTITUTE(SUBSTITUTE(SUBSTITUTE(TEXT(C60,"#.##0"),",","*"),".",","),"*","."),"-",""),")"),IF(C60=0," -",SUBSTITUTE(SUBSTITUTE(SUBSTITUTE(TEXT(C60,"#.##0"),",","*"),".",","),"*","."))) -> 879 | N60: =IF(D60<0,CONCATENATE("(",SUBSTITUTE(SUBSTITUTE(SUBSTITUTE(SUBSTITUTE(TEXT(D60,"#.##0"),",","*"),".",","),"*","."),"-",""),")"),IF(D60=0," -",SUBSTITUTE(SUBSTITUTE(SUBSTITUTE(TEXT(D60,"#.##0"),",","*"),".",","),"*","."))) -> 793 | O60: =IF(E60<0,CONCATENATE("(",SUBSTITUTE(SUBSTITUTE(SUBSTITUTE(SUBSTITUTE(TEXT(E60,"#.##0"),",","*"),".",","),"*","."),"-",""),")"),IF(E60=0," -",SUBSTITUTE(SUBSTITUTE(SUBSTITUTE(TEXT(E60,"#.##0"),",","*"),".",","),"*","."))) -> 376 | P60: =IF(F60<0,CONCATENATE("(",SUBSTITUTE(SUBSTITUTE(SUBSTITUTE(SUBSTITUTE(TEXT(F60,"#.##0"),",","*"),".",","),"*","."),"-",""),")"),IF(F60=0," -",SUBSTITUTE(SUBSTITUTE(SUBSTITUTE(TEXT(F60,"#.##0"),",","*"),".",","),"*","."))) -> 271 | Q60: =IF(G60<0,CONCATENATE("(",SUBSTITUTE(SUBSTITUTE(SUBSTITUTE(SUBSTITUTE(TEXT(G60,"#.##0"),",","*"),".",","),"*","."),"-",""),")"),IF(G60=0," -",SUBSTITUTE(SUBSTITUTE(SUBSTITUTE(TEXT(G60,"#.##0"),",","*"),".",","),"*","."))) -> 459 | R60: =IF(H60<0,CONCATENATE("(",SUBSTITUTE(SUBSTITUTE(SUBSTITUTE(SUBSTITUTE(TEXT(H60,"#.##0"),",","*"),".",","),"*","."),"-",""),")"),IF(H60=0," -",SUBSTITUTE(SUBSTITUTE(SUBSTITUTE(TEXT(H60,"#.##0"),",","*"),".",","),"*","."))) -> 511
B61: Outros | C61: =C42*D$68/100 -> 424.564 | D61: =C42*D$69/100 -> 382.956 | E61: =D42*D$70/100 -> 177.582 | F61: =E42*E$71/100 -> 116.181 | G61: =F42*7177/100 -> 222.487 | H61: =G42*7985/100 -> 223.58 | L61: Others | M61: =IF(C61<0,CONCATENATE("(",SUBSTITUTE(SUBSTITUTE(SUBSTITUTE(SUBSTITUTE(TEXT(C61,"#.##0"),",","*"),".",","),"*","."),"-",""),")"),IF(C61=0," -",SUBSTITUTE(SUBSTITUTE(SUBSTITUTE(TEXT(C61,"#.##0"),",","*"),".",","),"*","."))) -> 425 | N61: =IF(D61<0,CONCATENATE("(",SUBSTITUTE(SUBSTITUTE(SUBSTITUTE(SUBSTITUTE(TEXT(D61,"#.##0"),",","*"),".",","),"*","."),"-",""),")"),IF(D61=0," -",SUBSTITUTE(SUBSTITUTE(SUBSTITUTE(TEXT(D61,"#.##0"),",","*"),".",","),"*","."))) -> 383 | O61: =IF(E61<0,CONCATENATE("(",SUBSTITUTE(SUBSTITUTE(SUBSTITUTE(SUBSTITUTE(TEXT(E61,"#.##0"),",","*"),".",","),"*","."),"-",""),")"),IF(E61=0," -",SUBSTITUTE(SUBSTITUTE(SUBSTITUTE(TEXT(E61,"#.##0"),",","*"),".",","),"*","."))) -> 178 | P61: =IF(F61<0,CONCATENATE("(",SUBSTITUTE(SUBSTITUTE(SUBSTITUTE(SUBSTITUTE(TEXT(F61,"#.##0"),",","*"),".",","),"*","."),"-",""),")"),IF(F61=0," -",SUBSTITUTE(SUBSTITUTE(SUBSTITUTE(TEXT(F61,"#.##0"),",","*"),".",","),"*","."))) -> 116 | Q61: =IF(G61<0,CONCATENATE("(",SUBSTITUTE(SUBSTITUTE(SUBSTITUTE(SUBSTITUTE(TEXT(G61,"#.##0"),",","*"),".",","),"*","."),"-",""),")"),IF(G61=0," -",SUBSTITUTE(SUBSTITUTE(SUBSTITUTE(TEXT(G61,"#.##0"),",","*"),".",","),"*","."))) -> 222 | R61: =IF(H61<0,CONCATENATE("(",SUBSTITUTE(SUBSTITUTE(SUBSTITUTE(SUBSTITUTE(TEXT(H61,"#.##0"),",","*"),".",","),"*","."),"-",""),")"),IF(H61=0," -",SUBSTITUTE(SUBSTITUTE(SUBSTITUTE(TEXT(H61,"#.##0"),",","*"),".",","),"*","."))) -> 224
B62: Total | C62: =C57+C47 -> 15163 | D62: =D57+D47 -> 13677 | E62: =E57+E47 -> 5223 | F62: =F57+F47 -> 4749.333 | G62: =G57+G47 -> 7177 | H62: =H57+H47 -> 7985 | L62: Total | M62: =IF(C62<0,CONCATENATE("(",SUBSTITUTE(SUBSTITUTE(SUBSTITUTE(SUBSTITUTE(TEXT(C62,"#.##0"),",","*"),".",","),"*","."),"-",""),")"),IF(C62=0," -",SUBSTITUTE(SUBSTITUTE(SUBSTITUTE(TEXT(C62,"#.##0"),",","*"),".",","),"*","."))) -> 15,163 | N62: =IF(D62<0,CONCATENATE("(",SUBSTITUTE(SUBSTITUTE(SUBSTITUTE(SUBSTITUTE(TEXT(D62,"#.##0"),",","*"),".",","),"*","."),"-",""),")"),IF(D62=0," -",SUBSTITUTE(SUBSTITUTE(SUBSTITUTE(TEXT(D62,"#.##0"),",","*"),".",","),"*","."))) -> 13,677 | O62: =IF(E62<0,CONCATENATE("(",SUBSTITUTE(SUBSTITUTE(SUBSTITUTE(SUBSTITUTE(TEXT(E62,"#.##0"),",","*"),".",","),"*","."),"-",""),")"),IF(E62=0," -",SUBSTITUTE(SUBSTITUTE(SUBSTITUTE(TEXT(E62,"#.##0"),",","*"),".",","),"*","."))) -> 5,223 | P62: =IF(F62<0,CONCATENATE("(",SUBSTITUTE(SUBSTITUTE(SUBSTITUTE(SUBSTITUTE(TEXT(F62,"#.##0"),",","*"),".",","),"*","."),"-",""),")"),IF(F62=0," -",SUBSTITUTE(SUBSTITUTE(SUBSTITUTE(TEXT(F62,"#.##0"),",","*"),".",","),"*","."))) -> 4,749 | Q62: =IF(G62<0,CONCATENATE("(",SUBSTITUTE(SUBSTITUTE(SUBSTITUTE(SUBSTITUTE(TEXT(G62,"#.##0"),",","*"),".",","),"*","."),"-",""),")"),IF(G62=0," -",SUBSTITUTE(SUBSTITUTE(SUBSTITUTE(TEXT(G62,"#.##0"),",","*"),".",","),"*","."))) -> 7,177 | R62: =IF(H62<0,CONCATENATE("(",SUBSTITUTE(SUBSTITUTE(SUBSTITUTE(SUBSTITUTE(TEXT(H62,"#.##0"),",","*"),".",","),"*","."),"-",""),")"),IF(H62=0," -",SUBSTITUTE(SUBSTITUTE(SUBSTITUTE(TEXT(H62,"#.##0"),",","*"),".",","),"*","."))) -> 7,985
B66: Tabela 4 - Custo de Produção em R$/ha Safra 2023/24 | L66: Table 4 - Production Cost in R$/hectare, 2023/24 Crop Year
B67: Total (R$/ha) | D67: Orçado 2022/23 | E67: Orçado 2023/24 (1) | F67: ∆% | L67: Total (R$/ha) | N67: Budget 2023/22 | O67: Budget 2023/24 (1) | P67: ∆%
B68: Algodão em pluma 1ª safra | D68: 15163 | E68: 13205 | F68: =E68/D68-1 -> -0.12913012 | L68: Cotton lint 1st crop | N68: =IF(D68<0,CONCATENATE("(",SUBSTITUTE(SUBSTITUTE(SUBSTITUTE(SUBSTITUTE(TEXT(D68,"#.##0"),",","*"),".",","),"*","."),"-",""),")"),IF(D68=0," -",SUBSTITUTE(SUBSTITUTE(SUBSTITUTE(TEXT(D68,"#.##0"),",","*"),".",","),"*","."))) -> 15,163 | O68: =IF(E68<0,CONCATENATE("(",SUBSTITUTE(SUBSTITUTE(SUBSTITUTE(SUBSTITUTE(TEXT(E68,"#.##0"),",","*"),".",","),"*","."),"-",""),")"),IF(E68=0," -",SUBSTITUTE(SUBSTITUTE(SUBSTITUTE(TEXT(E68,"#.##0"),",","*"),".",","),"*","."))) -> 13,205 | P68: =SUBSTITUTE(TEXT(F68,"0,0%"),",",".") -> -12.9%
B69: Algodão em pluma 2ª safra | D69: 13677 | E69: 11906 | F69: =E69/D69-1 -> -0.12948746 | L69: Cotton lint 2nd crop | N69: =IF(D69<0,CONCATENATE("(",SUBSTITUTE(SUBSTITUTE(SUBSTITUTE(SUBSTITUTE(TEXT(D69,"#.##0"),",","*"),".",","),"*","."),"-",""),")"),IF(D69=0," -",SUBSTITUTE(SUBSTITUTE(SUBSTITUTE(TEXT(D69,"#.##0"),",","*"),".",","),"*","."))) -> 13,677 | O69: =IF(E69<0,CONCATENATE("(",SUBSTITUTE(SUBSTITUTE(SUBSTITUTE(SUBSTITUTE(TEXT(E69,"#.##0"),",","*"),".",","),"*","."),"-",""),")"),IF(E69=0," -",SUBSTITUTE(SUBSTITUTE(SUBSTITUTE(TEXT(E69,"#.##0"),",","*"),".",","),"*","."))) -> 11,906 | P69: =SUBSTITUTE(TEXT(F69,"0,0%"),",",".") -> -12.9%
B70: Soja (Comercial + Semente) | D70: 5223 | E70: 5081 | F70: =E70/D70-1 -> -0.02718744 | L70: Soybean (Commercial + Seed) | N70: =IF(D70<0,CONCATENATE("(",SUBSTITUTE(SUBSTITUTE(SUBSTITUTE(SUBSTITUTE(TEXT(D70,"#.##0"),",","*"),".",","),"*","."),"-",""),")"),IF(D70=0," -",SUBSTITUTE(SUBSTITUTE(SUBSTITUTE(TEXT(D70,"#.##0"),",","*"),".",","),"*","."))) -> 5,223 | O70: =IF(E70<0,CONCATENATE("(",SUBSTITUTE(SUBSTITUTE(SUBSTITUTE(SUBSTITUTE(TEXT(E70,"#.##0"),",","*"),".",","),"*","."),"-",""),")"),IF(E70=0," -",SUBSTITUTE(SUBSTITUTE(SUBSTITUTE(TEXT(E70,"#.##0"),",","*"),".",","),"*","."))) -> 5,081 | P70: =SUBSTITUTE(TEXT(F70,"0,0%"),",",".") -> -2.7%
B71: Milho 2ª safra | D71: 4867 | E71: 4303 | F71: =E71/D71-1 -> -0.11588247 | L71: Corn 2nd crop | N71: =IF(D71<0,CONCATENATE("(",SUBSTITUTE(SUBSTITUTE(SUBSTITUTE(SUBSTITUTE(TEXT(D71,"#.##0"),",","*"),".",","),"*","."),"-",""),")"),IF(D71=0," -",SUBSTITUTE(SUBSTITUTE(SUBSTITUTE(TEXT(D71,"#.##0"),",","*"),".",","),"*","."))) -> 4,867 | O71: =IF(E71<0,CONCATENATE("(",SUBSTITUTE(SUBSTITUTE(SUBSTITUTE(SUBSTITUTE(TEXT(E71,"#.##0"),",","*"),".",","),"*","."),"-",""),")"),IF(E71=0," -",SUBSTITUTE(SUBSTITUTE(SUBSTITUTE(TEXT(E71,"#.##0"),",","*"),".",","),"*","."))) -> 4,303 | P71: =SUBSTITUTE(TEXT(F71,"0,0%"),",",".") -> -11.6%
B72: Custo médio total | D72: 7.985(2) | E72: 7.177(2) | F72: =7177/7985-1 -> -0.10118973 | L72: Total average cost | N72: =IF(D72<0,CONCATENATE("(",SUBSTITUTE(SUBSTITUTE(SUBSTITUTE(SUBSTITUTE(TEXT(D72,"#.##0"),",","*"),".",","),"*","."),"-",""),")"),IF(D72=0," -",SUBSTITUTE(SUBSTITUTE(SUBSTITUTE(TEXT(D72,"#.##0"),",","*"),".",","),"*","."))) -> 7,985(2) | O72: =IF(E72<0,CONCATENATE("(",SUBSTITUTE(SUBSTITUTE(SUBSTITUTE(SUBSTITUTE(TEXT(E72,"#.##0"),",","*"),".",","),"*","."),"-",""),")"),IF(E72=0," -",SUBSTITUTE(SUBSTITUTE(SUBSTITUTE(TEXT(E72,"#.##0"),",","*"),".",","),"*","."))) -> 7,177(2) | P72: =SUBSTITUTE(TEXT(F72,"0,0%"),",",".") -> -10.1%
B73: (1)Os valores podem sofrer alteração até o final de beneficiamento de algodão e da comercialização de grãos | L73: (1) Values ​​may change until the end of cotton processing and grain sales
B74: (2) Ponderado pelas áreas da safra 2022/23, para evitar alterações oriundas de variações no mix de produtos. | L74: (2) Weighted by areas in the 2021/22 crop year to avoid impacts from changes in the product mix.
B76: Tabela 5 – Custo unitário Safra 2023/24 | L76: Table 5 – Unitary Cost 2023/24 Crop Year
C77: Produtividade | D77: Custo Orçado | E77: Custo | F77: Produtividade | G77: Custo Orçado | H77: Custo | I77: ∆% | M77: Budget Yield (Kg/ha) | N77: Budget Cost (R$/ha) | O77: Budget | P77: Budget Yield (Kg/ha) | Q77: Budget Cost (R$/ha) | R77: Budget | S77: ∆%
C78: Orçada (Kg/ha) | D78: (R$/ha) | E78: Orçado (a) | F78: Orçada (Kg/ha) | G78: (R$/ha) | H78: Orçado (b) | I78: b x a | M78: 2022/23 | N78: 2022/23 | O78: R$/Kg (a) | P78: 2023/24 | Q78: 2023/24 | R78: R$/Kg (b) | S78: b x a
C79: 2022/23 | D79: 2022/23 | E79: (R$/Kg) | F79: 2023/24 | G79: 2023/24 | H79: (R$/Kg) | O79: 2022/23 | R79: 2023/24
E80: 2022/23 | H80: 2023/24
B81: Algodão em pluma 1ª safra | C81: ='Operacoes 22.23'!C79 -> 1927 | D81: ='Operacoes 22.23'!D79 -> 15163 | E81: ='Operacoes 22.23'!E79 -> 7.8687078 | F81: =D19 -> 2020 | G81: =E68 -> 13205 | H81: =G81/F81 -> 6.5371287 | I81: =H81/E81-1 -> -0.16922462 | L81: Cotton lint 1st crop | M81: =IF(C81<0,CONCATENATE("(",SUBSTITUTE(SUBSTITUTE(SUBSTITUTE(SUBSTITUTE(TEXT(C81,"#.##0"),",","*"),".",","),"*","."),"-",""),")"),IF(C81=0," -",SUBSTITUTE(SUBSTITUTE(SUBSTITUTE(TEXT(C81,"#.##0"),",","*"),".",","),"*","."))) -> 1,927 | N81: =IF(D81<0,CONCATENATE("(",SUBSTITUTE(SUBSTITUTE(SUBSTITUTE(SUBSTITUTE(TEXT(D81,"#.##0"),",","*"),".",","),"*","."),"-",""),")"),IF(D81=0," -",SUBSTITUTE(SUBSTITUTE(SUBSTITUTE(TEXT(D81,"#.##0"),",","*"),".",","),"*","."))) -> 15,163 | O81: =E81 -> 7.8687078 | P81: =IF(F81<0,CONCATENATE("(",SUBSTITUTE(SUBSTITUTE(SUBSTITUTE(SUBSTITUTE(TEXT(F81,"#.##0"),",","*"),".",","),"*","."),"-",""),")"),IF(F81=0," -",SUBSTITUTE(SUBSTITUTE(SUBSTITUTE(TEXT(F81,"#.##0"),",","*"),".",","),"*","."))) -> 2,020 | Q81: =IF(G81<0,CONCATENATE("(",SUBSTITUTE(SUBSTITUTE(SUBSTITUTE(SUBSTITUTE(TEXT(G81,"#.##0"),",","*"),".",","),"*","."),"-",""),")"),IF(G81=0," -",SUBSTITUTE(SUBSTITUTE(SUBSTITUTE(TEXT(G81,"#.##0"),",","*"),".",","),"*","."))) -> 13,205 | R81: =H81 -> 6.5371287 | S81: =R81/O81-1 -> -0.16922462
B82: Algodão em pluma 2ª safra | C82: ='Operacoes 22.23'!C80 -> 1839 | D82: ='Operacoes 22.23'!D80 -> 13677 | E82: ='Operacoes 22.23'!E80 -> 7.4371941 | F82: =D20 -> 1869 | G82: =E69 -> 11906 | H82: =G82/F82 -> 6.3702515 | I82: =H82/E82-1 -> -0.14346037 | L82: Cotton lint 2nd crop | M82: =IF(C82<0,CONCATENATE("(",SUBSTITUTE(SUBSTITUTE(SUBSTITUTE(SUBSTITUTE(TEXT(C82,"#.##0"),",","*"),".",","),"*","."),"-",""),")"),IF(C82=0," -",SUBSTITUTE(SUBSTITUTE(SUBSTITUTE(TEXT(C82,"#.##0"),",","*"),".",","),"*","."))) -> 1,839 | N82: =IF(D82<0,CONCATENATE("(",SUBSTITUTE(SUBSTITUTE(SUBSTITUTE(SUBSTITUTE(TEXT(D82,"#.##0"),",","*"),".",","),"*","."),"-",""),")"),IF(D82=0," -",SUBSTITUTE(SUBSTITUTE(SUBSTITUTE(TEXT(D82,"#.##0"),",","*"),".",","),"*","."))) -> 13,677 | O82: =E82 -> 7.4371941 | P82: =IF(F82<0,CONCATENATE("(",SUBSTITUTE(SUBSTITUTE(SUBSTITUTE(SUBSTITUTE(TEXT(F82,"#.##0"),",","*"),".",","),"*","."),"-",""),")"),IF(F82=0," -",SUBSTITUTE(SUBSTITUTE(SUBSTITUTE(TEXT(F82,"#.##0"),",","*"),".",","),"*","."))) -> 1,869 | Q82: =IF(G82<0,CONCATENATE("(",SUBSTITUTE(SUBSTITUTE(SUBSTITUTE(SUBSTITUTE(TEXT(G82,"#.##0"),",","*"),".",","),"*","."),"-",""),")"),IF(G82=0," -",SUBSTITUTE(SUBSTITUTE(SUBSTITUTE(TEXT(G82,"#.##0"),",","*"),".",","),"*","."))) -> 11,906 | R82: =H82 -> 6.3702515 | S82: =R82/O82-1 -> -0.14346037
B83: Soja(1) | C83: ='Operacoes 22.23'!C81 -> 3918 | D83: ='Operacoes 22.23'!D81 -> 5377 | E83: ='Operacoes 22.23'!E81 -> 1.3723839 | F83: =D22 -> 3948 | G83: =E70 -> 5081 | H83: =G83/F83 -> 1.2869807 | I83: =H83/E83-1 -> -0.062229761 | L83: Soybean(1) | M83: =IF(C83<0,CONCATENATE("(",SUBSTITUTE(SUBSTITUTE(SUBSTITUTE(SUBSTITUTE(TEXT(C83,"#.##0"),",","*"),".",","),"*","."),"-",""),")"),IF(C83=0," -",SUBSTITUTE(SUBSTITUTE(SUBSTITUTE(TEXT(C83,"#.##0"),",","*"),".",","),"*","."))) -> 3,918 | N83: =IF(D83<0,CONCATENATE("(",SUBSTITUTE(SUBSTITUTE(SUBSTITUTE(SUBSTITUTE(TEXT(D83,"#.##0"),",","*"),".",","),"*","."),"-",""),")"),IF(D83=0," -",SUBSTITUTE(SUBSTITUTE(SUBSTITUTE(TEXT(D83,"#.##0"),",","*"),".",","),"*","."))) -> 5,377 | O83: =E83 -> 1.3723839 | P83: =IF(F83<0,CONCATENATE("(",SUBSTITUTE(SUBSTITUTE(SUBSTITUTE(SUBSTITUTE(TEXT(F83,"#.##0"),",","*"),".",","),"*","."),"-",""),")"),IF(F83=0," -",SUBSTITUTE(SUBSTITUTE(SUBSTITUTE(TEXT(F83,"#.##0"),",","*"),".",","),"*","."))) -> 3,948 | Q83: =IF(G83<0,CONCATENATE("(",SUBSTITUTE(SUBSTITUTE(SUBSTITUTE(SUBSTITUTE(TEXT(G83,"#.##0"),",","*"),".",","),"*","."),"-",""),")"),IF(G83=0," -",SUBSTITUTE(SUBSTITUTE(SUBSTITUTE(TEXT(G83,"#.##0"),",","*"),".",","),"*","."))) -> 5,081 | R83: =H83 -> 1.2869807 | S83: =R83/O83-1 -> -0.062229761
B84: Milho 2ª safra | C84: ='Operacoes 22.23'!C82 -> 7685 | D84: ='Operacoes 22.23'!D82 -> 4867 | E84: ='Operacoes 22.23'!E82 -> 0.63331165 | F84: =D23 -> 7580 | G84: =E71 -> 4303 | H84: =G84/F84 -> 0.5676781 | I84: =H84/E84-1 -> -0.10363546 | L84: Corn 2nd crop | M84: =IF(C84<0,CONCATENATE("(",SUBSTITUTE(SUBSTITUTE(SUBSTITUTE(SUBSTITUTE(TEXT(C84,"#.##0"),",","*"),".",","),"*","."),"-",""),")"),IF(C84=0," -",SUBSTITUTE(SUBSTITUTE(SUBSTITUTE(TEXT(C84,"#.##0"),",","*"),".",","),"*","."))) -> 7,685 | N84: =IF(D84<0,CONCATENATE("(",SUBSTITUTE(SUBSTITUTE(SUBSTITUTE(SUBSTITUTE(TEXT(D84,"#.##0"),",","*"),".",","),"*","."),"-",""),")"),IF(D84=0," -",SUBSTITUTE(SUBSTITUTE(SUBSTITUTE(TEXT(D84,"#.##0"),",","*"),".",","),"*","."))) -> 4,867 | O84: =E84 -> 0.63331165 | P84: =IF(F84<0,CONCATENATE("(",SUBSTITUTE(SUBSTITUTE(SUBSTITUTE(SUBSTITUTE(TEXT(F84,"#.##0"),",","*"),".",","),"*","."),"-",""),")"),IF(F84=0," -",SUBSTITUTE(SUBSTITUTE(SUBSTITUTE(TEXT(F84,"#.##0"),",","*"),".",","),"*","."))) -> 7,580 | Q84: =IF(G84<0,CONCATENATE("(",SUBSTITUTE(SUBSTITUTE(SUBSTITUTE(SUBSTITUTE(TEXT(G84,"#.##0"),",","*"),".",","),"*","."),"-",""),")"),IF(G84=0," -",SUBSTITUTE(SUBSTITUTE(SUBSTITUTE(TEXT(G84,"#.##0"),",","*"),".",","),"*","."))) -> 4,303 | R84: =H84 -> 0.5676781 | S84: =R84/O84-1 -> -0.10363546
B85: (1) Inclusos os custos com produção de sementes. | L85: (1) Including seed production costs
B87: Tabela – Parque de máquinas e Capacidade de Armazenagem | L87: Table –Machinery Base and Storage Capacity
C88: 2021 | D88: 2022 | E88: 3T23 | F88: 4T23(1) | M88: 2021 | N88: 2022 | O88: 3Q23 | P88: 4Q23(1)
B89: Maquinário (quantidade) | C89: 1.173 | D89: 1.195 | E89: 1194 | F89: =SUM(F90:F94) -> 1192 | L89: Machinery (quantity) | M89: =IF(C89<0,CONCATENATE("(",SUBSTITUTE(SUBSTITUTE(SUBSTITUTE(SUBSTITUTE(TEXT(C89,"#.##0"),",","*"),".",","),"*","."),"-",""),")"),IF(C89=0," -",SUBSTITUTE(SUBSTITUTE(SUBSTITUTE(TEXT(C89,"#.##0"),",","*"),".",","),"*","."))) -> 1,173 | N89: =IF(D89<0,CONCATENATE("(",SUBSTITUTE(SUBSTITUTE(SUBSTITUTE(SUBSTITUTE(TEXT(D89,"#.##0"),",","*"),".",","),"*","."),"-",""),")"),IF(D89=0," -",SUBSTITUTE(SUBSTITUTE(SUBSTITUTE(TEXT(D89,"#.##0"),",","*"),".",","),"*","."))) -> 1,195 | O89: =IF(E89<0,CONCATENATE("(",SUBSTITUTE(SUBSTITUTE(SUBSTITUTE(SUBSTITUTE(TEXT(E89,"#.##0"),",","*"),".",","),"*","."),"-",""),")"),IF(E89=0," -",SUBSTITUTE(SUBSTITUTE(SUBSTITUTE(TEXT(E89,"#.##0"),",","*"),".",","),"*","."))) -> 1,194 | P89: =IF(F89<0,CONCATENATE("(",SUBSTITUTE(SUBSTITUTE(SUBSTITUTE(SUBSTITUTE(TEXT(F89,"#.##0"),",","*"),".",","),"*","."),"-",""),")"),IF(F89=0," -",SUBSTITUTE(SUBSTITUTE(SUBSTITUTE(TEXT(F89,"#.##0"),",","*"),".",","),"*","."))) -> 1,192
B90: Tratores | C90: 350 | D90: 338 | E90: 330 | F90: 329 | L90: Tractors | M90: =IF(C90<0,CONCATENATE("(",SUBSTITUTE(SUBSTITUTE(SUBSTITUTE(SUBSTITUTE(TEXT(C90,"#.##0"),",","*"),".",","),"*","."),"-",""),")"),IF(C90=0," -",SUBSTITUTE(SUBSTITUTE(SUBSTITUTE(TEXT(C90,"#.##0"),",","*"),".",","),"*","."))) -> 350 | N90: =IF(D90<0,CONCATENATE("(",SUBSTITUTE(SUBSTITUTE(SUBSTITUTE(SUBSTITUTE(TEXT(D90,"#.##0"),",","*"),".",","),"*","."),"-",""),")"),IF(D90=0," -",SUBSTITUTE(SUBSTITUTE(SUBSTITUTE(TEXT(D90,"#.##0"),",","*"),".",","),"*","."))) -> 338 | O90: =IF(E90<0,CONCATENATE("(",SUBSTITUTE(SUBSTITUTE(SUBSTITUTE(SUBSTITUTE(TEXT(E90,"#.##0"),",","*"),".",","),"*","."),"-",""),")"),IF(E90=0," -",SUBSTITUTE(SUBSTITUTE(SUBSTITUTE(TEXT(E90,"#.##0"),",","*"),".",","),"*","."))) -> 330 | P90: =IF(F90<0,CONCATENATE("(",SUBSTITUTE(SUBSTITUTE(SUBSTITUTE(SUBSTITUTE(TEXT(F90,"#.##0"),",","*"),".",","),"*","."),"-",""),")"),IF(F90=0," -",SUBSTITUTE(SUBSTITUTE(SUBSTITUTE(TEXT(F90,"#.##0"),",","*"),".",","),"*","."))) -> 329
B91: Colheitadeiras de grãos | C91: 217 | D91: 254 | E91: 258 | F91: 258 | L91: Grains Combiners | M91: =IF(C91<0,CONCATENATE("(",SUBSTITUTE(SUBSTITUTE(SUBSTITUTE(SUBSTITUTE(TEXT(C91,"#.##0"),",","*"),".",","),"*","."),"-",""),")"),IF(C91=0," -",SUBSTITUTE(SUBSTITUTE(SUBSTITUTE(TEXT(C91,"#.##0"),",","*"),".",","),"*","."))) -> 217 | N91: =IF(D91<0,CONCATENATE("(",SUBSTITUTE(SUBSTITUTE(SUBSTITUTE(SUBSTITUTE(TEXT(D91,"#.##0"),",","*"),".",","),"*","."),"-",""),")"),IF(D91=0," -",SUBSTITUTE(SUBSTITUTE(SUBSTITUTE(TEXT(D91,"#.##0"),",","*"),".",","),"*","."))) -> 254 | O91: =IF(E91<0,CONCATENATE("(",SUBSTITUTE(SUBSTITUTE(SUBSTITUTE(SUBSTITUTE(TEXT(E91,"#.##0"),",","*"),".",","),"*","."),"-",""),")"),IF(E91=0," -",SUBSTITUTE(SUBSTITUTE(SUBSTITUTE(TEXT(E91,"#.##0"),",","*"),".",","),"*","."))) -> 258 | P91: =IF(F91<0,CONCATENATE("(",SUBSTITUTE(SUBSTITUTE(SUBSTITUTE(SUBSTITUTE(TEXT(F91,"#.##0"),",","*"),".",","),"*","."),"-",""),")"),IF(F91=0," -",SUBSTITUTE(SUBSTITUTE(SUBSTITUTE(TEXT(F91,"#.##0"),",","*"),".",","),"*","."))) -> 258
B92: Colheitadeiras de algodão | C92: 103 | D92: 127 | E92: 126 | F92: 126 | L92: Cotton Pickers | M92: =IF(C92<0,CONCATENATE("(",SUBSTITUTE(SUBSTITUTE(SUBSTITUTE(SUBSTITUTE(TEXT(C92,"#.##0"),",","*"),".",","),"*","."),"-",""),")"),IF(C92=0," -",SUBSTITUTE(SUBSTITUTE(SUBSTITUTE(TEXT(C92,"#.##0"),",","*"),".",","),"*","."))) -> 103 | N92: =IF(D92<0,CONCATENATE("(",SUBSTITUTE(SUBSTITUTE(SUBSTITUTE(SUBSTITUTE(TEXT(D92,"#.##0"),",","*"),".",","),"*","."),"-",""),")"),IF(D92=0," -",SUBSTITUTE(SUBSTITUTE(SUBSTITUTE(TEXT(D92,"#.##0"),",","*"),".",","),"*","."))) -> 127 | O92: =IF(E92<0,CONCATENATE("(",SUBSTITUTE(SUBSTITUTE(SUBSTITUTE(SUBSTITUTE(TEXT(E92,"#.##0"),",","*"),".",","),"*","."),"-",""),")"),IF(E92=0," -",SUBSTITUTE(SUBSTITUTE(SUBSTITUTE(TEXT(E92,"#.##0"),",","*"),".",","),"*","."))) -> 126 | P92: =IF(F92<0,CONCATENATE("(",SUBSTITUTE(SUBSTITUTE(SUBSTITUTE(SUBSTITUTE(TEXT(F92,"#.##0"),",","*"),".",","),"*","."),"-",""),")"),IF(F92=0," -",SUBSTITUTE(SUBSTITUTE(SUBSTITUTE(TEXT(F92,"#.##0"),",","*"),".",","),"*","."))) -> 126
B93: Plantadeiras | C93: 297 | D93: 276 | E93: 273 | F93: 272 | L93: Planters | M93: =IF(C93<0,CONCATENATE("(",SUBSTITUTE(SUBSTITUTE(SUBSTITUTE(SUBSTITUTE(TEXT(C93,"#.##0"),",","*"),".",","),"*","."),"-",""),")"),IF(C93=0," -",SUBSTITUTE(SUBSTITUTE(SUBSTITUTE(TEXT(C93,"#.##0"),",","*"),".",","),"*","."))) -> 297 | N93: =IF(D93<0,CONCATENATE("(",SUBSTITUTE(SUBSTITUTE(SUBSTITUTE(SUBSTITUTE(TEXT(D93,"#.##0"),",","*"),".",","),"*","."),"-",""),")"),IF(D93=0," -",SUBSTITUTE(SUBSTITUTE(SUBSTITUTE(TEXT(D93,"#.##0"),",","*"),".",","),"*","."))) -> 276 | O93: =IF(E93<0,CONCATENATE("(",SUBSTITUTE(SUBSTITUTE(SUBSTITUTE(SUBSTITUTE(TEXT(E93,"#.##0"),",","*"),".",","),"*","."),"-",""),")"),IF(E93=0," -",SUBSTITUTE(SUBSTITUTE(SUBSTITUTE(TEXT(E93,"#.##0"),",","*"),".",","),"*","."))) -> 273 | P93: =IF(F93<0,CONCATENATE("(",SUBSTITUTE(SUBSTITUTE(SUBSTITUTE(SUBSTITUTE(TEXT(F93,"#.##0"),",","*"),".",","),"*","."),"-",""),")"),IF(F93=0," -",SUBSTITUTE(SUBSTITUTE(SUBSTITUTE(TEXT(F93,"#.##0"),",","*"),".",","),"*","."))) -> 272
B94: Pulverizadores autopropelidos | C94: 206 | D94: 200 | E94: 207 | F94: 207 | L94: Self propelled sprayers | M94: =IF(C94<0,CONCATENATE("(",SUBSTITUTE(SUBSTITUTE(SUBSTITUTE(SUBSTITUTE(TEXT(C94,"#.##0"),",","*"),".",","),"*","."),"-",""),")"),IF(C94=0," -",SUBSTITUTE(SUBSTITUTE(SUBSTITUTE(TEXT(C94,"#.##0"),",","*"),".",","),"*","."))) -> 206 | N94: =IF(D94<0,CONCATENATE("(",SUBSTITUTE(SUBSTITUTE(SUBSTITUTE(SUBSTITUTE(TEXT(D94,"#.##0"),",","*"),".",","),"*","."),"-",""),")"),IF(D94=0," -",SUBSTITUTE(SUBSTITUTE(SUBSTITUTE(TEXT(D94,"#.##0"),",","*"),".",","),"*","."))) -> 200 | O94: =IF(E94<0,CONCATENATE("(",SUBSTITUTE(SUBSTITUTE(SUBSTITUTE(SUBSTITUTE(TEXT(E94,"#.##0"),",","*"),".",","),"*","."),"-",""),")"),IF(E94=0," -",SUBSTITUTE(SUBSTITUTE(SUBSTITUTE(TEXT(E94,"#.##0"),",","*"),".",","),"*","."))) -> 207 | P94: =IF(F94<0,CONCATENATE("(",SUBSTITUTE(SUBSTITUTE(SUBSTITUTE(SUBSTITUTE(TEXT(F94,"#.##0"),",","*"),".",","),"*","."),"-",""),")"),IF(F94=0," -",SUBSTITUTE(SUBSTITUTE(SUBSTITUTE(TEXT(F94,"#.##0"),",","*"),".",","),"*","."))) -> 207
B95: Capacidade de armazenagem (toneladas) | L95: Storage capacity (tons)
B96: Grãos | C96: 1.054.920 | D96: 1.054.920 | E96: 1058220 | F96: 1028220 | L96: Grains | M96: =IF(C96<0,CONCATENATE("(",SUBSTITUTE(SUBSTITUTE(SUBSTITUTE(SUBSTITUTE(TEXT(C96,"#.##0"),",","*"),".",","),"*","."),"-",""),")"),IF(C96=0," -",SUBSTITUTE(SUBSTITUTE(SUBSTITUTE(TEXT(C96,"#.##0"),",","*"),".",","),"*","."))) -> 1,054,920 | N96: =IF(D96<0,CONCATENATE("(",SUBSTITUTE(SUBSTITUTE(SUBSTITUTE(SUBSTITUTE(TEXT(D96,"#.##0"),",","*"),".",","),"*","."),"-",""),")"),IF(D96=0," -",SUBSTITUTE(SUBSTITUTE(SUBSTITUTE(TEXT(D96,"#.##0"),",","*"),".",","),"*","."))) -> 1,054,920 | O96: =IF(E96<0,CONCATENATE("(",SUBSTITUTE(SUBSTITUTE(SUBSTITUTE(SUBSTITUTE(TEXT(E96,"#.##0"),",","*"),".",","),"*","."),"-",""),")"),IF(E96=0," -",SUBSTITUTE(SUBSTITUTE(SUBSTITUTE(TEXT(E96,"#.##0"),",","*"),".",","),"*","."))) -> 1,058,220 | P96: =IF(F96<0,CONCATENATE("(",SUBSTITUTE(SUBSTITUTE(SUBSTITUTE(SUBSTITUTE(TEXT(F96,"#.##0"),",","*"),".",","),"*","."),"-",""),")"),IF(F96=0," -",SUBSTITUTE(SUBSTITUTE(SUBSTITUTE(TEXT(F96,"#.##0"),",","*"),".",","),"*","."))) -> 1,028,220
B97: % Produção | C97: 61% | D97: 0.43 | E97: 0.5 | F97: 0.56 | L97: % Production | M97: =SUBSTITUTE(TEXT(C97,"0,0%"),",",".") -> 61% | N97: =SUBSTITUTE(TEXT(D97,"0,0%"),",",".") -> 43.0% | O97: =SUBSTITUTE(TEXT(E97,"0,0%"),",",".") -> 50.0% | P97: =SUBSTITUTE(TEXT(F97,"0,0%"),",",".") -> 56.0%
B98: Algodão | C98: 190.447 | D98: 190.447 | E98: 190.447 | F98: 190.447 | L98: Cotton | M98: =IF(C98<0,CONCATENATE("(",SUBSTITUTE(SUBSTITUTE(SUBSTITUTE(SUBSTITUTE(TEXT(C98,"#.##0"),",","*"),".",","),"*","."),"-",""),")"),IF(C98=0," -",SUBSTITUTE(SUBSTITUTE(SUBSTITUTE(TEXT(C98,"#.##0"),",","*"),".",","),"*","."))) -> 190,447 | N98: =IF(D98<0,CONCATENATE("(",SUBSTITUTE(SUBSTITUTE(SUBSTITUTE(SUBSTITUTE(TEXT(D98,"#.##0"),",","*"),".",","),"*","."),"-",""),")"),IF(D98=0," -",SUBSTITUTE(SUBSTITUTE(SUBSTITUTE(TEXT(D98,"#.##0"),",","*"),".",","),"*","."))) -> 190,447 | O98: =IF(E98<0,CONCATENATE("(",SUBSTITUTE(SUBSTITUTE(SUBSTITUTE(SUBSTITUTE(TEXT(E98,"#.##0"),",","*"),".",","),"*","."),"-",""),")"),IF(E98=0," -",SUBSTITUTE(SUBSTITUTE(SUBSTITUTE(TEXT(E98,"#.##0"),",","*"),".",","),"*","."))) -> 190,447 | P98: =IF(F98<0,CONCATENATE("(",SUBSTITUTE(SUBSTITUTE(SUBSTITUTE(SUBSTITUTE(TEXT(F98,"#.##0"),",","*"),".",","),"*","."),"-",""),")"),IF(F98=0," -",SUBSTITUTE(SUBSTITUTE(SUBSTITUTE(TEXT(F98,"#.##0"),",","*"),".",","),"*","."))) -> 190,447
B99: % Produção | C99: 72% | D99: 0.62 | E99: 0.53 | F99: 0.52 | L99: % Production | M99: =SUBSTITUTE(TEXT(C99,"0,0%"),",",".") -> 72% | N99: =SUBSTITUTE(TEXT(D99,"0,0%"),",",".") -> 62.0% | O99: =SUBSTITUTE(TEXT(E99,"0,0%"),",",".") -> 53.0% | P99: =SUBSTITUTE(TEXT(F99,"0,0%"),",",".") -> 52.0%
B100: (1) Estimativa com base na área plantada e produtividade da safra 2023/24 para o 4T23. | L100: (1) Estimate based on the planted area and yield for 2023/24 crop year for 4Q23.
